{
  "workflowConfig": {
    "name": "Circuly Customers Sync",
    "description": "Synchronize customers from Circuly to local database with pagination",
    "version": "2.0.0",
    "workflowType": "predefined",
    "config": {
      "timeout": 300000,
      "retryPolicy": { "maxRetries": 3, "backoffMs": 2000 },
      "variables": {
        "organizationId": "org_demo",
        "pageSize": 50,
        "maxPages": 20,
        "currentPage": 1
      }
    }
  },
  "stepsConfig": [
    {
      "stepSlug": "start",
      "name": "start",
      "stepType": "start",
      "config": {},
      "nextSteps": { "success": "fetch_customers" }
    },
    {
      "stepSlug": "fetch_customers",
      "name": "Fetch Customers from Circuly",
      "stepType": "action",
      "config": {
        "type": "integration",
        "parameters": {
          "name": "circuly",
          "operation": "list_customers",
          "params": {
            "page": "{{currentPage}}",
            "per_page": "{{pageSize}}",
            "sort": "created_at",
            "desc": false
          }
        }
      },
      "nextSteps": { "success": "loop_customers" }
    },
    {
      "stepSlug": "loop_customers",
      "name": "Loop Through Customers",
      "stepType": "loop",
      "config": {
        "items": "{{steps.fetch_customers.output.data.result.data}}",
        "itemVariable": "customer"
      },
      "nextSteps": { "loop": "query_existing_customer", "done": "check_has_next_page" }
    },
    {
      "stepSlug": "query_existing_customer",
      "name": "Query Existing Customer",
      "stepType": "action",
      "config": {
        "type": "customer",
        "parameters": {
          "operation": "query",
          "externalId": "{{loop.item.id}}",
          "paginationOpts": { "numItems": 1, "cursor": null }
        }
      },
      "nextSteps": { "success": "check_customer_exists" }
    },
    {
      "stepSlug": "check_customer_exists",
      "name": "Check Customer Exists",
      "stepType": "condition",
      "config": {
        "expression": "steps.query_existing_customer.output.data.page|length > 0",
        "description": "Check if customer already exists in database"
      },
      "nextSteps": { "true": "update_existing_customer", "false": "insert_new_customer" }
    },
    {
      "stepSlug": "update_existing_customer",
      "name": "Update Existing Customer",
      "stepType": "action",
      "config": {
        "type": "customer",
        "parameters": {
          "operation": "update",
          "customerId": "{{steps.query_existing_customer.output.data.page[0]._id}}",
          "updates": {
            "name": "{{loop.item.first_name}} {{loop.item.last_name}}",
            "email": "{{loop.item.email}}",
            "address": {
              "street": "{{loop.item.address.shipping.street}}",
              "city": "{{loop.item.address.shipping.city}}",
              "country": "{{loop.item.address.shipping.country}}",
              "postalCode": "{{loop.item.address.shipping.postal_code}}"
            },
            "status": "active",
            "source": "circuly",
            "locale": "{{loop.item.default_locale}}",
            "metadata": {
              "circuly": "{{loop.item}}",
              "syncedAt": "{{now}}"
            }
          }
        }
      },
      "nextSteps": { "success": "loop_customers" }
    },
    {
      "stepSlug": "insert_new_customer",
      "name": "Insert New Customer",
      "stepType": "action",
      "config": {
        "type": "customer",
        "parameters": {
          "operation": "create",
          "name": "{{loop.item.first_name}} {{loop.item.last_name}}",
          "email": "{{loop.item.email}}",
          "address": {
            "street": "{{loop.item.address.shipping.street}}",
            "city": "{{loop.item.address.shipping.city}}",
            "country": "{{loop.item.address.shipping.country}}",
            "postalCode": "{{loop.item.address.shipping.postal_code}}"
          },
          "externalId": "{{loop.item.id}}",
          "status": "active",
          "source": "circuly",
          "locale": "{{loop.item.default_locale}}",
          "metadata": {
            "circuly": "{{loop.item}}",
            "syncedAt": "{{now}}"
          }
        }
      },
      "nextSteps": { "success": "loop_customers" }
    },
    {
      "stepSlug": "check_has_next_page",
      "name": "Check Has Next Page",
      "stepType": "condition",
      "config": {
        "expression": "steps.fetch_customers.output.data.result.pagination.hasNextPage == true && currentPage < maxPages",
        "description": "Check if Circuly has more pages and we have not exceeded max page limit"
      },
      "nextSteps": { "true": "prepare_next_page", "false": "noop" }
    },
    {
      "stepSlug": "prepare_next_page",
      "name": "Prepare Next Page",
      "stepType": "action",
      "config": {
        "type": "set_variables",
        "parameters": {
          "variables": [{ "name": "currentPage", "value": "{{currentPage + 1}}" }]
        }
      },
      "nextSteps": { "success": "fetch_customers" }
    }
  ]
}
