[
  {
    "text": "Ez nem lep meg.",
    "source": "tatoeba",
    "upstreamId": "331032"
  },
  {
    "text": "Minden emberi lény szabadon születik és egyenlő méltósága és joga van. Az emberek, ésszel és lelkiismerettel bírván, egymással szemben testvéri szellemben kell hogy viseltessenek.",
    "source": "tatoeba",
    "upstreamId": "382214"
  },
  {
    "text": "Köszönöm szépen!",
    "source": "tatoeba",
    "upstreamId": "401104"
  },
  {
    "text": "Ez tényleg szörnyű.",
    "source": "tatoeba",
    "upstreamId": "406278"
  },
  {
    "text": "Vettem egy táskát.",
    "source": "tatoeba",
    "upstreamId": "406299"
  },
  {
    "text": "Van nálad egy ceruza?",
    "source": "tatoeba",
    "upstreamId": "406303"
  },
  {
    "text": "Ha ő jön, én is megyek.",
    "source": "tatoeba",
    "upstreamId": "408382"
  },
  {
    "text": "Ne állj mindig az ő oldalára!",
    "source": "tatoeba",
    "upstreamId": "408384"
  },
  {
    "text": "Ön nincs bejelentkezve.",
    "source": "tatoeba",
    "upstreamId": "409199"
  },
  {
    "text": "Egy jó szótárat akarok.",
    "source": "tatoeba",
    "upstreamId": "409201"
  },
  {
    "text": "Nem akarok iskolába menni.",
    "source": "tatoeba",
    "upstreamId": "414524"
  },
  {
    "text": "Egyszer teszek az életemben jó dolgot... és teljesen hiába.",
    "source": "tatoeba",
    "upstreamId": "414525"
  },
  {
    "text": "Nem beszélek japánul.",
    "source": "tatoeba",
    "upstreamId": "414526"
  },
  {
    "text": "Mennem kell aludni.",
    "source": "tatoeba",
    "upstreamId": "414529"
  },
  {
    "text": "Jim még mindig nem jött meg?",
    "source": "tatoeba",
    "upstreamId": "414532"
  },
  {
    "text": "Boldog születésnapot, Muiriel!",
    "source": "tatoeba",
    "upstreamId": "414534"
  },
  {
    "text": "Muiriel húsz éves.",
    "source": "tatoeba",
    "upstreamId": "414537"
  },
  {
    "text": "A jelszó: Muiriel.",
    "source": "tatoeba",
    "upstreamId": "414538"
  },
  {
    "text": "Nem találok rá szavakat.",
    "source": "tatoeba",
    "upstreamId": "414543"
  },
  {
    "text": "Ez egy mostani fénykép?",
    "source": "tatoeba",
    "upstreamId": "414550"
  },
  {
    "text": "Nem tudom, hogy tudok-e időt szakítani rá.",
    "source": "tatoeba",
    "upstreamId": "414554"
  },
  {
    "text": "A hegyekben jártam.",
    "source": "tatoeba",
    "upstreamId": "414557"
  },
  {
    "text": "Holnapra hazaérek, és felhívom őket.",
    "source": "tatoeba",
    "upstreamId": "414565"
  },
  {
    "text": "Nem tudok így élni.",
    "source": "tatoeba",
    "upstreamId": "414568"
  },
  {
    "text": "Sajnálatos, de igaz.",
    "source": "tatoeba",
    "upstreamId": "414572"
  },
  {
    "text": "Biztos vagy benne?",
    "source": "tatoeba",
    "upstreamId": "414574"
  },
  {
    "text": "Ezt most viccnek szántad?",
    "source": "tatoeba",
    "upstreamId": "414578"
  },
  {
    "text": "Ekkora butaságot még életemben nem mondtam.",
    "source": "tatoeba",
    "upstreamId": "414595"
  },
  {
    "text": "Egy, kettő, három, négy, öt, hat, hét, nyolc, kilenc, tíz.",
    "source": "tatoeba",
    "upstreamId": "431732"
  },
  {
    "text": "A beteg ágyban fekszik.",
    "source": "tatoeba",
    "upstreamId": "431961"
  },
  {
    "text": "Finom ez a sütemény.",
    "source": "tatoeba",
    "upstreamId": "431966"
  },
  {
    "text": "Jacknek hívnak.",
    "source": "tatoeba",
    "upstreamId": "433158"
  },
  {
    "text": "Olaszország nagyon szép ország.",
    "source": "tatoeba",
    "upstreamId": "433165"
  },
  {
    "text": "Ma nagyon meleg van.",
    "source": "tatoeba",
    "upstreamId": "433826"
  },
  {
    "text": "- Köszönöm. - Nincs mit.",
    "source": "tatoeba",
    "upstreamId": "435320"
  },
  {
    "text": "Hol van a klozett?",
    "source": "tatoeba",
    "upstreamId": "435518"
  },
  {
    "text": "Ezek az emberek.",
    "source": "tatoeba",
    "upstreamId": "492626"
  },
  {
    "text": "- Köszönöm. - Szívesen.",
    "source": "tatoeba",
    "upstreamId": "494186"
  },
  {
    "text": "Beszél ön japánul?",
    "source": "tatoeba",
    "upstreamId": "494212"
  },
  {
    "text": "Boldog születésnapot!",
    "source": "tatoeba",
    "upstreamId": "494235"
  },
  {
    "text": "Jöttem, láttam, győztem.",
    "source": "tatoeba",
    "upstreamId": "495875"
  },
  {
    "text": "Az, aki nemrég még azt hitte, hogy irányít, mozdulatlan fekszik egy faládában; s a hátramaradók, belátván, hogy hasznát többé nem vehetik, elégetik a kemencében.",
    "source": "tatoeba",
    "upstreamId": "501549"
  },
  {
    "text": "Lengyel, magyar – két jó barát, együtt harcol, s issza borát.",
    "source": "tatoeba",
    "upstreamId": "506135"
  },
  {
    "text": "Ha megmondta volna nekem az igazat, most nem lennék ideges.",
    "source": "tatoeba",
    "upstreamId": "506858"
  },
  {
    "text": "A rendőrségnek sikerült megtalálni a bűnözőt.",
    "source": "tatoeba",
    "upstreamId": "522332"
  },
  {
    "text": "A gyermekek lecsúsztak a padról.",
    "source": "tatoeba",
    "upstreamId": "522333"
  },
  {
    "text": "A lány segített apjának a kerti munkában.",
    "source": "tatoeba",
    "upstreamId": "522334"
  },
  {
    "text": "Tudod-e, ki fedezte fel a távírót?",
    "source": "tatoeba",
    "upstreamId": "522335"
  },
  {
    "text": "A háború alatt Amerika megpróbálta megállítani az Angliával folytatott kereskedelmet.",
    "source": "tatoeba",
    "upstreamId": "522336"
  },
  {
    "text": "Aludni kell mennem.",
    "source": "tatoeba",
    "upstreamId": "522344"
  },
  {
    "text": "Mivel foglalkozol?",
    "source": "tatoeba",
    "upstreamId": "522354"
  },
  {
    "text": "Megédesítjük a teánkat.",
    "source": "tatoeba",
    "upstreamId": "522362"
  },
  {
    "text": "Itt várom meg a nővéremet.",
    "source": "tatoeba",
    "upstreamId": "522381"
  },
  {
    "text": "Ez egy nem várt dolog.",
    "source": "tatoeba",
    "upstreamId": "522497"
  },
  {
    "text": "Rögtön visszajövök!",
    "source": "tatoeba",
    "upstreamId": "523582"
  },
  {
    "text": "Ennek soha sem lesz vége.",
    "source": "tatoeba",
    "upstreamId": "523585"
  },
  {
    "text": "Nem tudom, hogy mit is mondjak.",
    "source": "tatoeba",
    "upstreamId": "523586"
  },
  {
    "text": "Ez egy gonosz nyúl volt.",
    "source": "tatoeba",
    "upstreamId": "523587"
  },
  {
    "text": "Valamiért nem működött a mikrofon.",
    "source": "tatoeba",
    "upstreamId": "523590"
  },
  {
    "text": "Magunknak kell mindent megtanulni.",
    "source": "tatoeba",
    "upstreamId": "523599"
  },
  {
    "text": "Az oktatás ezen a világon kiábrándít engem.",
    "source": "tatoeba",
    "upstreamId": "523600"
  },
  {
    "text": "Nehéz választani a jó és rossz között, de a dolgunkat tennünk kell.",
    "source": "tatoeba",
    "upstreamId": "523609"
  },
  {
    "text": "Ez nem változtat semmit.",
    "source": "tatoeba",
    "upstreamId": "523612"
  },
  {
    "text": "Lehet, hogy hamarosan feladom, inkább szunyókálok egyet.",
    "source": "tatoeba",
    "upstreamId": "523619"
  },
  {
    "text": "Az eszperantóul beszélő emberek elvileg mindig legalább kétnyelvűek.",
    "source": "tatoeba",
    "upstreamId": "523624"
  },
  {
    "text": "Ez nem fog megtörténni.",
    "source": "tatoeba",
    "upstreamId": "524107"
  },
  {
    "text": "Megteszek mindent, hogy ne zavarjalak a tanulásban.",
    "source": "tatoeba",
    "upstreamId": "524121"
  },
  {
    "text": "Egyre inkább kedvelem a rejtélyes személyiségeket.",
    "source": "tatoeba",
    "upstreamId": "524149"
  },
  {
    "text": "Aludnod kellene.",
    "source": "tatoeba",
    "upstreamId": "524153"
  },
  {
    "text": "Azt mondtam nekik, hogy küldjenek másik jegyet.",
    "source": "tatoeba",
    "upstreamId": "524165"
  },
  {
    "text": "Nem tudom, mikor ment férjhez.",
    "source": "tatoeba",
    "upstreamId": "524180"
  },
  {
    "text": "Valaki ellopta az utazási csekkjeimet.",
    "source": "tatoeba",
    "upstreamId": "525837"
  },
  {
    "text": "Valamikor asztrofizikus akartam lenni.",
    "source": "tatoeba",
    "upstreamId": "525880"
  },
  {
    "text": "Sohasem kedveltem a biológiát.",
    "source": "tatoeba",
    "upstreamId": "525886"
  },
  {
    "text": "A legtöbb ember azt hiszi, hogy őrült vagyok.",
    "source": "tatoeba",
    "upstreamId": "525893"
  },
  {
    "text": "Nem, nem én vagyok, hanem te!",
    "source": "tatoeba",
    "upstreamId": "525901"
  },
  {
    "text": "Ez az én válaszom!",
    "source": "tatoeba",
    "upstreamId": "525915"
  },
  {
    "text": "Van itt egy probléma...",
    "source": "tatoeba",
    "upstreamId": "525956"
  },
  {
    "text": "Ó, itt van egy pillangó!",
    "source": "tatoeba",
    "upstreamId": "525973"
  },
  {
    "text": "Ha ilyen lehetnék...",
    "source": "tatoeba",
    "upstreamId": "525978"
  },
  {
    "text": "Ha olyan lehetnék, mint...",
    "source": "tatoeba",
    "upstreamId": "526002"
  },
  {
    "text": "Ha nagy leszek, király akarok lenni.",
    "source": "tatoeba",
    "upstreamId": "526040"
  },
  {
    "text": "Olyan kövér vagyok.",
    "source": "tatoeba",
    "upstreamId": "526043"
  },
  {
    "text": "Azért, mert lány vagy.",
    "source": "tatoeba",
    "upstreamId": "526099"
  },
  {
    "text": "Lehetnék boldogtalan, de nem lennék öngyilkos.",
    "source": "tatoeba",
    "upstreamId": "526128"
  },
  {
    "text": "Miért kérdezed?",
    "source": "tatoeba",
    "upstreamId": "526530"
  },
  {
    "text": "Meddig maradtál?",
    "source": "tatoeba",
    "upstreamId": "526532"
  },
  {
    "text": "Nem tudtam, honnan jött.",
    "source": "tatoeba",
    "upstreamId": "526535"
  },
  {
    "text": "Hol van itt probléma?",
    "source": "tatoeba",
    "upstreamId": "526542"
  },
  {
    "text": "Ne tekints rám többé úgy, mint egy „normális” személyre!",
    "source": "tatoeba",
    "upstreamId": "526557"
  },
  {
    "text": "Amit feltaláltak, mind igaz.",
    "source": "tatoeba",
    "upstreamId": "526561"
  },
  {
    "text": "Meglepődni, csodálkozni, - ez a megértés kezdete.",
    "source": "tatoeba",
    "upstreamId": "526573"
  },
  {
    "text": "A világegyetem kétségtelenül végtelen.",
    "source": "tatoeba",
    "upstreamId": "526580"
  },
  {
    "text": "A tökéletessége csak egy hibán múlt.",
    "source": "tatoeba",
    "upstreamId": "526600"
  },
  {
    "text": "A hajó tegnap áthaladt az Egyenlítőn.",
    "source": "tatoeba",
    "upstreamId": "526610"
  },
  {
    "text": "És mégis, az ellenkezője is mindig igaz.",
    "source": "tatoeba",
    "upstreamId": "526625"
  },
  {
    "text": "Nem úgy látjuk a dolgokat, mint amilyenek, hanem úgy, amilyenek mi vagyunk.",
    "source": "tatoeba",
    "upstreamId": "526636"
  },
  {
    "text": "A világ egy őrültek háza.",
    "source": "tatoeba",
    "upstreamId": "526644"
  },
  {
    "text": "A szerelem sohasem pazarlás.",
    "source": "tatoeba",
    "upstreamId": "526694"
  },
  {
    "text": "Tegyük ismertté az eszperantót!",
    "source": "tatoeba",
    "upstreamId": "527979"
  },
  {
    "text": "Zamenhof, a tervezett eszperantó nyelv kezdeményezője, szemorvos volt.",
    "source": "tatoeba",
    "upstreamId": "527987"
  },
  {
    "text": "Az eszperantóban a hangsúly mindig az utolsó előtti szótagra esik.",
    "source": "tatoeba",
    "upstreamId": "527992"
  },
  {
    "text": "Mióta tanulsz eszperantóul?",
    "source": "tatoeba",
    "upstreamId": "527993"
  },
  {
    "text": "Az eszperantó nélkül biztosan nem tudtam volna egy pekingi családnál étkezni, Lengyelországban a barátommal síelni, Belgrádban a barátnőmnél lakni.",
    "source": "tatoeba",
    "upstreamId": "528001"
  },
  {
    "text": "Elkezdtem eszperantóul tanulni.",
    "source": "tatoeba",
    "upstreamId": "528003"
  },
  {
    "text": "Az eszperantó egy tervezett, nemzetközi nyelv.",
    "source": "tatoeba",
    "upstreamId": "528004"
  },
  {
    "text": "Az eszperantóban a melléknév a-val végződik. A többes számot j-vel képezzük.",
    "source": "tatoeba",
    "upstreamId": "528009"
  },
  {
    "text": "Zamenhof, a tervezett eszperantó nyelv megalkotója, szemorvos volt.",
    "source": "tatoeba",
    "upstreamId": "528014"
  },
  {
    "text": "Az élet az, ami megtörténik veled, miközben más tervekkel foglalkozol.",
    "source": "tatoeba",
    "upstreamId": "528031"
  },
  {
    "text": "Külföldi vagyok.",
    "source": "tatoeba",
    "upstreamId": "528905"
  },
  {
    "text": "Nem kevesebbet, mint száz dollárt fizettem ezért a tollért.",
    "source": "tatoeba",
    "upstreamId": "528911"
  },
  {
    "text": "Nem kívánni ugyanaz, mint birtokolni.",
    "source": "tatoeba",
    "upstreamId": "528914"
  },
  {
    "text": "Boldog karácsonyi ünnepeket!",
    "source": "tatoeba",
    "upstreamId": "528916"
  },
  {
    "text": "Róma sem egy nap alatt épült fel.",
    "source": "tatoeba",
    "upstreamId": "528919"
  },
  {
    "text": "Melyik országból jöttél?",
    "source": "tatoeba",
    "upstreamId": "528923"
  },
  {
    "text": "Rögtön visszajövök.",
    "source": "tatoeba",
    "upstreamId": "528957"
  },
  {
    "text": "A tanulást nem kényszeríteni, hanem bátorítani kell.",
    "source": "tatoeba",
    "upstreamId": "528979"
  },
  {
    "text": "Lehet, hogy nemsokára feladom, inkább szunyókálok egyet.",
    "source": "tatoeba",
    "upstreamId": "528987"
  },
  {
    "text": "Ez azért van, mert nem akarsz egyedül lenni.",
    "source": "tatoeba",
    "upstreamId": "528989"
  },
  {
    "text": "Néha különös fiúnak látszik.",
    "source": "tatoeba",
    "upstreamId": "528997"
  },
  {
    "text": "Csak kérdezem magamban, hogy ez mindenki másnak ugyanaz-e.",
    "source": "tatoeba",
    "upstreamId": "528999"
  },
  {
    "text": "Feltételezem, hogy ez a dolog másnak tűnik, ha sokáig gondolkodol rajta.",
    "source": "tatoeba",
    "upstreamId": "529000"
  },
  {
    "text": "Olyan türelmetlen vagy velem.",
    "source": "tatoeba",
    "upstreamId": "529002"
  },
  {
    "text": "Az utolsó személy, akinek elmondtam az ötletemet, őrültnek tartott.",
    "source": "tatoeba",
    "upstreamId": "529003"
  },
  {
    "text": "Ha a világ nem olyan lenne, mint most, akkor mindenkiben bízhatnék.",
    "source": "tatoeba",
    "upstreamId": "529004"
  },
  {
    "text": "Túlságosan elfoglaltak az egymás elleni küzdelemmel ahhoz, hogy közös eszméknek szenteljék magukat.",
    "source": "tatoeba",
    "upstreamId": "529008"
  },
  {
    "text": "Valamiért éjjel élénkebbnek érzem magam.",
    "source": "tatoeba",
    "upstreamId": "529029"
  },
  {
    "text": "Ez a szövegkörnyezettől függ.",
    "source": "tatoeba",
    "upstreamId": "529044"
  },
  {
    "text": "Ez a konteksztustól függ.",
    "source": "tatoeba",
    "upstreamId": "529045"
  },
  {
    "text": "Nem szánalmas, hanem közkedvelt akarok lenni!!",
    "source": "tatoeba",
    "upstreamId": "529083"
  },
  {
    "text": "Csodálatos dolog Amerikában lenni, ha azért vagy itt, hogy pénzt keressél.",
    "source": "tatoeba",
    "upstreamId": "529098"
  },
  {
    "text": "Földrengés bármikor előfordulhat.",
    "source": "tatoeba",
    "upstreamId": "530201"
  },
  {
    "text": "Nem vagyok igazi hal, csupán csak egy plüss.",
    "source": "tatoeba",
    "upstreamId": "530296"
  },
  {
    "text": "Csak úgy mondom!",
    "source": "tatoeba",
    "upstreamId": "530306"
  },
  {
    "text": "Valószínűleg ez volt az, ami befolyásolta döntésüket.",
    "source": "tatoeba",
    "upstreamId": "530314"
  },
  {
    "text": "Mindig érdekelt, milyen volna, ha lennének testvéreim.",
    "source": "tatoeba",
    "upstreamId": "530351"
  },
  {
    "text": "Ezt mondtam volna.",
    "source": "tatoeba",
    "upstreamId": "530357"
  },
  {
    "text": "Sokáig tartana mindent megmagyarázni.",
    "source": "tatoeba",
    "upstreamId": "530362"
  },
  {
    "text": "Néha nem tudom elkerülni, hogy érzelmeimet kimutassam.",
    "source": "tatoeba",
    "upstreamId": "530368"
  },
  {
    "text": "Van egy szó, mely helyett szeretnék másikat találni.",
    "source": "tatoeba",
    "upstreamId": "530375"
  },
  {
    "text": "Ez olyasmi lenne, amit be kellene programoznom.",
    "source": "tatoeba",
    "upstreamId": "530385"
  },
  {
    "text": "Nincs szándékomban, hogy önző legyek.",
    "source": "tatoeba",
    "upstreamId": "530397"
  },
  {
    "text": "Gondoljunk a legrosszabbra, ami megtörténhet.",
    "source": "tatoeba",
    "upstreamId": "530398"
  },
  {
    "text": "Hány közeli barátod van?",
    "source": "tatoeba",
    "upstreamId": "530402"
  },
  {
    "text": "Talán antiszociális vagyok, de ez nem jelenti azt, hogy nem beszélek az emberekkel.",
    "source": "tatoeba",
    "upstreamId": "530405"
  },
  {
    "text": "Ez mindig így volt.",
    "source": "tatoeba",
    "upstreamId": "530413"
  },
  {
    "text": "Azt hiszem, az a legjobb, ha nem vagyunk udvariatlanok.",
    "source": "tatoeba",
    "upstreamId": "530424"
  },
  {
    "text": "Mindig lehet időnk.",
    "source": "tatoeba",
    "upstreamId": "530429"
  },
  {
    "text": "Rögtön el kell kezdened.",
    "source": "tatoeba",
    "upstreamId": "530742"
  },
  {
    "text": "Otthon reggelizel?",
    "source": "tatoeba",
    "upstreamId": "530743"
  },
  {
    "text": "Nem kellett volna ilyesmit tenned.",
    "source": "tatoeba",
    "upstreamId": "530746"
  },
  {
    "text": "Fél pohár sör után látott evéshez.",
    "source": "tatoeba",
    "upstreamId": "530750"
  },
  {
    "text": "Fáj a hátsó felem.",
    "source": "tatoeba",
    "upstreamId": "530754"
  },
  {
    "text": "Hol van a tejes tea?",
    "source": "tatoeba",
    "upstreamId": "530758"
  },
  {
    "text": "Jó hírt hoztunk.",
    "source": "tatoeba",
    "upstreamId": "530760"
  },
  {
    "text": "Soha sem álmodtam ilyen csendes helyről ebben a zajos városban.",
    "source": "tatoeba",
    "upstreamId": "531081"
  },
  {
    "text": "Amikor gimnáziumba jártam, minden reggel hatkor keltem.",
    "source": "tatoeba",
    "upstreamId": "531102"
  },
  {
    "text": "Amikor felébredtem, szomorú voltam.",
    "source": "tatoeba",
    "upstreamId": "531108"
  },
  {
    "text": "Ez végül többé-kevésbé magyarázatot nyert.",
    "source": "tatoeba",
    "upstreamId": "531115"
  },
  {
    "text": "Azt gondoltam, hogy szívesen tanulnál új dolgokat.",
    "source": "tatoeba",
    "upstreamId": "531125"
  },
  {
    "text": "A legtöbb ember a mindennapi életéről ír.",
    "source": "tatoeba",
    "upstreamId": "531127"
  },
  {
    "text": "Trang, ha küldhetnék neked egy kis édességet, megtenném.",
    "source": "tatoeba",
    "upstreamId": "531130"
  },
  {
    "text": "Hogy ezt megtedd, kockázatot kell vállalnod.",
    "source": "tatoeba",
    "upstreamId": "531142"
  },
  {
    "text": "Minden magányos ember azért van egyedül, mert fél másoktól.",
    "source": "tatoeba",
    "upstreamId": "531154"
  },
  {
    "text": "Nem vagyok művész. Nem volt ehhez tehetségem.",
    "source": "tatoeba",
    "upstreamId": "531164"
  },
  {
    "text": "Ezt most nem tudom neki elmondani. A dolog már nem olyan egyszerű.",
    "source": "tatoeba",
    "upstreamId": "531181"
  },
  {
    "text": "Ember vagyok, sok hibával, de ezek a hibák könnyen javíthatók.",
    "source": "tatoeba",
    "upstreamId": "531186"
  },
  {
    "text": "Mindig, amikor egy nekem tetsző dolgot találok, az túl drága.",
    "source": "tatoeba",
    "upstreamId": "531209"
  },
  {
    "text": "Talán ez az ő számára pontosan ugyanaz lesz.",
    "source": "tatoeba",
    "upstreamId": "531247"
  },
  {
    "text": "Az ártatlanság szép dolog.",
    "source": "tatoeba",
    "upstreamId": "531254"
  },
  {
    "text": "Az embert nem teremtették örök életűnek.",
    "source": "tatoeba",
    "upstreamId": "531273"
  },
  {
    "text": "Nem akarom elveszíteni eszméimet még akkor sem, ha közöttük túlzók is vannak.",
    "source": "tatoeba",
    "upstreamId": "531282"
  },
  {
    "text": "Azt hiszem, hogy van erről egy elméletem.",
    "source": "tatoeba",
    "upstreamId": "531292"
  },
  {
    "text": "Terjesszük az eszperantót!",
    "source": "tatoeba",
    "upstreamId": "532718"
  },
  {
    "text": "Ő a legjobb barátom.",
    "source": "tatoeba",
    "upstreamId": "532772"
  },
  {
    "text": "Alig hallom őt.",
    "source": "tatoeba",
    "upstreamId": "532775"
  },
  {
    "text": "Ne kötelezd el magadat!",
    "source": "tatoeba",
    "upstreamId": "532784"
  },
  {
    "text": "Engedelmeskedned kell szüleidnek.",
    "source": "tatoeba",
    "upstreamId": "532788"
  },
  {
    "text": "Túl későn vettem észre, hogy kihagytam előadásom legfontosabb részét.",
    "source": "tatoeba",
    "upstreamId": "532789"
  },
  {
    "text": "Alig hallom a hölgyet.",
    "source": "tatoeba",
    "upstreamId": "532791"
  },
  {
    "text": "Otthon levelet írtam a szüleimnek.",
    "source": "tatoeba",
    "upstreamId": "532794"
  },
  {
    "text": "Levelet írtam otthon lévő szüleimnek.",
    "source": "tatoeba",
    "upstreamId": "532800"
  },
  {
    "text": "Egész reggel ezen a problémán töröd a fejedet. Tarts szünetet, menj ebédelni.",
    "source": "tatoeba",
    "upstreamId": "532855"
  },
  {
    "text": "Ha most nem teszem meg, akkor soha.",
    "source": "tatoeba",
    "upstreamId": "532858"
  },
  {
    "text": "Nem minden, amit a szemünkkel látunk, kell, hogy igaz legyen.",
    "source": "tatoeba",
    "upstreamId": "533086"
  },
  {
    "text": "Akarsz neki üzenetet hagyni?",
    "source": "tatoeba",
    "upstreamId": "533116"
  },
  {
    "text": "A háború nem elkerülhetetlen.",
    "source": "tatoeba",
    "upstreamId": "533121"
  },
  {
    "text": "Állj fel, amikor hozzád beszélek!",
    "source": "tatoeba",
    "upstreamId": "533134"
  },
  {
    "text": "Láttam, mikor bement a szobába.",
    "source": "tatoeba",
    "upstreamId": "533137"
  },
  {
    "text": "Kezdődik a film.",
    "source": "tatoeba",
    "upstreamId": "533909"
  },
  {
    "text": "A film olyan unalmas volt, hogy a nézők egymás után távoztak.",
    "source": "tatoeba",
    "upstreamId": "533911"
  },
  {
    "text": "Mikor van a nyitvatartási idő?",
    "source": "tatoeba",
    "upstreamId": "533918"
  },
  {
    "text": "Beszéltem az eladóinkkal.",
    "source": "tatoeba",
    "upstreamId": "533942"
  },
  {
    "text": "Ez a legnagyobb szálloda ebben a városban.",
    "source": "tatoeba",
    "upstreamId": "534006"
  },
  {
    "text": "Száz szál piros rózsát küldenék tenéked.",
    "source": "tatoeba",
    "upstreamId": "534007"
  },
  {
    "text": "Több üzletben is kérdeztem ezt a könyvet.",
    "source": "tatoeba",
    "upstreamId": "534009"
  },
  {
    "text": "Sikerült megérteni egymást.",
    "source": "tatoeba",
    "upstreamId": "534219"
  },
  {
    "text": "Innen csak néhány lépés.",
    "source": "tatoeba",
    "upstreamId": "534452"
  },
  {
    "text": "Ugye Smith úr nem beszél angolul?",
    "source": "tatoeba",
    "upstreamId": "534455"
  },
  {
    "text": "A kerékpár csikorgott és megállt.",
    "source": "tatoeba",
    "upstreamId": "534461"
  },
  {
    "text": "A motorkerékpárok olcsók.",
    "source": "tatoeba",
    "upstreamId": "534466"
  },
  {
    "text": "Ne feledd, hogy holnap reggel találkozunk.",
    "source": "tatoeba",
    "upstreamId": "534494"
  },
  {
    "text": "Rábízhatod magadat.",
    "source": "tatoeba",
    "upstreamId": "534498"
  },
  {
    "text": "Megbízhatsz benne.",
    "source": "tatoeba",
    "upstreamId": "534501"
  },
  {
    "text": "Hirtelen halott anyámra gondoltam.",
    "source": "tatoeba",
    "upstreamId": "534510"
  },
  {
    "text": "Ezt látnod kellene!",
    "source": "tatoeba",
    "upstreamId": "534513"
  },
  {
    "text": "Ha elmondta volna az igazat, most nem haragudnék.",
    "source": "tatoeba",
    "upstreamId": "534518"
  },
  {
    "text": "Ez kíváncsivá tesz.",
    "source": "tatoeba",
    "upstreamId": "534548"
  },
  {
    "text": "Azt akarod mondani, hogy szándékosan elrejted szépségedet?",
    "source": "tatoeba",
    "upstreamId": "534553"
  },
  {
    "text": "Nem jelentkeztem be ezeken a fórumokon.",
    "source": "tatoeba",
    "upstreamId": "534562"
  },
  {
    "text": "Ha valaki megkérdezné, hogy mi a történet csattanója, én bizony nem tudom.",
    "source": "tatoeba",
    "upstreamId": "534577"
  },
  {
    "text": "Azt hiszem, hogy veled való együttélésem befolyásolta életmódodat.",
    "source": "tatoeba",
    "upstreamId": "534593"
  },
  {
    "text": "Ez nem tetszett nekem.",
    "source": "tatoeba",
    "upstreamId": "534600"
  },
  {
    "text": "Azt kérdezi, ez hogyan lehetséges.",
    "source": "tatoeba",
    "upstreamId": "534603"
  },
  {
    "text": "Te egyszerűen elfutsz az élet problémái elől.",
    "source": "tatoeba",
    "upstreamId": "534605"
  },
  {
    "text": "Ha a dal szövegét figyeled, az valójában nem sokat jelent.",
    "source": "tatoeba",
    "upstreamId": "534608"
  },
  {
    "text": "Van itt egy probléma, amit nem látsz.",
    "source": "tatoeba",
    "upstreamId": "534612"
  },
  {
    "text": "Ezt meg tudod tenni!",
    "source": "tatoeba",
    "upstreamId": "534616"
  },
  {
    "text": "A fizikatanáromnak mindegy, hogy járok-e az órákra.",
    "source": "tatoeba",
    "upstreamId": "534620"
  },
  {
    "text": "Szeretném, ha elmehetnék Japánba.",
    "source": "tatoeba",
    "upstreamId": "534621"
  },
  {
    "text": "Nem szeretem a tömeget.",
    "source": "tatoeba",
    "upstreamId": "534623"
  },
  {
    "text": "Le kell feküdnöm.",
    "source": "tatoeba",
    "upstreamId": "534629"
  },
  {
    "text": "A játék sokakat lelkesített.",
    "source": "tatoeba",
    "upstreamId": "534634"
  },
  {
    "text": "Miután elmentem, eszembe jutott, hogy náluk felejtettem a hátizsákomat.",
    "source": "tatoeba",
    "upstreamId": "534661"
  },
  {
    "text": "Ma már nem kérdezlek többet.",
    "source": "tatoeba",
    "upstreamId": "534669"
  },
  {
    "text": "A jövő héten talán fagyni fog.",
    "source": "tatoeba",
    "upstreamId": "534683"
  },
  {
    "text": "Télapónak öltözött, hogy tetsszék a gyermekeinek.",
    "source": "tatoeba",
    "upstreamId": "534699"
  },
  {
    "text": "Van egy barátom, aki Angliában él.",
    "source": "tatoeba",
    "upstreamId": "534700"
  },
  {
    "text": "Köszönöm szépen.",
    "source": "tatoeba",
    "upstreamId": "534964"
  },
  {
    "text": "Melyik ér többet, az idő vagy a pénz?",
    "source": "tatoeba",
    "upstreamId": "535881"
  },
  {
    "text": "A kísérlet igazolta az elméletét.",
    "source": "tatoeba",
    "upstreamId": "535885"
  },
  {
    "text": "Nem akarok olyan soká várni.",
    "source": "tatoeba",
    "upstreamId": "535886"
  },
  {
    "text": "Mennél rosszabb, annál jobb.",
    "source": "tatoeba",
    "upstreamId": "535891"
  },
  {
    "text": "Szeretem a természetet.",
    "source": "tatoeba",
    "upstreamId": "535895"
  },
  {
    "text": "Egy millió dolláros kárpótlást kapott.",
    "source": "tatoeba",
    "upstreamId": "535897"
  },
  {
    "text": "Három évig éltem Sasayamában.",
    "source": "tatoeba",
    "upstreamId": "535898"
  },
  {
    "text": "Európában Elbrusz a legmagasabb hegy.",
    "source": "tatoeba",
    "upstreamId": "535900"
  },
  {
    "text": "Ön írta ezt a riportot?",
    "source": "tatoeba",
    "upstreamId": "535901"
  },
  {
    "text": "Bár bocsánatot kért, én még mindig dühös vagyok.",
    "source": "tatoeba",
    "upstreamId": "536008"
  },
  {
    "text": "A rendőrség rá fog venni benneteket, hogy megtaláljátok a golyókat.",
    "source": "tatoeba",
    "upstreamId": "536033"
  },
  {
    "text": "Köszönöm, hogy végre megmagyarázta, miért tartanak engem az emberek idiótának.",
    "source": "tatoeba",
    "upstreamId": "536046"
  },
  {
    "text": "Nem volt szándékomban.",
    "source": "tatoeba",
    "upstreamId": "536056"
  },
  {
    "text": "Köszönöm a magyarázatát.",
    "source": "tatoeba",
    "upstreamId": "536060"
  },
  {
    "text": "Elméletileg matematikával foglalkozom.",
    "source": "tatoeba",
    "upstreamId": "536066"
  },
  {
    "text": "Ha nem így ismertél, akkor egyáltalán nem ismertél.",
    "source": "tatoeba",
    "upstreamId": "536070"
  },
  {
    "text": "Majdnem megijesztett, hogy egész nap nem láttalak az interneten.",
    "source": "tatoeba",
    "upstreamId": "536072"
  },
  {
    "text": "Nem tudom, mi a véleményed.",
    "source": "tatoeba",
    "upstreamId": "536075"
  },
  {
    "text": "Kell, hogy a számítógépem jó legyen valamire.",
    "source": "tatoeba",
    "upstreamId": "536080"
  },
  {
    "text": "A szabadságról akartál velem beszélni?",
    "source": "tatoeba",
    "upstreamId": "536089"
  },
  {
    "text": "Ó, ez most tényleg zavaros...",
    "source": "tatoeba",
    "upstreamId": "536094"
  },
  {
    "text": "Ha meg akarnálak ijeszteni, elmesélném neked, hogy mit álmodtam néhány héttel ezelőtt.",
    "source": "tatoeba",
    "upstreamId": "536097"
  },
  {
    "text": "Nem lehet mindent az iskoláktól várni.",
    "source": "tatoeba",
    "upstreamId": "536098"
  },
  {
    "text": "Sok szó van, amit nem értek.",
    "source": "tatoeba",
    "upstreamId": "536099"
  },
  {
    "text": "Nem szeretem, amikor a matematikusok, akik nálam jóval többet tudnak, nem tudják pontosan kifejezni magukat.",
    "source": "tatoeba",
    "upstreamId": "536101"
  },
  {
    "text": "Tényleg nem vagy ostoba.",
    "source": "tatoeba",
    "upstreamId": "536107"
  },
  {
    "text": "Egy buta kérdést kell neked feltennem.",
    "source": "tatoeba",
    "upstreamId": "536112"
  },
  {
    "text": "Nem tudom, hogyan bizonyítsam, hiszen teljesen nyilvánvaló.",
    "source": "tatoeba",
    "upstreamId": "536130"
  },
  {
    "text": "A főnöknek jó véleménye van a munkádról.",
    "source": "tatoeba",
    "upstreamId": "536396"
  },
  {
    "text": "A kertet magas fal vette körül.",
    "source": "tatoeba",
    "upstreamId": "536398"
  },
  {
    "text": "Hírnevet kell szereznünk.",
    "source": "tatoeba",
    "upstreamId": "536399"
  },
  {
    "text": "El fogom fogadni a javaslatodat.",
    "source": "tatoeba",
    "upstreamId": "536400"
  },
  {
    "text": "Ne érintsd az üveget.",
    "source": "tatoeba",
    "upstreamId": "536402"
  },
  {
    "text": "Előzetes tapasztalatai után érdeklődtek.",
    "source": "tatoeba",
    "upstreamId": "536403"
  },
  {
    "text": "Tevékenységünknek a probléma megoldását kell céloznia.",
    "source": "tatoeba",
    "upstreamId": "536404"
  },
  {
    "text": "Még korai erről beszélni.",
    "source": "tatoeba",
    "upstreamId": "536405"
  },
  {
    "text": "Nem is tudom, mikor megyek vissza.",
    "source": "tatoeba",
    "upstreamId": "536935"
  },
  {
    "text": "Nagyjából egyidősek.",
    "source": "tatoeba",
    "upstreamId": "536936"
  },
  {
    "text": "Francia vagyok.",
    "source": "tatoeba",
    "upstreamId": "536947"
  },
  {
    "text": "Ennek a cipőnek már kampec.",
    "source": "tatoeba",
    "upstreamId": "536952"
  },
  {
    "text": "Pénzügyileg a feleségétől függ.",
    "source": "tatoeba",
    "upstreamId": "536958"
  },
  {
    "text": "Narancslét kérek.",
    "source": "tatoeba",
    "upstreamId": "536961"
  },
  {
    "text": "Ha így van, akkor nincs is itt semmi probléma, úgy-e?",
    "source": "tatoeba",
    "upstreamId": "536965"
  },
  {
    "text": "Fordító vagyok.",
    "source": "tatoeba",
    "upstreamId": "536966"
  },
  {
    "text": "Nagyon szeretne balerina lenni.",
    "source": "tatoeba",
    "upstreamId": "536969"
  },
  {
    "text": "Egyáltalán nem probléma, igaz?",
    "source": "tatoeba",
    "upstreamId": "536996"
  },
  {
    "text": "Csukd be a szemedet, és számolj tízig.",
    "source": "tatoeba",
    "upstreamId": "537132"
  },
  {
    "text": "A váza a padlóra esett és eltört.",
    "source": "tatoeba",
    "upstreamId": "537133"
  },
  {
    "text": "A nagybátyám Londonban él.",
    "source": "tatoeba",
    "upstreamId": "537135"
  },
  {
    "text": "A férfit az egész faluban jól ismerik.",
    "source": "tatoeba",
    "upstreamId": "537136"
  },
  {
    "text": "Addig üsd a vasat, amíg meleg.",
    "source": "tatoeba",
    "upstreamId": "537137"
  },
  {
    "text": "Kellemes hangja van.",
    "source": "tatoeba",
    "upstreamId": "537138"
  },
  {
    "text": "Ne hagyd bekapcsolva a televíziót!",
    "source": "tatoeba",
    "upstreamId": "537139"
  },
  {
    "text": "Mondhatjuk másképp is?",
    "source": "tatoeba",
    "upstreamId": "537142"
  },
  {
    "text": "Kifejezhetjük másképp is?",
    "source": "tatoeba",
    "upstreamId": "537143"
  },
  {
    "text": "Senki sem fogja tudni.",
    "source": "tatoeba",
    "upstreamId": "537144"
  },
  {
    "text": "Találtam egy megoldást, de olyan gyorsan, hogy az nem is lehet az igazi.",
    "source": "tatoeba",
    "upstreamId": "537145"
  },
  {
    "text": "Ez érdekesnek tűnik nekem.",
    "source": "tatoeba",
    "upstreamId": "537146"
  },
  {
    "text": "Szeretem a gyertyafényt.",
    "source": "tatoeba",
    "upstreamId": "537147"
  },
  {
    "text": "Nem, ő nem az új barátom.",
    "source": "tatoeba",
    "upstreamId": "537150"
  },
  {
    "text": "Kár, hogy nem kell lefogynom.",
    "source": "tatoeba",
    "upstreamId": "537151"
  },
  {
    "text": "Akkor inkább sodoku-t játszom, ahelyett, hogy tovább zavarjalak.",
    "source": "tatoeba",
    "upstreamId": "537163"
  },
  {
    "text": "Ez nem nagy meglepetés, ugye?",
    "source": "tatoeba",
    "upstreamId": "537170"
  },
  {
    "text": "Kíváncsi vagyok.",
    "source": "tatoeba",
    "upstreamId": "537174"
  },
  {
    "text": "Már nem szeretlek.",
    "source": "tatoeba",
    "upstreamId": "537176"
  },
  {
    "text": "Szívből gratulálok!",
    "source": "tatoeba",
    "upstreamId": "537178"
  },
  {
    "text": "Miért nem jössz meglátogatni bennünket?",
    "source": "tatoeba",
    "upstreamId": "537427"
  },
  {
    "text": "Már nem tudom, hogy mit tegyek.",
    "source": "tatoeba",
    "upstreamId": "537437"
  },
  {
    "text": "Elkerülhetetlen, hogy valamelyik napon Franciaországba menjek, csak azt nem tudom, hogy mikor.",
    "source": "tatoeba",
    "upstreamId": "537439"
  },
  {
    "text": "Gyűlölöm a kémiát.",
    "source": "tatoeba",
    "upstreamId": "537440"
  },
  {
    "text": "Nem akartam, hogy ez történjen.",
    "source": "tatoeba",
    "upstreamId": "537441"
  },
  {
    "text": "Van más választásom?",
    "source": "tatoeba",
    "upstreamId": "537448"
  },
  {
    "text": "Mielőtt felocsúdol, benne leszel az újságban.",
    "source": "tatoeba",
    "upstreamId": "537449"
  },
  {
    "text": "Nem vagyok nagy utazó.",
    "source": "tatoeba",
    "upstreamId": "537450"
  },
  {
    "text": "Nincs jobb tennivalóm.",
    "source": "tatoeba",
    "upstreamId": "537453"
  },
  {
    "text": "El sem tudom magyarázni.",
    "source": "tatoeba",
    "upstreamId": "537456"
  },
  {
    "text": "Ez csak azt mutatja, hogy nem vagy egy robot.",
    "source": "tatoeba",
    "upstreamId": "537460"
  },
  {
    "text": "Hogyan lehetnék robot? A robotok nem álmodnak.",
    "source": "tatoeba",
    "upstreamId": "537465"
  },
  {
    "text": "- Erre sohasem gondoltam - mondta az öregember. - Mit tegyünk?",
    "source": "tatoeba",
    "upstreamId": "537470"
  },
  {
    "text": "Ez nem olyan dolog, amit bárki meg tud tenni.",
    "source": "tatoeba",
    "upstreamId": "537472"
  },
  {
    "text": "Ő nem figyel a tanárra.",
    "source": "tatoeba",
    "upstreamId": "537544"
  },
  {
    "text": "Ő intelligensebb, mint a többiek.",
    "source": "tatoeba",
    "upstreamId": "537563"
  },
  {
    "text": "Angliát megszállták a dánok.",
    "source": "tatoeba",
    "upstreamId": "537569"
  },
  {
    "text": "Jártál már külföldön?",
    "source": "tatoeba",
    "upstreamId": "537572"
  },
  {
    "text": "Állj fel, ha hozzád beszélek!",
    "source": "tatoeba",
    "upstreamId": "538354"
  },
  {
    "text": "Te egy angyal vagy!",
    "source": "tatoeba",
    "upstreamId": "538390"
  },
  {
    "text": "A madridiak őrültek.",
    "source": "tatoeba",
    "upstreamId": "538401"
  },
  {
    "text": "Jól van, az éjszaka elég hosszú, ugye?",
    "source": "tatoeba",
    "upstreamId": "538414"
  },
  {
    "text": "Álljatok fel, ha hozzátok beszélek!",
    "source": "tatoeba",
    "upstreamId": "538423"
  },
  {
    "text": "Szerencséd volt, hogy nem harapott meg.",
    "source": "tatoeba",
    "upstreamId": "538424"
  },
  {
    "text": "Álljon fel, ha magához beszélek!",
    "source": "tatoeba",
    "upstreamId": "538428"
  },
  {
    "text": "Álljanak fel, ha magukhoz beszélek!",
    "source": "tatoeba",
    "upstreamId": "538432"
  },
  {
    "text": "Hiányoztam neked?",
    "source": "tatoeba",
    "upstreamId": "538441"
  },
  {
    "text": "Nem tudom, hogy még megvan-e.",
    "source": "tatoeba",
    "upstreamId": "538468"
  },
  {
    "text": "Mit gondolsz, mit csináltam éppen?",
    "source": "tatoeba",
    "upstreamId": "538469"
  },
  {
    "text": "Ne becsüld alá az erőmet.",
    "source": "tatoeba",
    "upstreamId": "538475"
  },
  {
    "text": "Anyám nem beszél nagyon jól angolul.",
    "source": "tatoeba",
    "upstreamId": "538477"
  },
  {
    "text": "Nem beszélek elég jól franciául!",
    "source": "tatoeba",
    "upstreamId": "538478"
  },
  {
    "text": "Hol találsz táplálékot a világűrben?",
    "source": "tatoeba",
    "upstreamId": "538481"
  },
  {
    "text": "Mindenki találkozni akar veled, híres vagy!",
    "source": "tatoeba",
    "upstreamId": "538490"
  },
  {
    "text": "Miért sajnálsz valamit, amit nem tettél meg?",
    "source": "tatoeba",
    "upstreamId": "538495"
  },
  {
    "text": "Mélységesen utálom a formális írást!",
    "source": "tatoeba",
    "upstreamId": "538504"
  },
  {
    "text": "Nenszi fél a kutyáktól.",
    "source": "tatoeba",
    "upstreamId": "538691"
  },
  {
    "text": "Az egyik könyvesboltban vett egy angolkönyvet.",
    "source": "tatoeba",
    "upstreamId": "538698"
  },
  {
    "text": "Ha mondasz valamit, én mindig a saját szájam íze szerint csinálom.",
    "source": "tatoeba",
    "upstreamId": "538703"
  },
  {
    "text": "A zöldet kéred vagy a kéket?",
    "source": "tatoeba",
    "upstreamId": "538704"
  },
  {
    "text": "Szerintem jó táncosnő.",
    "source": "tatoeba",
    "upstreamId": "538710"
  },
  {
    "text": "Megírta egy híres költő életrajzát.",
    "source": "tatoeba",
    "upstreamId": "538714"
  },
  {
    "text": "Az ott egy arckép Bobról a falnál.",
    "source": "tatoeba",
    "upstreamId": "538718"
  },
  {
    "text": "A férfi megijesztette a kisgyerekeket.",
    "source": "tatoeba",
    "upstreamId": "538719"
  },
  {
    "text": "Olyan gyorsan futott, hogy teljesen kifulladt.",
    "source": "tatoeba",
    "upstreamId": "538720"
  },
  {
    "text": "Úgy tűnik, ő ismeri Annát.",
    "source": "tatoeba",
    "upstreamId": "538721"
  },
  {
    "text": "Két sört kérek!",
    "source": "tatoeba",
    "upstreamId": "538728"
  },
  {
    "text": "A Nozomi az összes közül a leggyorsabb vonat Japánban.",
    "source": "tatoeba",
    "upstreamId": "538732"
  },
  {
    "text": "Jó csapatkapitány lesz belőle.",
    "source": "tatoeba",
    "upstreamId": "538735"
  },
  {
    "text": "Gyakran játszottam baseball-t, amikor fiatal voltam.",
    "source": "tatoeba",
    "upstreamId": "538772"
  },
  {
    "text": "A külföldiek kíváncsivá tesznek.",
    "source": "tatoeba",
    "upstreamId": "538776"
  },
  {
    "text": "Bármit teszek, azt mondja, hogy jobban is meg tudom csinálni.",
    "source": "tatoeba",
    "upstreamId": "538783"
  },
  {
    "text": "Miért vagy még ébren ilyen későn?",
    "source": "tatoeba",
    "upstreamId": "538785"
  },
  {
    "text": "Senki sem akar velem utazni.",
    "source": "tatoeba",
    "upstreamId": "538791"
  },
  {
    "text": "Nem vagy elég gyors.",
    "source": "tatoeba",
    "upstreamId": "538792"
  },
  {
    "text": "Az élet kemény, de én keményebb vagyok.",
    "source": "tatoeba",
    "upstreamId": "538794"
  },
  {
    "text": "Tűrhetetlen lehet valamit eltűrni.",
    "source": "tatoeba",
    "upstreamId": "538807"
  },
  {
    "text": "A szabadságért fizetni kell.",
    "source": "tatoeba",
    "upstreamId": "538815"
  },
  {
    "text": "Kövesd az orvos tanácsát.",
    "source": "tatoeba",
    "upstreamId": "538829"
  },
  {
    "text": "Tanulsz angolul?",
    "source": "tatoeba",
    "upstreamId": "538834"
  },
  {
    "text": "Hagyd abba! Kellemetlenül érzi magát emiatt.",
    "source": "tatoeba",
    "upstreamId": "538839"
  },
  {
    "text": "Csak az igazság szép.",
    "source": "tatoeba",
    "upstreamId": "538844"
  },
  {
    "text": "Holnap leszáll a Holdra.",
    "source": "tatoeba",
    "upstreamId": "538848"
  },
  {
    "text": "Ez egy szójáték.",
    "source": "tatoeba",
    "upstreamId": "538849"
  },
  {
    "text": "Senki sem ért meg engem.",
    "source": "tatoeba",
    "upstreamId": "538850"
  },
  {
    "text": "Megtanultam nélküle élni.",
    "source": "tatoeba",
    "upstreamId": "538853"
  },
  {
    "text": "Mostanában túl sok dolog jár a fejemben.",
    "source": "tatoeba",
    "upstreamId": "538856"
  },
  {
    "text": "Éppen le akartam hívni az elektronikus postámat.",
    "source": "tatoeba",
    "upstreamId": "538860"
  },
  {
    "text": "Valóban fel kell tenned a kérdést ahhoz, hogy megtudd a választ?",
    "source": "tatoeba",
    "upstreamId": "538863"
  },
  {
    "text": "Nem várhatod el tőlem, hogy mindig mindenre gondoljak!",
    "source": "tatoeba",
    "upstreamId": "538865"
  },
  {
    "text": "Feltételezem, hogy minden mögött, amit meg kell tennünk, van valami, amit meg akarunk tenni...",
    "source": "tatoeba",
    "upstreamId": "538885"
  },
  {
    "text": "Igazán nincsenek jó prioritásaid!",
    "source": "tatoeba",
    "upstreamId": "538890"
  },
  {
    "text": "Soha sincsen időd a fontos dolgokra!",
    "source": "tatoeba",
    "upstreamId": "538896"
  },
  {
    "text": "Sokáig tartana elmagyarázni neked, hogy ez miért nem fog működni.",
    "source": "tatoeba",
    "upstreamId": "538898"
  },
  {
    "text": "Megtaláltad a kontaktlencsédet?",
    "source": "tatoeba",
    "upstreamId": "538899"
  },
  {
    "text": "Olyan buta vagyok... Megpróbálok elmagyarázni neked olyan dolgokat, amelyeket magam sem értek.",
    "source": "tatoeba",
    "upstreamId": "538904"
  },
  {
    "text": "A kutya kimúlt.",
    "source": "tatoeba",
    "upstreamId": "539077"
  },
  {
    "text": "A nagybátyád megengedte, hogy vezesd az autóját?",
    "source": "tatoeba",
    "upstreamId": "539080"
  },
  {
    "text": "Bárcsak tudnám a címét!",
    "source": "tatoeba",
    "upstreamId": "539117"
  },
  {
    "text": "Mit mondott? Meg tudná ismételni?",
    "source": "tatoeba",
    "upstreamId": "539126"
  },
  {
    "text": "Ön filozófus, nemde?",
    "source": "tatoeba",
    "upstreamId": "539127"
  },
  {
    "text": "Mit gondol erről?",
    "source": "tatoeba",
    "upstreamId": "539130"
  },
  {
    "text": "Mit gondolsz erről?",
    "source": "tatoeba",
    "upstreamId": "539134"
  },
  {
    "text": "Három gyermek játszott a parkban.",
    "source": "tatoeba",
    "upstreamId": "539135"
  },
  {
    "text": "Énekeljünk egy vidám dalt.",
    "source": "tatoeba",
    "upstreamId": "539142"
  },
  {
    "text": "A boldog iskolaévek már elmúltak.",
    "source": "tatoeba",
    "upstreamId": "539148"
  },
  {
    "text": "Hideg van ott, habár nyár van.",
    "source": "tatoeba",
    "upstreamId": "539921"
  },
  {
    "text": "Mindenki szereti az udvarias embereket.",
    "source": "tatoeba",
    "upstreamId": "539922"
  },
  {
    "text": "Milyen messze van az iskola, ahova jársz?",
    "source": "tatoeba",
    "upstreamId": "539924"
  },
  {
    "text": "Hagyd abba a macerálást. El vagyok foglalva.",
    "source": "tatoeba",
    "upstreamId": "539927"
  },
  {
    "text": "Tegnap elvesztettem a karórámat.",
    "source": "tatoeba",
    "upstreamId": "539929"
  },
  {
    "text": "Rá kellene nevelni a gyerekeket, hogy ne hazudjanak.",
    "source": "tatoeba",
    "upstreamId": "539930"
  },
  {
    "text": "Nagyon kedves tőled, hogy segítesz nekem megcsinálni a házi feladatokat.",
    "source": "tatoeba",
    "upstreamId": "539931"
  },
  {
    "text": "Hallok egy kutyát ugatni az erdőben.",
    "source": "tatoeba",
    "upstreamId": "539932"
  },
  {
    "text": "Melyik a kedvenc mondatod?",
    "source": "tatoeba",
    "upstreamId": "539934"
  },
  {
    "text": "Ellen nem beszél angolul.",
    "source": "tatoeba",
    "upstreamId": "539939"
  },
  {
    "text": "Legközelebb korábban jövök.",
    "source": "tatoeba",
    "upstreamId": "539942"
  },
  {
    "text": "Ugyanolyan idős, mint én.",
    "source": "tatoeba",
    "upstreamId": "539946"
  },
  {
    "text": "Szeretnék beváltani egy utazási csekket.",
    "source": "tatoeba",
    "upstreamId": "539951"
  },
  {
    "text": "Hány könyvet olvasol el havonta?",
    "source": "tatoeba",
    "upstreamId": "539956"
  },
  {
    "text": "Aki mer, az nyer.",
    "source": "tatoeba",
    "upstreamId": "539975"
  },
  {
    "text": "Olyan becsületes, hogy mindenki megbízik benne.",
    "source": "tatoeba",
    "upstreamId": "539990"
  },
  {
    "text": "Először találkozom vele.",
    "source": "tatoeba",
    "upstreamId": "540776"
  },
  {
    "text": "Nara tetszik nekem, különösen ősszel.",
    "source": "tatoeba",
    "upstreamId": "545560"
  },
  {
    "text": "Legalább megpróbálhatnál kissé udvariasabb lenni, még akkor is, ha nem ilyen a természeted.",
    "source": "tatoeba",
    "upstreamId": "545607"
  },
  {
    "text": "Nem éri meg a fáradságot, hogy úgy tegyünk, mintha elhitetnéd velem, hogy olyan dolgokat hiszek, amelyeket te nem hiszel.",
    "source": "tatoeba",
    "upstreamId": "545614"
  },
  {
    "text": "Mindig vannak olyan dolgok, amelyeket sohasem fogok megtanulni, nem rendelkezem az örökkévalósággal.",
    "source": "tatoeba",
    "upstreamId": "545617"
  },
  {
    "text": "Ez nem lehetséges!",
    "source": "tatoeba",
    "upstreamId": "546430"
  },
  {
    "text": "Szeretnél valamit inni?",
    "source": "tatoeba",
    "upstreamId": "546444"
  },
  {
    "text": "„A gördülő kő nem lesz mohos” egy közmondás.",
    "source": "tatoeba",
    "upstreamId": "546459"
  },
  {
    "text": "- Ki az? - Az édesanyád.",
    "source": "tatoeba",
    "upstreamId": "546467"
  },
  {
    "text": "- Mikor jössz vissza? - Ez teljesen az időjárástól függ.",
    "source": "tatoeba",
    "upstreamId": "546468"
  },
  {
    "text": "- Mi van? - kérdezte a kis, fehér nyuszi.",
    "source": "tatoeba",
    "upstreamId": "546474"
  },
  {
    "text": "- Mi történik a barlangban? Kíváncsi vagyok. - Fogalmam sincsen.",
    "source": "tatoeba",
    "upstreamId": "546478"
  },
  {
    "text": "- Mi a kívánságod? - kérdezte a kis, fehér nyuszi.",
    "source": "tatoeba",
    "upstreamId": "546482"
  },
  {
    "text": "Meg kell tanulnunk testvérként együtt élni, vagy őrültként együtt veszünk el.",
    "source": "tatoeba",
    "upstreamId": "546495"
  },
  {
    "text": "Hm... Hogy működik ez?",
    "source": "tatoeba",
    "upstreamId": "546502"
  },
  {
    "text": "- Bízzál bennem - mondta.",
    "source": "tatoeba",
    "upstreamId": "546515"
  },
  {
    "text": "- Ezt keresgéltem! - kiáltott fel.",
    "source": "tatoeba",
    "upstreamId": "546523"
  },
  {
    "text": "- Ez elég érdekesnek látszik - mondja Hiroshi.",
    "source": "tatoeba",
    "upstreamId": "546531"
  },
  {
    "text": "A kommunikációjuk talán sokkal bonyolultabb, mint ahogy gondoltuk.",
    "source": "tatoeba",
    "upstreamId": "546561"
  },
  {
    "text": "- Cseng a telefon. - Felveszem.",
    "source": "tatoeba",
    "upstreamId": "546571"
  },
  {
    "text": "- Ez nagyon kedves öntől - válaszolta Willie.",
    "source": "tatoeba",
    "upstreamId": "546576"
  },
  {
    "text": "- Köszönöm a segítséget. - Nincs mit.",
    "source": "tatoeba",
    "upstreamId": "546923"
  },
  {
    "text": "Valamikor úgy futok majd, mint a szél.",
    "source": "tatoeba",
    "upstreamId": "546924"
  },
  {
    "text": "- Ő szereti a zenét. - Én is.",
    "source": "tatoeba",
    "upstreamId": "546925"
  },
  {
    "text": "Tudasd velem, ha van valami, amit tehetek.",
    "source": "tatoeba",
    "upstreamId": "546926"
  },
  {
    "text": "Te döntöd el, hogy odamegyünk-e, vagy sem.",
    "source": "tatoeba",
    "upstreamId": "546941"
  },
  {
    "text": "Nem kezdődik fél kilenc előtt.",
    "source": "tatoeba",
    "upstreamId": "546955"
  },
  {
    "text": "Egy csónakot akarok, mely messzire visz innen.",
    "source": "tatoeba",
    "upstreamId": "546981"
  },
  {
    "text": "- Kedvem van kártyázni. - Nekem is.",
    "source": "tatoeba",
    "upstreamId": "546989"
  },
  {
    "text": "- Nem találkoztunk már valamikor? - kérdezte a hallgató.",
    "source": "tatoeba",
    "upstreamId": "547014"
  },
  {
    "text": "Egy japán sohase tenne ilyesmit.",
    "source": "tatoeba",
    "upstreamId": "547019"
  },
  {
    "text": "Az íjász megölte a szarvast.",
    "source": "tatoeba",
    "upstreamId": "547027"
  },
  {
    "text": "Az én életemben a kommunizmus sohasem valósul meg.",
    "source": "tatoeba",
    "upstreamId": "547039"
  },
  {
    "text": "Nekem úgy látszik, hogy gazdag volt.",
    "source": "tatoeba",
    "upstreamId": "549264"
  },
  {
    "text": "Ezzel a vonattal kétszer gyorsabban odaérsz.",
    "source": "tatoeba",
    "upstreamId": "552993"
  },
  {
    "text": "A rozsot a szegény emberek gabonájának hívták.",
    "source": "tatoeba",
    "upstreamId": "553027"
  },
  {
    "text": "Kérlek, ha látsz egy hibát, javítsd ki.",
    "source": "tatoeba",
    "upstreamId": "553049"
  },
  {
    "text": "Tedd a kártyapaklit a tölgyasztalra.",
    "source": "tatoeba",
    "upstreamId": "553056"
  },
  {
    "text": "A németek nagyon furfangosak.",
    "source": "tatoeba",
    "upstreamId": "553062"
  },
  {
    "text": "Ha nem eszünk, meghalunk.",
    "source": "tatoeba",
    "upstreamId": "553063"
  },
  {
    "text": "Hogyan írják azt, hogy pretty?",
    "source": "tatoeba",
    "upstreamId": "553095"
  },
  {
    "text": "Ken baseballjátékos szeretne lenni.",
    "source": "tatoeba",
    "upstreamId": "553403"
  },
  {
    "text": "A szobában állt egy zongora, azon viszont senki nem játszott.",
    "source": "tatoeba",
    "upstreamId": "553405"
  },
  {
    "text": "Egyre kevesebb időm van az olvasásra.",
    "source": "tatoeba",
    "upstreamId": "553412"
  },
  {
    "text": "Mikor mész vissza Japánba?",
    "source": "tatoeba",
    "upstreamId": "553413"
  },
  {
    "text": "Fogkefével fogat mosok.",
    "source": "tatoeba",
    "upstreamId": "553414"
  },
  {
    "text": "A meleg és a fény elengedhetetlen életben maradásunkhoz.",
    "source": "tatoeba",
    "upstreamId": "553421"
  },
  {
    "text": "Kivágott egy képet a könyvből.",
    "source": "tatoeba",
    "upstreamId": "553422"
  },
  {
    "text": "Nem engedhetünk a terrorista követeléseknek.",
    "source": "tatoeba",
    "upstreamId": "553424"
  },
  {
    "text": "A híres énekes öngyilkosságot követett el.",
    "source": "tatoeba",
    "upstreamId": "553427"
  },
  {
    "text": "Sokkal több a víz a tóban, mint előtte volt.",
    "source": "tatoeba",
    "upstreamId": "553430"
  },
  {
    "text": "Az eszperantó nyelv elterjesztését leginkább az segíti, ha nyíltan és szabatosan használják a nyelvet.",
    "source": "tatoeba",
    "upstreamId": "553435"
  },
  {
    "text": "Az autóbuszon gyakran szóba elegyedek vele.",
    "source": "tatoeba",
    "upstreamId": "553437"
  },
  {
    "text": "A kávét cukor nélkül szereti.",
    "source": "tatoeba",
    "upstreamId": "553439"
  },
  {
    "text": "Megmutatta hogyan kell gitáron játszani.",
    "source": "tatoeba",
    "upstreamId": "553443"
  },
  {
    "text": "Elmondott egy érdekes történetet.",
    "source": "tatoeba",
    "upstreamId": "553445"
  },
  {
    "text": "Amint a fiú meglátott, elfutott.",
    "source": "tatoeba",
    "upstreamId": "553448"
  },
  {
    "text": "Nem áll módomban új autót venni.",
    "source": "tatoeba",
    "upstreamId": "553450"
  },
  {
    "text": "Ezeket a gyógyszereket napi háromszor kell szedni.",
    "source": "tatoeba",
    "upstreamId": "553451"
  },
  {
    "text": "A barátaim meghívtak vacsorázni.",
    "source": "tatoeba",
    "upstreamId": "553454"
  },
  {
    "text": "Sok barátja amerikai.",
    "source": "tatoeba",
    "upstreamId": "553456"
  },
  {
    "text": "Rosszul érzi magát a barátnőm.",
    "source": "tatoeba",
    "upstreamId": "553458"
  },
  {
    "text": "A szüleim kínaiak.",
    "source": "tatoeba",
    "upstreamId": "553459"
  },
  {
    "text": "Kínaiul beszél.",
    "source": "tatoeba",
    "upstreamId": "553461"
  },
  {
    "text": "Kínaiul tanulunk.",
    "source": "tatoeba",
    "upstreamId": "553462"
  },
  {
    "text": "Beszél ön kínaiul?",
    "source": "tatoeba",
    "upstreamId": "553466"
  },
  {
    "text": "Három fényképezőgépem van.",
    "source": "tatoeba",
    "upstreamId": "553468"
  },
  {
    "text": "Tom szeret úszni.",
    "source": "tatoeba",
    "upstreamId": "553469"
  },
  {
    "text": "Néha összefutok vele a klubban.",
    "source": "tatoeba",
    "upstreamId": "553472"
  },
  {
    "text": "Beszédem van veled.",
    "source": "tatoeba",
    "upstreamId": "553473"
  },
  {
    "text": "Egyedül élt az erdőben.",
    "source": "tatoeba",
    "upstreamId": "553474"
  },
  {
    "text": "Kína és Japán sokban különbözik.",
    "source": "tatoeba",
    "upstreamId": "553477"
  },
  {
    "text": "Rögtön összebarátkoztunk.",
    "source": "tatoeba",
    "upstreamId": "553480"
  },
  {
    "text": "Nem hallottam semmit.",
    "source": "tatoeba",
    "upstreamId": "553482"
  },
  {
    "text": "Linda szereti a csokoládét.",
    "source": "tatoeba",
    "upstreamId": "553483"
  },
  {
    "text": "Amikor két erő összecsap, aki tud, harcoljon. Aki nem harcol, az védekezzen. Aki nem védekezik, az meneküljön. Aki nem menekül el, az adja meg magát. Akik magukat nem adták meg, azoknak a halál jár.",
    "source": "tatoeba",
    "upstreamId": "553487"
  },
  {
    "text": "Most változtattam meg a profilképemet.",
    "source": "tatoeba",
    "upstreamId": "553493"
  },
  {
    "text": "Erre nagyon nagy a hideg.",
    "source": "tatoeba",
    "upstreamId": "553501"
  },
  {
    "text": "Saját szememmel láttam.",
    "source": "tatoeba",
    "upstreamId": "553507"
  },
  {
    "text": "Az idő gyógyít.",
    "source": "tatoeba",
    "upstreamId": "553512"
  },
  {
    "text": "Az esetleges hibákat javítsd ki.",
    "source": "tatoeba",
    "upstreamId": "553519"
  },
  {
    "text": "Miért nem megyünk haza?",
    "source": "tatoeba",
    "upstreamId": "555618"
  },
  {
    "text": "Sajnálom, nem tudok sokáig maradni.",
    "source": "tatoeba",
    "upstreamId": "555620"
  },
  {
    "text": "- Miért nem mész? - Mert nem akarok.",
    "source": "tatoeba",
    "upstreamId": "555637"
  },
  {
    "text": "Egymillió ember vesztette életét a háborúban.",
    "source": "tatoeba",
    "upstreamId": "555679"
  },
  {
    "text": "Három éve jöttem Tokióba és azóta itt élek.",
    "source": "tatoeba",
    "upstreamId": "555702"
  },
  {
    "text": "Több mint egy hónapig éltem Nagoyában.",
    "source": "tatoeba",
    "upstreamId": "555760"
  },
  {
    "text": "Egyáltalán nem ritka, ha valaki kilencven évnél tovább él.",
    "source": "tatoeba",
    "upstreamId": "555766"
  },
  {
    "text": "Te nem tudod, mennyire szeretlek.",
    "source": "tatoeba",
    "upstreamId": "556471"
  },
  {
    "text": "Itt vagyok csak miattad.",
    "source": "tatoeba",
    "upstreamId": "556544"
  },
  {
    "text": "Itt vagyok miattad, szerelmem!",
    "source": "tatoeba",
    "upstreamId": "556547"
  },
  {
    "text": "Én szomorú vagyok nélküled.",
    "source": "tatoeba",
    "upstreamId": "556548"
  },
  {
    "text": "Megőrülök érted!",
    "source": "tatoeba",
    "upstreamId": "556560"
  },
  {
    "text": "Hová mész, őrült vándor?",
    "source": "tatoeba",
    "upstreamId": "556570"
  },
  {
    "text": "Azok a magyar lányok nagyon szépek.",
    "source": "tatoeba",
    "upstreamId": "556575"
  },
  {
    "text": "A halál nem válogatós, mindenkit utolér.",
    "source": "tatoeba",
    "upstreamId": "556585"
  },
  {
    "text": "Fáradt vagyok a betegség és a munka miatt.",
    "source": "tatoeba",
    "upstreamId": "556599"
  },
  {
    "text": "Úgy megzabálnálak téged!",
    "source": "tatoeba",
    "upstreamId": "556608"
  },
  {
    "text": "Mit szeretsz hát, különös idegen?",
    "source": "tatoeba",
    "upstreamId": "556632"
  },
  {
    "text": "Sikerkönyv lett az új regénye.",
    "source": "tatoeba",
    "upstreamId": "557211"
  },
  {
    "text": "Nagy bajban vagyok.",
    "source": "tatoeba",
    "upstreamId": "557515"
  },
  {
    "text": "Beszél németül?",
    "source": "tatoeba",
    "upstreamId": "559068"
  },
  {
    "text": "A győzelmet vagy a vereséget nem csak a hadsereg mérete dönti el.",
    "source": "tatoeba",
    "upstreamId": "559069"
  },
  {
    "text": "A kakaó nagyon keserű lehet.",
    "source": "tatoeba",
    "upstreamId": "559072"
  },
  {
    "text": "Ha szeretnéd, megtanítalak sakkozni.",
    "source": "tatoeba",
    "upstreamId": "559075"
  },
  {
    "text": "Doktor úr, fáj a hasam.",
    "source": "tatoeba",
    "upstreamId": "559078"
  },
  {
    "text": "Este tizenegykor megyek aludni.",
    "source": "tatoeba",
    "upstreamId": "559081"
  },
  {
    "text": "Kérem, várjon fél órát.",
    "source": "tatoeba",
    "upstreamId": "559086"
  },
  {
    "text": "Elég idős vagy ahhoz, hogy magad is tudjad.",
    "source": "tatoeba",
    "upstreamId": "559087"
  },
  {
    "text": "Használhatnám a ceruzádat?",
    "source": "tatoeba",
    "upstreamId": "559089"
  },
  {
    "text": "A késnek éles pengéje van.",
    "source": "tatoeba",
    "upstreamId": "559090"
  },
  {
    "text": "Azt az autót vettem.",
    "source": "tatoeba",
    "upstreamId": "559091"
  },
  {
    "text": "Szabaduljon meg attól a sok régi újságpapírtól.",
    "source": "tatoeba",
    "upstreamId": "559092"
  },
  {
    "text": "Az első randevúnknál elővette a telefonját, hogy üzenetet írjon valakinek. El sem akartam hinni!",
    "source": "tatoeba",
    "upstreamId": "559095"
  },
  {
    "text": "Lassan haladtunk befelé a jéghideg vízben.",
    "source": "tatoeba",
    "upstreamId": "559098"
  },
  {
    "text": "Rengeteg ember volt a parkban.",
    "source": "tatoeba",
    "upstreamId": "559099"
  },
  {
    "text": "Szeretem az almát.",
    "source": "tatoeba",
    "upstreamId": "559100"
  },
  {
    "text": "Ideje ágyba bújnom.",
    "source": "tatoeba",
    "upstreamId": "559101"
  },
  {
    "text": "Elesett, és megsértette a lábát.",
    "source": "tatoeba",
    "upstreamId": "559103"
  },
  {
    "text": "A nővérem tíz centiméterrel magasabb mint én.",
    "source": "tatoeba",
    "upstreamId": "559120"
  },
  {
    "text": "Errefele nyáron is hideg van.",
    "source": "tatoeba",
    "upstreamId": "559123"
  },
  {
    "text": "Ekkor, a legidősebb lány megszólalt -Cukrot akarok!",
    "source": "tatoeba",
    "upstreamId": "559129"
  },
  {
    "text": "Nyáron a turisták elárasztották a várost.",
    "source": "tatoeba",
    "upstreamId": "559132"
  },
  {
    "text": "Vérzik az orrod.",
    "source": "tatoeba",
    "upstreamId": "559134"
  },
  {
    "text": "Betörik a súlyunk alatt a jég.",
    "source": "tatoeba",
    "upstreamId": "559135"
  },
  {
    "text": "A csokoládét kakaóbabból készítik.",
    "source": "tatoeba",
    "upstreamId": "559138"
  },
  {
    "text": "Tehetséges a festészetben.",
    "source": "tatoeba",
    "upstreamId": "559141"
  },
  {
    "text": "Önnek melyek a kedvenc virágai?",
    "source": "tatoeba",
    "upstreamId": "559143"
  },
  {
    "text": "Mi a vércsoportod?",
    "source": "tatoeba",
    "upstreamId": "559146"
  },
  {
    "text": "A víz fogyasztásra alkalmatlan.",
    "source": "tatoeba",
    "upstreamId": "559147"
  },
  {
    "text": "Hogy ejti ki a nevét?",
    "source": "tatoeba",
    "upstreamId": "559154"
  },
  {
    "text": "Vajon miért késik?",
    "source": "tatoeba",
    "upstreamId": "559255"
  },
  {
    "text": "Ha madár lennék, hozzád repülnék.",
    "source": "tatoeba",
    "upstreamId": "559273"
  },
  {
    "text": "A boldogságtól szárnyalok.",
    "source": "tatoeba",
    "upstreamId": "559280"
  },
  {
    "text": "Szeretnék időpontot kérni.",
    "source": "tatoeba",
    "upstreamId": "559289"
  },
  {
    "text": "Bármi is történjék, soha ne add fel.",
    "source": "tatoeba",
    "upstreamId": "559294"
  },
  {
    "text": "Kiolvastad a regényt?",
    "source": "tatoeba",
    "upstreamId": "559311"
  },
  {
    "text": "Nyissa meg a piros színnel bekarikázott fájlt a szövegszerkesztőben.",
    "source": "tatoeba",
    "upstreamId": "559314"
  },
  {
    "text": "Évek kellenek, amíg elsajátítunk egy nyelvet.",
    "source": "tatoeba",
    "upstreamId": "559318"
  },
  {
    "text": "Nem beszéli a nyelvünket.",
    "source": "tatoeba",
    "upstreamId": "559319"
  },
  {
    "text": "Nem értettem, mit mondott.",
    "source": "tatoeba",
    "upstreamId": "559325"
  },
  {
    "text": "Ő tartja az úszás rekordját.",
    "source": "tatoeba",
    "upstreamId": "559326"
  },
  {
    "text": "Ne zavard. Könyvet olvas.",
    "source": "tatoeba",
    "upstreamId": "559327"
  },
  {
    "text": "Ha sietsz, még elérheted a vonatot.",
    "source": "tatoeba",
    "upstreamId": "559328"
  },
  {
    "text": "Kétségbe volt esve férje halálakor.",
    "source": "tatoeba",
    "upstreamId": "559329"
  },
  {
    "text": "Megmostad a fogad?",
    "source": "tatoeba",
    "upstreamId": "559330"
  },
  {
    "text": "Nagyon rosszul érzem magam.",
    "source": "tatoeba",
    "upstreamId": "559331"
  },
  {
    "text": "Hidat emeltek a folyó fölé.",
    "source": "tatoeba",
    "upstreamId": "559332"
  },
  {
    "text": "Van fiútestvéred?",
    "source": "tatoeba",
    "upstreamId": "559333"
  },
  {
    "text": "Nővérem titkárnőként dolgozik a bankban.",
    "source": "tatoeba",
    "upstreamId": "559334"
  },
  {
    "text": "Húszezernél is több amerikai válik gyilkosság áldozatává minden évben.",
    "source": "tatoeba",
    "upstreamId": "559339"
  },
  {
    "text": "Nem igazán megy az úszás.",
    "source": "tatoeba",
    "upstreamId": "559342"
  },
  {
    "text": "Hiroko teljesen egyedül ült ott.",
    "source": "tatoeba",
    "upstreamId": "559343"
  },
  {
    "text": "A szeme elárulta félelmét.",
    "source": "tatoeba",
    "upstreamId": "559346"
  },
  {
    "text": "Egy órát vártam a barátodra.",
    "source": "tatoeba",
    "upstreamId": "559350"
  },
  {
    "text": "Japánban sok a földrengés.",
    "source": "tatoeba",
    "upstreamId": "559351"
  },
  {
    "text": "Az egész csak egy félreértés.",
    "source": "tatoeba",
    "upstreamId": "559356"
  },
  {
    "text": "Fáradt vagyok és pihenésre vágyom.",
    "source": "tatoeba",
    "upstreamId": "559357"
  },
  {
    "text": "Több könyve van, mint amennyit valaha is el tud olvasni.",
    "source": "tatoeba",
    "upstreamId": "559359"
  },
  {
    "text": "Holnap esős idő lesz?",
    "source": "tatoeba",
    "upstreamId": "559361"
  },
  {
    "text": "Meghosszabbodnak a nappalok.",
    "source": "tatoeba",
    "upstreamId": "559362"
  },
  {
    "text": "A szobájában játszik.",
    "source": "tatoeba",
    "upstreamId": "559363"
  },
  {
    "text": "A helyedben elfogadnám az ajánlatát.",
    "source": "tatoeba",
    "upstreamId": "559367"
  },
  {
    "text": "Fél a kutyáktól.",
    "source": "tatoeba",
    "upstreamId": "559369"
  },
  {
    "text": "Szerbiában nagyon lassan haladnak a vonatok.",
    "source": "tatoeba",
    "upstreamId": "559374"
  },
  {
    "text": "A birka ad nekünk gyapjút.",
    "source": "tatoeba",
    "upstreamId": "559386"
  },
  {
    "text": "Ezt az ablakot törte be Jack tegnap.",
    "source": "tatoeba",
    "upstreamId": "559397"
  },
  {
    "text": "Mi a helyzet a halpiacon?",
    "source": "tatoeba",
    "upstreamId": "559400"
  },
  {
    "text": "Szeretem a romantikus regényeket.",
    "source": "tatoeba",
    "upstreamId": "559402"
  },
  {
    "text": "Charles Moore létrehozta a Forth programnyelvet, amely a számítógép teljesítményét nem korlátozta amellett, hogy a programozó hatékonyságán hivatott javítani.",
    "source": "tatoeba",
    "upstreamId": "559416"
  },
  {
    "text": "Naponta lejár teniszedzésekre iskola után.",
    "source": "tatoeba",
    "upstreamId": "559417"
  },
  {
    "text": "Köszönöm a szép képeslapot.",
    "source": "tatoeba",
    "upstreamId": "559419"
  },
  {
    "text": "Mindig viszek magammal egy üveg ásványvizet.",
    "source": "tatoeba",
    "upstreamId": "559422"
  },
  {
    "text": "Még egy korsó sört, legyen szíves.",
    "source": "tatoeba",
    "upstreamId": "559424"
  },
  {
    "text": "Ne felejtsd el, hogy el kell készítenünk a házi feladatunkat.",
    "source": "tatoeba",
    "upstreamId": "559425"
  },
  {
    "text": "Kérem, lekapcsolná a rádiót?",
    "source": "tatoeba",
    "upstreamId": "559426"
  },
  {
    "text": "Édesapám ezen a hétvégén jön haza.",
    "source": "tatoeba",
    "upstreamId": "559427"
  },
  {
    "text": "A kenyér lisztből és vízből készül, amelyet gyakran dolgoznak össze élesztővel.",
    "source": "tatoeba",
    "upstreamId": "559430"
  },
  {
    "text": "A tó legmélyebb része itt van.",
    "source": "tatoeba",
    "upstreamId": "559432"
  },
  {
    "text": "Ki törte be az ablakot?",
    "source": "tatoeba",
    "upstreamId": "559434"
  },
  {
    "text": "Carole három éve tanul spanyolul.",
    "source": "tatoeba",
    "upstreamId": "559436"
  },
  {
    "text": "Megbukott a vizsgán.",
    "source": "tatoeba",
    "upstreamId": "559438"
  },
  {
    "text": "Ne használd tovább azt a szót a férfiakra, hogy csinos.",
    "source": "tatoeba",
    "upstreamId": "559442"
  },
  {
    "text": "Szabad vagy délután?",
    "source": "tatoeba",
    "upstreamId": "559443"
  },
  {
    "text": "Megadná a címét?",
    "source": "tatoeba",
    "upstreamId": "559444"
  },
  {
    "text": "Ne kritizálj engem!",
    "source": "tatoeba",
    "upstreamId": "559446"
  },
  {
    "text": "Megint elvesztette az esernyőjét.",
    "source": "tatoeba",
    "upstreamId": "559449"
  },
  {
    "text": "Amíg elmegy vásárolni, a gyermekei magukra maradnak.",
    "source": "tatoeba",
    "upstreamId": "559450"
  },
  {
    "text": "A világ tele van hülyékkel.",
    "source": "tatoeba",
    "upstreamId": "559453"
  },
  {
    "text": "Ritkán reggelizik.",
    "source": "tatoeba",
    "upstreamId": "559455"
  },
  {
    "text": "Hatvanon túl jár.",
    "source": "tatoeba",
    "upstreamId": "559460"
  },
  {
    "text": "Bezárkózott a szobájába.",
    "source": "tatoeba",
    "upstreamId": "559467"
  },
  {
    "text": "Ő egy nagyon jó tanárnő.",
    "source": "tatoeba",
    "upstreamId": "559469"
  },
  {
    "text": "Mi? Megetted a medve-csokoládémat?",
    "source": "tatoeba",
    "upstreamId": "559479"
  },
  {
    "text": "Most nyáron sokkal kevesebb a csapadék a szokásosnál.",
    "source": "tatoeba",
    "upstreamId": "559484"
  },
  {
    "text": "A kulcs az asztalon van.",
    "source": "tatoeba",
    "upstreamId": "559485"
  },
  {
    "text": "Mosógép híján a ruhák a mosodába mennek.",
    "source": "tatoeba",
    "upstreamId": "559490"
  },
  {
    "text": "Ideje indulni az iskolába.",
    "source": "tatoeba",
    "upstreamId": "559495"
  },
  {
    "text": "Ki vigyáz a gyermekekre?",
    "source": "tatoeba",
    "upstreamId": "559504"
  },
  {
    "text": "A vonat eltűnt a távolban.",
    "source": "tatoeba",
    "upstreamId": "559510"
  },
  {
    "text": "Kiszáradt a szám.",
    "source": "tatoeba",
    "upstreamId": "559517"
  },
  {
    "text": "Ez a betegség gyógyíthatatlan.",
    "source": "tatoeba",
    "upstreamId": "559524"
  },
  {
    "text": "Az állatokat ne etesse.",
    "source": "tatoeba",
    "upstreamId": "559530"
  },
  {
    "text": "Elébb kivel beszéltél?",
    "source": "tatoeba",
    "upstreamId": "559533"
  },
  {
    "text": "Kérlek, bocsáss meg.",
    "source": "tatoeba",
    "upstreamId": "559534"
  },
  {
    "text": "Bárki is legyen a könyv szerzője, az csakis egy nagyszerű író lehet.",
    "source": "tatoeba",
    "upstreamId": "559541"
  },
  {
    "text": "Megtelt a lány szeme könnyekkel.",
    "source": "tatoeba",
    "upstreamId": "559543"
  },
  {
    "text": "Hasonlít az édesanyjára.",
    "source": "tatoeba",
    "upstreamId": "559546"
  },
  {
    "text": "Kapsz egy nyaklevest!",
    "source": "tatoeba",
    "upstreamId": "559548"
  },
  {
    "text": "Minden ló állat, de nem minden állat ló.",
    "source": "tatoeba",
    "upstreamId": "559556"
  },
  {
    "text": "Ebben rengeteg szó ismeretlen.",
    "source": "tatoeba",
    "upstreamId": "559560"
  },
  {
    "text": "A földrengésben sokan otthonaikat vesztették el.",
    "source": "tatoeba",
    "upstreamId": "559649"
  },
  {
    "text": "Jövő szombaton be szeretnélek mutatni a szüleimnek.",
    "source": "tatoeba",
    "upstreamId": "559652"
  },
  {
    "text": "Holnap vasárnap.",
    "source": "tatoeba",
    "upstreamId": "559657"
  },
  {
    "text": "Jack nem engedhet meg magának egy új biciklit.",
    "source": "tatoeba",
    "upstreamId": "559663"
  },
  {
    "text": "Később megbeszéljük a problémát.",
    "source": "tatoeba",
    "upstreamId": "559664"
  },
  {
    "text": "Szökési kísérlete sikeresnek bizonyult.",
    "source": "tatoeba",
    "upstreamId": "559665"
  },
  {
    "text": "Ezt nehezen hiszem el.",
    "source": "tatoeba",
    "upstreamId": "559668"
  },
  {
    "text": "Tom dühös a gyermekeire.",
    "source": "tatoeba",
    "upstreamId": "559669"
  },
  {
    "text": "Lefekvés előtt tudd meg, hogy hol találni a vészkijáratot a hotelben.",
    "source": "tatoeba",
    "upstreamId": "559670"
  },
  {
    "text": "A repülőtéren megpróbáltalak felhívni, de egyetlen pénzes telefonfülke sem működött.",
    "source": "tatoeba",
    "upstreamId": "559671"
  },
  {
    "text": "Nem csoda, hogy olyan mérges.",
    "source": "tatoeba",
    "upstreamId": "559674"
  },
  {
    "text": "A csésze kávéja után belekezdett.",
    "source": "tatoeba",
    "upstreamId": "559675"
  },
  {
    "text": "Szeret édesapja sikeres autókereskedésével dicsekedni.",
    "source": "tatoeba",
    "upstreamId": "559678"
  },
  {
    "text": "Ha megtehetném, világkörüli útra mennék.",
    "source": "tatoeba",
    "upstreamId": "559679"
  },
  {
    "text": "Az orvos szigorú diétát írt elő neki.",
    "source": "tatoeba",
    "upstreamId": "559680"
  },
  {
    "text": "A előadóterem külső falát ellepték a foltok, amit feltehetőleg a savas eső okozott.",
    "source": "tatoeba",
    "upstreamId": "559682"
  },
  {
    "text": "Az iskola közelében lakunk.",
    "source": "tatoeba",
    "upstreamId": "559683"
  },
  {
    "text": "Isten megteremtette a világot.",
    "source": "tatoeba",
    "upstreamId": "559766"
  },
  {
    "text": "A japánok többsége sötét hajú.",
    "source": "tatoeba",
    "upstreamId": "559776"
  },
  {
    "text": "Betegség miatt hiányzik.",
    "source": "tatoeba",
    "upstreamId": "559782"
  },
  {
    "text": "Mivel nagyon szimpatikus nekem, szeretek vele dolgozni.",
    "source": "tatoeba",
    "upstreamId": "559790"
  },
  {
    "text": "Ennek a gyógyszernek nincsenek mellékhatásai.",
    "source": "tatoeba",
    "upstreamId": "559795"
  },
  {
    "text": "Elváltak, és soha nem látták egymást.",
    "source": "tatoeba",
    "upstreamId": "559798"
  },
  {
    "text": "A köd ma olyan sűrű, akárcsak egy tál borsóleves.",
    "source": "tatoeba",
    "upstreamId": "559804"
  },
  {
    "text": "Törölték a nevét a felsorolásból.",
    "source": "tatoeba",
    "upstreamId": "559806"
  },
  {
    "text": "Hármat kérek belőle.",
    "source": "tatoeba",
    "upstreamId": "559808"
  },
  {
    "text": "A felhő elhaladt a hold előtt.",
    "source": "tatoeba",
    "upstreamId": "559817"
  },
  {
    "text": "Láthatom jövő hétfőn?",
    "source": "tatoeba",
    "upstreamId": "559818"
  },
  {
    "text": "Gyakorlat teszi a mestert.",
    "source": "tatoeba",
    "upstreamId": "559820"
  },
  {
    "text": "Mennyiért tisztítják a kabátot?",
    "source": "tatoeba",
    "upstreamId": "559823"
  },
  {
    "text": "Miután elmentek, a part közelében egy lelket sem lehetett találni, a város ciprusaival teljesen halott, a parton még hallani a tenger zúgását, ahogy az a partnak ütközik.",
    "source": "tatoeba",
    "upstreamId": "559838"
  },
  {
    "text": "A táskáját teletömte almával.",
    "source": "tatoeba",
    "upstreamId": "559844"
  },
  {
    "text": "Nem kell az adatoknak hinni. Távol áll mind a valóságtól.",
    "source": "tatoeba",
    "upstreamId": "559846"
  },
  {
    "text": "A teába kevés cukrot és tejet tett.",
    "source": "tatoeba",
    "upstreamId": "559847"
  },
  {
    "text": "Egyre nagyobb divat külföldön üdülni.",
    "source": "tatoeba",
    "upstreamId": "559848"
  },
  {
    "text": "Nem is tudok és nem is hallottam róla semmit.",
    "source": "tatoeba",
    "upstreamId": "559850"
  },
  {
    "text": "Nem bírom tovább ezt a nőszemélyt.",
    "source": "tatoeba",
    "upstreamId": "559851"
  },
  {
    "text": "Üljünk le arra a padra.",
    "source": "tatoeba",
    "upstreamId": "559854"
  },
  {
    "text": "Nem bírtam magam visszatartani a nevetéstől, amikor megláttam, hogyan táncol.",
    "source": "tatoeba",
    "upstreamId": "559855"
  },
  {
    "text": "Hallottam, hogy egy meleg papot tettek meg püspöknek, de kiderült, hogy csak kacsa.",
    "source": "tatoeba",
    "upstreamId": "559859"
  },
  {
    "text": "Sokan kapva kapnának az alkalmon, hogy New York legyen az otthonuk.",
    "source": "tatoeba",
    "upstreamId": "559881"
  },
  {
    "text": "Előlépett a függönyök mögül.",
    "source": "tatoeba",
    "upstreamId": "559887"
  },
  {
    "text": "Az út a domb mentén halad körbe.",
    "source": "tatoeba",
    "upstreamId": "559949"
  },
  {
    "text": "A város nyugati részében él.",
    "source": "tatoeba",
    "upstreamId": "559950"
  },
  {
    "text": "A lényeg, hogy semmit nem tanultál tőle.",
    "source": "tatoeba",
    "upstreamId": "559951"
  },
  {
    "text": "Beismerte, hogy ellopta az aranyat.",
    "source": "tatoeba",
    "upstreamId": "559953"
  },
  {
    "text": "A tükör szilánkjai szétszóródtak a földön.",
    "source": "tatoeba",
    "upstreamId": "559957"
  },
  {
    "text": "Erről a dombról belátni az egész várost.",
    "source": "tatoeba",
    "upstreamId": "559958"
  },
  {
    "text": "Messze vagyunk még a céltól.",
    "source": "tatoeba",
    "upstreamId": "559959"
  },
  {
    "text": "Ne vedd a szívedre!",
    "source": "tatoeba",
    "upstreamId": "559961"
  },
  {
    "text": "Benéztem a könyvesboltba, és vettem egy érdekes könyvet.",
    "source": "tatoeba",
    "upstreamId": "559963"
  },
  {
    "text": "Bill mindig elküldte a születésnapi ajándékát édesanyjának.",
    "source": "tatoeba",
    "upstreamId": "559964"
  },
  {
    "text": "Az út párhuzamosan fut a folyóval.",
    "source": "tatoeba",
    "upstreamId": "559965"
  },
  {
    "text": "Munka után sétálni mentünk.",
    "source": "tatoeba",
    "upstreamId": "559966"
  },
  {
    "text": "Keresne nekem egy ügyvédet?",
    "source": "tatoeba",
    "upstreamId": "559967"
  },
  {
    "text": "A története felevenítette a boldog gyermekkorunkat.",
    "source": "tatoeba",
    "upstreamId": "559971"
  },
  {
    "text": "Édesapám néha magával vitt az irodájába.",
    "source": "tatoeba",
    "upstreamId": "559972"
  },
  {
    "text": "Megöröklöm édesapám üzletét.",
    "source": "tatoeba",
    "upstreamId": "559977"
  },
  {
    "text": "Keress fel holnap, rendben?",
    "source": "tatoeba",
    "upstreamId": "559978"
  },
  {
    "text": "Éhes kiskutya ugat az utcán.",
    "source": "tatoeba",
    "upstreamId": "559980"
  },
  {
    "text": "Régen volt, amikor utoljára láttam önt.",
    "source": "tatoeba",
    "upstreamId": "559985"
  },
  {
    "text": "Párizsba ment művészetet tanulni.",
    "source": "tatoeba",
    "upstreamId": "559986"
  },
  {
    "text": "Furcsa, hogy semmit nem tudsz erről.",
    "source": "tatoeba",
    "upstreamId": "559996"
  },
  {
    "text": "Elvetette az ötletet.",
    "source": "tatoeba",
    "upstreamId": "560006"
  },
  {
    "text": "Mindenki ismerte ezt a dalt.",
    "source": "tatoeba",
    "upstreamId": "560013"
  },
  {
    "text": "Jót tesz nekünk, ha megértünk más kultúrákat.",
    "source": "tatoeba",
    "upstreamId": "560019"
  },
  {
    "text": "Maradj önmagad, ne akarj más lenni.",
    "source": "tatoeba",
    "upstreamId": "560025"
  },
  {
    "text": "A csekket a mai napon kell befizetni.",
    "source": "tatoeba",
    "upstreamId": "560029"
  },
  {
    "text": "Ha megkéred, eljön.",
    "source": "tatoeba",
    "upstreamId": "560032"
  },
  {
    "text": "Nem hagyok soha semmit félben.",
    "source": "tatoeba",
    "upstreamId": "560042"
  },
  {
    "text": "Lucy felkeresett három napja.",
    "source": "tatoeba",
    "upstreamId": "560048"
  },
  {
    "text": "Bárcsak veled tarthatnék az estre.",
    "source": "tatoeba",
    "upstreamId": "560055"
  },
  {
    "text": "Vett neki egy kutyát.",
    "source": "tatoeba",
    "upstreamId": "560073"
  },
  {
    "text": "Szörnyű álom gyötört tegnap éjjel.",
    "source": "tatoeba",
    "upstreamId": "560078"
  },
  {
    "text": "Minden eddigi fáradozásom hiábavaló.",
    "source": "tatoeba",
    "upstreamId": "560091"
  },
  {
    "text": "Erről a könyvről meséltem neked.",
    "source": "tatoeba",
    "upstreamId": "560094"
  },
  {
    "text": "Meg sem köszöni, bármit tehetek én érte.",
    "source": "tatoeba",
    "upstreamId": "560097"
  },
  {
    "text": "Megkérnélek valamire.",
    "source": "tatoeba",
    "upstreamId": "560098"
  },
  {
    "text": "Ma én is álmos vagyok.",
    "source": "tatoeba",
    "upstreamId": "560102"
  },
  {
    "text": "Mindenben a legtöbbet kell nyújtani mindenkinek.",
    "source": "tatoeba",
    "upstreamId": "560105"
  },
  {
    "text": "Egy tanár nem lehet elfogult egyik vagy másik diákjával szemben.",
    "source": "tatoeba",
    "upstreamId": "560115"
  },
  {
    "text": "Hol kaphatok telefonkártyát?",
    "source": "tatoeba",
    "upstreamId": "560131"
  },
  {
    "text": "Soha nem veszíti el a reményt.",
    "source": "tatoeba",
    "upstreamId": "560355"
  },
  {
    "text": "Hölgyeim és uraim, megkezdjük a vetítést.",
    "source": "tatoeba",
    "upstreamId": "560361"
  },
  {
    "text": "Gyermekek csúszkáltak a jégen.",
    "source": "tatoeba",
    "upstreamId": "560362"
  },
  {
    "text": "Nem habozott visszajönni.",
    "source": "tatoeba",
    "upstreamId": "560365"
  },
  {
    "text": "Megvitattuk a jövőre vonatkozó terveinket.",
    "source": "tatoeba",
    "upstreamId": "562984"
  },
  {
    "text": "Három hónapja épült a házunk.",
    "source": "tatoeba",
    "upstreamId": "562985"
  },
  {
    "text": "Őt most választották az iskola igazgatójává.",
    "source": "tatoeba",
    "upstreamId": "562987"
  },
  {
    "text": "A következő állomáson szálljon át.",
    "source": "tatoeba",
    "upstreamId": "562988"
  },
  {
    "text": "Miért nem próbál meg jó benyomást kelteni?",
    "source": "tatoeba",
    "upstreamId": "562990"
  },
  {
    "text": "Eldöntötte, hogy nem tér vissza szülőhazájába.",
    "source": "tatoeba",
    "upstreamId": "562991"
  },
  {
    "text": "Nem tudom megoldani a problémát, túl nehéz nekem.",
    "source": "tatoeba",
    "upstreamId": "562995"
  },
  {
    "text": "Egy igaz barátra találtam benne.",
    "source": "tatoeba",
    "upstreamId": "562997"
  },
  {
    "text": "A lányok egymagukban ültek, mindkettő a másik felé nézett.",
    "source": "tatoeba",
    "upstreamId": "563004"
  },
  {
    "text": "Tudod, hogy mi történhetett?",
    "source": "tatoeba",
    "upstreamId": "563006"
  },
  {
    "text": "A gepárd képes elérni az óránkénti hetven mérföldes sebességet.",
    "source": "tatoeba",
    "upstreamId": "563014"
  },
  {
    "text": "Elsőre senki nem hitt nekem.",
    "source": "tatoeba",
    "upstreamId": "563018"
  },
  {
    "text": "Azonkívül, hogy nagyon hideg egy nap volt, még esett is.",
    "source": "tatoeba",
    "upstreamId": "563025"
  },
  {
    "text": "Kész a reggeli!",
    "source": "tatoeba",
    "upstreamId": "563029"
  },
  {
    "text": "Kérem, itt töltse ki az űrlapot.",
    "source": "tatoeba",
    "upstreamId": "563035"
  },
  {
    "text": "Én a kutyákat, de a nővérem a macskákat szereti.",
    "source": "tatoeba",
    "upstreamId": "563038"
  },
  {
    "text": "A férfi felállt, és belekezdett az énekbe.",
    "source": "tatoeba",
    "upstreamId": "563042"
  },
  {
    "text": "Az autóbalesetben elvesztette az emlékezetét.",
    "source": "tatoeba",
    "upstreamId": "563043"
  },
  {
    "text": "Minden gyermek külön szobát kapott.",
    "source": "tatoeba",
    "upstreamId": "563046"
  },
  {
    "text": "Remélem, végül nem én kerülök ki vesztesen.",
    "source": "tatoeba",
    "upstreamId": "563052"
  },
  {
    "text": "Ön a szerzője ennek a könyvnek?",
    "source": "tatoeba",
    "upstreamId": "563059"
  },
  {
    "text": "Reggelire főleg gyümölcsöt eszem.",
    "source": "tatoeba",
    "upstreamId": "563060"
  },
  {
    "text": "Mikor indul az autóbusz a repülőtérre?",
    "source": "tatoeba",
    "upstreamId": "563061"
  },
  {
    "text": "Kate autóbusszal ment haza.",
    "source": "tatoeba",
    "upstreamId": "563064"
  },
  {
    "text": "Már olvasta a könyvet?",
    "source": "tatoeba",
    "upstreamId": "563065"
  },
  {
    "text": "Többször jártam ott.",
    "source": "tatoeba",
    "upstreamId": "563067"
  },
  {
    "text": "A nagybátyám több évet élt kint külföldön.",
    "source": "tatoeba",
    "upstreamId": "563070"
  },
  {
    "text": "Vele akartam menni, de annyi dolgom volt.",
    "source": "tatoeba",
    "upstreamId": "563071"
  },
  {
    "text": "Remélem, minden összejön neki a kialakult helyzetben.",
    "source": "tatoeba",
    "upstreamId": "563074"
  },
  {
    "text": "Akarom, hogy lássátok egymást.",
    "source": "tatoeba",
    "upstreamId": "563076"
  },
  {
    "text": "Nem válaszolt a kérdésemre.",
    "source": "tatoeba",
    "upstreamId": "563079"
  },
  {
    "text": "Nem emlékszem a nevére.",
    "source": "tatoeba",
    "upstreamId": "563080"
  },
  {
    "text": "Tavaly nyugdíjba vonultam.",
    "source": "tatoeba",
    "upstreamId": "563083"
  },
  {
    "text": "Kaptam tőle egy rotringbelet.",
    "source": "tatoeba",
    "upstreamId": "563086"
  },
  {
    "text": "Éjfél után felébredtünk.",
    "source": "tatoeba",
    "upstreamId": "563089"
  },
  {
    "text": "Egy fiú felém futott.",
    "source": "tatoeba",
    "upstreamId": "563090"
  },
  {
    "text": "Az úszócsapat tagja vagyok.",
    "source": "tatoeba",
    "upstreamId": "563091"
  },
  {
    "text": "Ember tervez, Isten végez.",
    "source": "tatoeba",
    "upstreamId": "563093"
  },
  {
    "text": "Május ötödikén van a születésnapja.",
    "source": "tatoeba",
    "upstreamId": "563094"
  },
  {
    "text": "Koreába szeretnék látogatni.",
    "source": "tatoeba",
    "upstreamId": "563095"
  },
  {
    "text": "Holnap repülök Hanoiba.",
    "source": "tatoeba",
    "upstreamId": "563096"
  },
  {
    "text": "Hogy nevezik Európa legmagasabb hegyét?",
    "source": "tatoeba",
    "upstreamId": "563099"
  },
  {
    "text": "Satoru ötünk közül a leggyorsabb futó.",
    "source": "tatoeba",
    "upstreamId": "563100"
  },
  {
    "text": "Ez az újság ingyenes.",
    "source": "tatoeba",
    "upstreamId": "563103"
  },
  {
    "text": "Maradj csöndben!",
    "source": "tatoeba",
    "upstreamId": "563108"
  },
  {
    "text": "Ittunk egy sócsút a karaoke bárban.",
    "source": "tatoeba",
    "upstreamId": "563139"
  },
  {
    "text": "Tessék, megérkezett a vonat.",
    "source": "tatoeba",
    "upstreamId": "563143"
  },
  {
    "text": "Fordítsa le a mondatot angolra.",
    "source": "tatoeba",
    "upstreamId": "563144"
  },
  {
    "text": "Ebben a boltban több édesség kapható, mint a másikban.",
    "source": "tatoeba",
    "upstreamId": "563145"
  },
  {
    "text": "Napról napra csak szebb lesz.",
    "source": "tatoeba",
    "upstreamId": "563146"
  },
  {
    "text": "Mindig ellenszegül főnökével.",
    "source": "tatoeba",
    "upstreamId": "563149"
  },
  {
    "text": "Édesanyám megterítette az asztalt.",
    "source": "tatoeba",
    "upstreamId": "563151"
  },
  {
    "text": "A vezetéknevem Wan.",
    "source": "tatoeba",
    "upstreamId": "563156"
  },
  {
    "text": "A baba még nem tud járni.",
    "source": "tatoeba",
    "upstreamId": "563166"
  },
  {
    "text": "A fiam kereste a zoknija másik felét.",
    "source": "tatoeba",
    "upstreamId": "563171"
  },
  {
    "text": "Ő egy valódi zseni.",
    "source": "tatoeba",
    "upstreamId": "563175"
  },
  {
    "text": "Nem lehetett látni csillagot az égen.",
    "source": "tatoeba",
    "upstreamId": "563178"
  },
  {
    "text": "Én vasárnap nem megyek iskolába.",
    "source": "tatoeba",
    "upstreamId": "563181"
  },
  {
    "text": "Jó napot kívánok! Hogy van?",
    "source": "tatoeba",
    "upstreamId": "563184"
  },
  {
    "text": "A bal oldalon nyílik egy rejtett átjáró.",
    "source": "tatoeba",
    "upstreamId": "563186"
  },
  {
    "text": "Tegnap édesapámnak segítettem.",
    "source": "tatoeba",
    "upstreamId": "563190"
  },
  {
    "text": "Különben is, már rég megbocsátottam neked.",
    "source": "tatoeba",
    "upstreamId": "563192"
  },
  {
    "text": "Épp zuhanyoztam.",
    "source": "tatoeba",
    "upstreamId": "563202"
  },
  {
    "text": "A gyermek a macskát simogatja.",
    "source": "tatoeba",
    "upstreamId": "563206"
  },
  {
    "text": "A világ egy könyv. Aki nem utazik, csak egy lapját olvasta.",
    "source": "tatoeba",
    "upstreamId": "563215"
  },
  {
    "text": "Egy tea mellett beszélgetett velem.",
    "source": "tatoeba",
    "upstreamId": "563217"
  },
  {
    "text": "Dicsekszik, hogy hat nyelven tud beszélni.",
    "source": "tatoeba",
    "upstreamId": "563336"
  },
  {
    "text": "Az ifjú házasok kéz a kézben jártak.",
    "source": "tatoeba",
    "upstreamId": "563368"
  },
  {
    "text": "A méhek virágról virágra repültek.",
    "source": "tatoeba",
    "upstreamId": "563373"
  },
  {
    "text": "Örömében és szégyenében fülig elvörösödött.",
    "source": "tatoeba",
    "upstreamId": "563378"
  },
  {
    "text": "El kezdett folyni az orrodból a vér.",
    "source": "tatoeba",
    "upstreamId": "563380"
  },
  {
    "text": "Felkiáltott a fájdalomtól.",
    "source": "tatoeba",
    "upstreamId": "563381"
  },
  {
    "text": "Megfáztam, és lázam van.",
    "source": "tatoeba",
    "upstreamId": "563382"
  },
  {
    "text": "A postai rablást fényes nappal követte el a rabló.",
    "source": "tatoeba",
    "upstreamId": "563383"
  },
  {
    "text": "El kell végeznem a mosást, amíg jó az idő.",
    "source": "tatoeba",
    "upstreamId": "563384"
  },
  {
    "text": "Elhízol, ha nem mozogsz többet.",
    "source": "tatoeba",
    "upstreamId": "563385"
  },
  {
    "text": "Sok szerencsét a versenyekhez.",
    "source": "tatoeba",
    "upstreamId": "563389"
  },
  {
    "text": "A bogár még mindig életben van.",
    "source": "tatoeba",
    "upstreamId": "563392"
  },
  {
    "text": "Ki nem állhatom a pókokat. Kiborulok miattuk minden takarításkor.",
    "source": "tatoeba",
    "upstreamId": "563404"
  },
  {
    "text": "A hidegtől a lyukas fogamba belenyilall a fájdalom.",
    "source": "tatoeba",
    "upstreamId": "563409"
  },
  {
    "text": "A szerelem veszedelem.",
    "source": "tatoeba",
    "upstreamId": "566151"
  },
  {
    "text": "Tudsz mindig forrón csókolni?",
    "source": "tatoeba",
    "upstreamId": "566155"
  },
  {
    "text": "Imádlak én kis boszim.",
    "source": "tatoeba",
    "upstreamId": "566159"
  },
  {
    "text": "A nagyapám korán kel.",
    "source": "tatoeba",
    "upstreamId": "566333"
  },
  {
    "text": "Szeretnék pár szót veled váltani.",
    "source": "tatoeba",
    "upstreamId": "566334"
  },
  {
    "text": "Mit parancsol: teát vagy kávét?",
    "source": "tatoeba",
    "upstreamId": "566336"
  },
  {
    "text": "Mely ételek tartalmazzák a legtöbb kalóriát?",
    "source": "tatoeba",
    "upstreamId": "566340"
  },
  {
    "text": "Ki kellene az állatokat engedned a ketrecükből.",
    "source": "tatoeba",
    "upstreamId": "566345"
  },
  {
    "text": "Majdnem elkésett az iskolából.",
    "source": "tatoeba",
    "upstreamId": "566347"
  },
  {
    "text": "Félretesz tíz dollárt minden héten.",
    "source": "tatoeba",
    "upstreamId": "566349"
  },
  {
    "text": "Aljasabb, mint hinnéd.",
    "source": "tatoeba",
    "upstreamId": "566352"
  },
  {
    "text": "A szobám tele van veszélyekkel.",
    "source": "tatoeba",
    "upstreamId": "566361"
  },
  {
    "text": "Valamin agyalsz.",
    "source": "tatoeba",
    "upstreamId": "566363"
  },
  {
    "text": "Próbál leszokni a dohányzásról.",
    "source": "tatoeba",
    "upstreamId": "566367"
  },
  {
    "text": "Történelmi dokumentumokban keres utána, hogy fényt derítsen a rejtély titkára.",
    "source": "tatoeba",
    "upstreamId": "566371"
  },
  {
    "text": "Az édesapám olyan kopasz, akár egy biliárd golyó.",
    "source": "tatoeba",
    "upstreamId": "566386"
  },
  {
    "text": "Ilyenkor zsúfolt a metró.",
    "source": "tatoeba",
    "upstreamId": "566388"
  },
  {
    "text": "A lift hirtelen megállt.",
    "source": "tatoeba",
    "upstreamId": "566391"
  },
  {
    "text": "Milyen szerepet tölt be az Internet az oktatásban?",
    "source": "tatoeba",
    "upstreamId": "566400"
  },
  {
    "text": "Tom egész éjjel csak beszélt.",
    "source": "tatoeba",
    "upstreamId": "566406"
  },
  {
    "text": "Tom egész éjjel jártatta a bagólesőjét.",
    "source": "tatoeba",
    "upstreamId": "566409"
  },
  {
    "text": "Ez a zene mindenkinek az idegeire megy.",
    "source": "tatoeba",
    "upstreamId": "566416"
  },
  {
    "text": "Ez az időjárás rossz hatással van a közérzetedre.",
    "source": "tatoeba",
    "upstreamId": "566417"
  },
  {
    "text": "Annyit ígérj, amit be tudsz tartani!",
    "source": "tatoeba",
    "upstreamId": "566422"
  },
  {
    "text": "Elsírta magát örömében, amikor értesült róla, hogy a fia túlélte a légikatasztrófát.",
    "source": "tatoeba",
    "upstreamId": "566425"
  },
  {
    "text": "Ne vedd az észrevételeit szó szerint.",
    "source": "tatoeba",
    "upstreamId": "566426"
  }
]
