[
  {
    "text": "Той си помисли, че това може да е номер.",
    "source": "tatoeba",
    "upstreamId": "336114"
  },
  {
    "text": "Най-накрая, автобусът спря.",
    "source": "tatoeba",
    "upstreamId": "336115"
  },
  {
    "text": "Искам да уча в чужбина догодина.",
    "source": "tatoeba",
    "upstreamId": "336116"
  },
  {
    "text": "Той би се хванал за всяка сламка.",
    "source": "tatoeba",
    "upstreamId": "336118"
  },
  {
    "text": "Чичо ми почина от рак на стомаха вчера.",
    "source": "tatoeba",
    "upstreamId": "336119"
  },
  {
    "text": "Господине, забравили сте си запалката на масата.",
    "source": "tatoeba",
    "upstreamId": "336120"
  },
  {
    "text": "Тя повиши глас.",
    "source": "tatoeba",
    "upstreamId": "336121"
  },
  {
    "text": "Разчитаме на Пати, защото тя никога не нарушава обещанията си.",
    "source": "tatoeba",
    "upstreamId": "336122"
  },
  {
    "text": "Япония има много отличителни черти.",
    "source": "tatoeba",
    "upstreamId": "336123"
  },
  {
    "text": "Казват, че има заровено съкровище в тази област.",
    "source": "tatoeba",
    "upstreamId": "336124"
  },
  {
    "text": "Каква е тарифата от Осака до Акита?",
    "source": "tatoeba",
    "upstreamId": "336125"
  },
  {
    "text": "Идва му отвътре да говори на френски.",
    "source": "tatoeba",
    "upstreamId": "336126"
  },
  {
    "text": "Често чуваме да казват, че японците са добри работници.",
    "source": "tatoeba",
    "upstreamId": "336169"
  },
  {
    "text": "Бе обречен никога да не я срещне отново.",
    "source": "tatoeba",
    "upstreamId": "336170"
  },
  {
    "text": "Той нахлу в стаята с без да сваля палтото си.",
    "source": "tatoeba",
    "upstreamId": "336187"
  },
  {
    "text": "Баща ми е малко старомоден.",
    "source": "tatoeba",
    "upstreamId": "336189"
  },
  {
    "text": "Моля те, внимавай повече в бъдеще.",
    "source": "tatoeba",
    "upstreamId": "336190"
  },
  {
    "text": "В случай на спешност, свържете се с агента ми.",
    "source": "tatoeba",
    "upstreamId": "336192"
  },
  {
    "text": "Не толкова болестта го повали, колкото мързелът.",
    "source": "tatoeba",
    "upstreamId": "336193"
  },
  {
    "text": "Децата изглеждаха изморени от плуването.",
    "source": "tatoeba",
    "upstreamId": "336194"
  },
  {
    "text": "Не изпускай автобуса.",
    "source": "tatoeba",
    "upstreamId": "336195"
  },
  {
    "text": "Серия от взривове превърна лабораторията в руини.",
    "source": "tatoeba",
    "upstreamId": "336196"
  },
  {
    "text": "Той не каза нищо, което я ядоса.",
    "source": "tatoeba",
    "upstreamId": "336197"
  },
  {
    "text": "Стигнах до гарата, след като влакът тръгна.",
    "source": "tatoeba",
    "upstreamId": "336198"
  },
  {
    "text": "За съжаление не стигнах навреме за речта му.",
    "source": "tatoeba",
    "upstreamId": "336199"
  },
  {
    "text": "Можеш ли да стигнеш навреме?",
    "source": "tatoeba",
    "upstreamId": "336200"
  },
  {
    "text": "От значение е не какво четеш, а как четеш.",
    "source": "tatoeba",
    "upstreamId": "336201"
  },
  {
    "text": "Виж с ушите си.",
    "source": "tatoeba",
    "upstreamId": "337352"
  },
  {
    "text": "Това, което казваш, няма смисъл.",
    "source": "tatoeba",
    "upstreamId": "337353"
  },
  {
    "text": "Танкерът има малък екипаж.",
    "source": "tatoeba",
    "upstreamId": "337355"
  },
  {
    "text": "Вчера, докато си пиехме чая, си поприказвахме.",
    "source": "tatoeba",
    "upstreamId": "369281"
  },
  {
    "text": "В Токио студеният сезон започва в средата на ноември.",
    "source": "tatoeba",
    "upstreamId": "369287"
  },
  {
    "text": "Странен човек вървеше напред-назад по тротоара.",
    "source": "tatoeba",
    "upstreamId": "369290"
  },
  {
    "text": "Ти съгласна ли си с войната или си против нея?",
    "source": "tatoeba",
    "upstreamId": "369291"
  },
  {
    "text": "Само си мечтая!",
    "source": "tatoeba",
    "upstreamId": "369298"
  },
  {
    "text": "Всъщност, изглежда че това е способност, която всички притежават.",
    "source": "tatoeba",
    "upstreamId": "369300"
  },
  {
    "text": "Когато заспиваш, изведнъж някакъв звук отеква и в очите падат искри.",
    "source": "tatoeba",
    "upstreamId": "369304"
  },
  {
    "text": "Колко красиво звучи тази дума!",
    "source": "tatoeba",
    "upstreamId": "369307"
  },
  {
    "text": "Бизнесът ми отново се възражда.",
    "source": "tatoeba",
    "upstreamId": "369308"
  },
  {
    "text": "Нещо днес не се чувствам добре.",
    "source": "tatoeba",
    "upstreamId": "369319"
  },
  {
    "text": "Когато пред теб се появят много врагове, добре е да се обърнеш и да погледнеш назад. Когато се появят и приятели, направи същото.",
    "source": "tatoeba",
    "upstreamId": "369321"
  },
  {
    "text": "Днес за пръв път ядох студени китайски нуделси.",
    "source": "tatoeba",
    "upstreamId": "369323"
  },
  {
    "text": "Аз винаги описвам нещата така, както са си.",
    "source": "tatoeba",
    "upstreamId": "369324"
  },
  {
    "text": "Това си е закон, затова се спазва от всички.",
    "source": "tatoeba",
    "upstreamId": "369325"
  },
  {
    "text": "Ако желаете, бихме ли могли да се срещнем?",
    "source": "tatoeba",
    "upstreamId": "369328"
  },
  {
    "text": "Тази зима ще чакам с нетърпение да посетя вашата страна.",
    "source": "tatoeba",
    "upstreamId": "369340"
  },
  {
    "text": "Не ме гледай така!",
    "source": "tatoeba",
    "upstreamId": "369346"
  },
  {
    "text": "Джейн е от Австралия.",
    "source": "tatoeba",
    "upstreamId": "369351"
  },
  {
    "text": "Джейн се държеше така, сякаш е богаташка.",
    "source": "tatoeba",
    "upstreamId": "369352"
  },
  {
    "text": "Джейн съвсем не беше наясно кога и къде да отиде.",
    "source": "tatoeba",
    "upstreamId": "369353"
  },
  {
    "text": "Джейн си мисли, че би било добре да може да гледа сумо и в Англия.",
    "source": "tatoeba",
    "upstreamId": "369354"
  },
  {
    "text": "Джейн опита доста неща за една година. Аз също.",
    "source": "tatoeba",
    "upstreamId": "369355"
  },
  {
    "text": "Джейн носеше същата панделка като нейната майка.",
    "source": "tatoeba",
    "upstreamId": "369356"
  },
  {
    "text": "Сълзите са оръжието на децата.",
    "source": "tatoeba",
    "upstreamId": "369359"
  },
  {
    "text": "Не мога да си позволя да прахосам и една йена.",
    "source": "tatoeba",
    "upstreamId": "369361"
  },
  {
    "text": "Дори да вали, той ще играе голф.",
    "source": "tatoeba",
    "upstreamId": "369362"
  },
  {
    "text": "Той бързаше, за да е навреме за автобуса.",
    "source": "tatoeba",
    "upstreamId": "369366"
  },
  {
    "text": "Добре съм , не ми е дискомфортно!",
    "source": "tatoeba",
    "upstreamId": "369368"
  },
  {
    "text": "По-евтино е, отколкото си мислех.",
    "source": "tatoeba",
    "upstreamId": "369371"
  },
  {
    "text": "В един миг той изскочи.",
    "source": "tatoeba",
    "upstreamId": "369373"
  },
  {
    "text": "Със сестра ти по едно и също време ли заминахте?",
    "source": "tatoeba",
    "upstreamId": "369375"
  },
  {
    "text": "Лека нощ! Сладки сънища!",
    "source": "tatoeba",
    "upstreamId": "369386"
  },
  {
    "text": "Вчера не стигнахме доникъде с работата, просто непрекъснато допускахме грешки.",
    "source": "tatoeba",
    "upstreamId": "369391"
  },
  {
    "text": "Моят чичо напълно се възстанови от болестта.",
    "source": "tatoeba",
    "upstreamId": "369392"
  },
  {
    "text": "До сутринта ли все така ще ме прегръщаш?",
    "source": "tatoeba",
    "upstreamId": "369394"
  },
  {
    "text": "О, колко сте мил!",
    "source": "tatoeba",
    "upstreamId": "369395"
  },
  {
    "text": "Това място за ядене навън е изключително скъпо.",
    "source": "tatoeba",
    "upstreamId": "369397"
  },
  {
    "text": "Той не обича спорта. Аз също.",
    "source": "tatoeba",
    "upstreamId": "369398"
  },
  {
    "text": "Ако си подготвен, няма да се разболееш.",
    "source": "tatoeba",
    "upstreamId": "369401"
  },
  {
    "text": "Тя винаги идва без закъснение.",
    "source": "tatoeba",
    "upstreamId": "369402"
  },
  {
    "text": "Всеки има право да се радва на свободата си.",
    "source": "tatoeba",
    "upstreamId": "369403"
  },
  {
    "text": "Още в началото всички се убедиха в неговата простодушност.",
    "source": "tatoeba",
    "upstreamId": "369404"
  },
  {
    "text": "Докато съм жив, никакво неудобство няма да ти причиня.",
    "source": "tatoeba",
    "upstreamId": "369405"
  },
  {
    "text": "Върнах се у дома с влака.",
    "source": "tatoeba",
    "upstreamId": "369406"
  },
  {
    "text": "Той си мисли, че разполага със собствения си дом.",
    "source": "tatoeba",
    "upstreamId": "369407"
  },
  {
    "text": "Данъкът се базира на доходите.",
    "source": "tatoeba",
    "upstreamId": "369408"
  },
  {
    "text": "Дали времето ще се задържи така до утре?",
    "source": "tatoeba",
    "upstreamId": "369411"
  },
  {
    "text": "Той нарани рамото си.",
    "source": "tatoeba",
    "upstreamId": "369413"
  },
  {
    "text": "Да обичаш и да си обичан, е най-радостното нещо в живота.",
    "source": "tatoeba",
    "upstreamId": "369417"
  },
  {
    "text": "С желание всичко се постига.",
    "source": "tatoeba",
    "upstreamId": "369418"
  },
  {
    "text": "Ако бях на твое място, бих подал молба за тази работа.",
    "source": "tatoeba",
    "upstreamId": "369419"
  },
  {
    "text": "Това не бях го учил.",
    "source": "tatoeba",
    "upstreamId": "369420"
  },
  {
    "text": "Бях вървял една минута преди да го срещна.",
    "source": "tatoeba",
    "upstreamId": "369421"
  },
  {
    "text": "Утре имам среща с чичо ми.",
    "source": "tatoeba",
    "upstreamId": "369422"
  },
  {
    "text": "По това се разбира неговото невежество.",
    "source": "tatoeba",
    "upstreamId": "369423"
  },
  {
    "text": "Още когато е бил млад, родителите му починали, затова го е отгледал чичо му.",
    "source": "tatoeba",
    "upstreamId": "369424"
  },
  {
    "text": "Във времето на безконечната зима сме.",
    "source": "tatoeba",
    "upstreamId": "369425"
  },
  {
    "text": "Този климатик харчи много ток.",
    "source": "tatoeba",
    "upstreamId": "369426"
  },
  {
    "text": "Баща ми е в Токио и там работи.",
    "source": "tatoeba",
    "upstreamId": "369428"
  },
  {
    "text": "Джак избърса праха от палтото си с четка.",
    "source": "tatoeba",
    "upstreamId": "369429"
  },
  {
    "text": "Колко са големи твоите деца?",
    "source": "tatoeba",
    "upstreamId": "369458"
  },
  {
    "text": "Пробвай да погледнеш под постелката.",
    "source": "tatoeba",
    "upstreamId": "369459"
  },
  {
    "text": "Те бяха измокрени от дъжда.",
    "source": "tatoeba",
    "upstreamId": "369460"
  },
  {
    "text": "Приятелите на Том го наричат „Торба с пари“.",
    "source": "tatoeba",
    "upstreamId": "369461"
  },
  {
    "text": "Той седеше наобиколен от деца.",
    "source": "tatoeba",
    "upstreamId": "369462"
  },
  {
    "text": "Може би той има много приятелки.",
    "source": "tatoeba",
    "upstreamId": "369463"
  },
  {
    "text": "В днешно време младите не се грижат възрастните.",
    "source": "tatoeba",
    "upstreamId": "369464"
  },
  {
    "text": "В галактиката има безброй звезди.",
    "source": "tatoeba",
    "upstreamId": "369465"
  },
  {
    "text": "Бях изключен от училище.",
    "source": "tatoeba",
    "upstreamId": "369466"
  },
  {
    "text": "Тази гледка е толкова красива, че не можеш я описа с думи.",
    "source": "tatoeba",
    "upstreamId": "369467"
  },
  {
    "text": "Чудесна идея ми дойде на ум.",
    "source": "tatoeba",
    "upstreamId": "369468"
  },
  {
    "text": "Засега всичко е наред.",
    "source": "tatoeba",
    "upstreamId": "369470"
  },
  {
    "text": "От този язовир добиваме вода и електроенергия.",
    "source": "tatoeba",
    "upstreamId": "369471"
  },
  {
    "text": "Пред къщата има двор.",
    "source": "tatoeba",
    "upstreamId": "369472"
  },
  {
    "text": "Колумб е вярвал, че Земята е кръгла.",
    "source": "tatoeba",
    "upstreamId": "369473"
  },
  {
    "text": "Там няма ни Господ Бог, ни Буда.",
    "source": "tatoeba",
    "upstreamId": "369474"
  },
  {
    "text": "Предайте домашните си!",
    "source": "tatoeba",
    "upstreamId": "369475"
  },
  {
    "text": "Напук на нея реших да го направя.",
    "source": "tatoeba",
    "upstreamId": "369476"
  },
  {
    "text": "Смит поиска заплатата си.",
    "source": "tatoeba",
    "upstreamId": "369479"
  },
  {
    "text": "Свързах се с вас преди време, обаче отговор не получих.",
    "source": "tatoeba",
    "upstreamId": "369483"
  },
  {
    "text": "Може би и днес сте на работа?",
    "source": "tatoeba",
    "upstreamId": "369488"
  },
  {
    "text": "Първо да си обещаем взаимно доверие.",
    "source": "tatoeba",
    "upstreamId": "369493"
  },
  {
    "text": "Ако има нещо да ме питате, питайте моля.",
    "source": "tatoeba",
    "upstreamId": "369497"
  },
  {
    "text": "Бях си счупил очилата и не можех да виждам черната дъска.",
    "source": "tatoeba",
    "upstreamId": "369512"
  },
  {
    "text": "Той беше ядосан, че никой нищо не каза.",
    "source": "tatoeba",
    "upstreamId": "369519"
  },
  {
    "text": "Неговото изказване не беше убедително.",
    "source": "tatoeba",
    "upstreamId": "369523"
  },
  {
    "text": "Гарата не е далеч от тук.",
    "source": "tatoeba",
    "upstreamId": "369524"
  },
  {
    "text": "Всички хора са равни.",
    "source": "tatoeba",
    "upstreamId": "369527"
  },
  {
    "text": "Мисля си, че ако имах малко повечко пари, бих си купил това нещо.",
    "source": "tatoeba",
    "upstreamId": "369530"
  },
  {
    "text": "Тази къща изгоря.",
    "source": "tatoeba",
    "upstreamId": "369536"
  },
  {
    "text": "Тази работа изисква високи умения.",
    "source": "tatoeba",
    "upstreamId": "369538"
  },
  {
    "text": "Вчера беше горещо.",
    "source": "tatoeba",
    "upstreamId": "369539"
  },
  {
    "text": "Къде смяташ да прекараш почивката си?",
    "source": "tatoeba",
    "upstreamId": "369543"
  },
  {
    "text": "Детето се бои от тъмнината.",
    "source": "tatoeba",
    "upstreamId": "369545"
  },
  {
    "text": "Напълнете резервоара догоре с безоловен бензин.",
    "source": "tatoeba",
    "upstreamId": "369547"
  },
  {
    "text": "Докорът му каза да не яде между основните часове за хранене.",
    "source": "tatoeba",
    "upstreamId": "369552"
  },
  {
    "text": "Навън светлината беше ослепителна, но вътре беше мрачно.",
    "source": "tatoeba",
    "upstreamId": "369647"
  },
  {
    "text": "Тази страна на къщата улавя сутрешното слънце.",
    "source": "tatoeba",
    "upstreamId": "369664"
  },
  {
    "text": "Всяко мнение е смесица от истини и грешки.",
    "source": "tatoeba",
    "upstreamId": "369665"
  },
  {
    "text": "Корабът бе натоварен за два дни.",
    "source": "tatoeba",
    "upstreamId": "369669"
  },
  {
    "text": "Хората са на този свят не за да стават богаташи, а да са щастливи.",
    "source": "tatoeba",
    "upstreamId": "369673"
  },
  {
    "text": "Имаш много приятели, които се тревожат за теб.",
    "source": "tatoeba",
    "upstreamId": "369674"
  },
  {
    "text": "Учителя ни по математика начерта окръжност на черната дъска.",
    "source": "tatoeba",
    "upstreamId": "369775"
  },
  {
    "text": "Тя казва истината.",
    "source": "tatoeba",
    "upstreamId": "369968"
  },
  {
    "text": "Тя притежава таланта да преподава английски.",
    "source": "tatoeba",
    "upstreamId": "369970"
  },
  {
    "text": "Да отидем там да се срещнем с него.",
    "source": "tatoeba",
    "upstreamId": "369971"
  },
  {
    "text": "Нашето училище е използвало неговите методи на обучение.",
    "source": "tatoeba",
    "upstreamId": "369972"
  },
  {
    "text": "Точно преди да съмне, е най-тъмно.",
    "source": "tatoeba",
    "upstreamId": "370037"
  },
  {
    "text": "Той никога не ми се е оплаквал от жена си.",
    "source": "tatoeba",
    "upstreamId": "370039"
  },
  {
    "text": "Ние бихме могли да изиграем по- положителна роля в борбата с глобалното затопляне.",
    "source": "tatoeba",
    "upstreamId": "370040"
  },
  {
    "text": "Днес сутринта първо ходих до пощата и до аптеката, после денят мина без особени ангажименти.",
    "source": "tatoeba",
    "upstreamId": "370042"
  },
  {
    "text": "Премахнете най-долния фонов слой.",
    "source": "tatoeba",
    "upstreamId": "370044"
  },
  {
    "text": "Не е добре да се храниш между основните яденета.",
    "source": "tatoeba",
    "upstreamId": "370060"
  },
  {
    "text": "Тази вечер свободна ли ти е?",
    "source": "tatoeba",
    "upstreamId": "370061"
  },
  {
    "text": "Друго не можах да сторя.",
    "source": "tatoeba",
    "upstreamId": "370062"
  },
  {
    "text": "Първо да се сдобием с продуктите.",
    "source": "tatoeba",
    "upstreamId": "370068"
  },
  {
    "text": "Докъдето стигаше окото, нямаше жива душа.",
    "source": "tatoeba",
    "upstreamId": "370069"
  },
  {
    "text": "Умен е, но не и мъдър.",
    "source": "tatoeba",
    "upstreamId": "370070"
  },
  {
    "text": "Том и Бил достигнаха до края независимо един от друг.",
    "source": "tatoeba",
    "upstreamId": "370071"
  },
  {
    "text": "Обаче искам да разбереш какво ти казвам.",
    "source": "tatoeba",
    "upstreamId": "370073"
  },
  {
    "text": "Ако преброиш само колко бележки съм ти написала.",
    "source": "tatoeba",
    "upstreamId": "370075"
  },
  {
    "text": "Хареса ли ти филмът?",
    "source": "tatoeba",
    "upstreamId": "370076"
  },
  {
    "text": "И друг път е добре, но все пак „желязото се кове докато е горещо\" нали!",
    "source": "tatoeba",
    "upstreamId": "370078"
  },
  {
    "text": "Филмът добър ли беше?",
    "source": "tatoeba",
    "upstreamId": "370079"
  },
  {
    "text": "Станаха три години, откак той почина.",
    "source": "tatoeba",
    "upstreamId": "370081"
  },
  {
    "text": "Тази книга беше толково трудна, че нищо не разбрах.",
    "source": "tatoeba",
    "upstreamId": "370082"
  },
  {
    "text": "Решението дали да отидем или не е твоя отговорност.",
    "source": "tatoeba",
    "upstreamId": "370083"
  },
  {
    "text": "Продължилият пет дни дъжд спря.",
    "source": "tatoeba",
    "upstreamId": "370107"
  },
  {
    "text": "Ти трябва да преодолееш трудностите.",
    "source": "tatoeba",
    "upstreamId": "370109"
  },
  {
    "text": "Аз допусках, че ще дойдеш.",
    "source": "tatoeba",
    "upstreamId": "370184"
  },
  {
    "text": "Питър и Керол не бяха на едно мнение за това къде да прекарат почивката си.",
    "source": "tatoeba",
    "upstreamId": "370193"
  },
  {
    "text": "Какво ли би било да имах кола.",
    "source": "tatoeba",
    "upstreamId": "370198"
  },
  {
    "text": "Колко добре би било да имах кола.",
    "source": "tatoeba",
    "upstreamId": "370199"
  },
  {
    "text": "Трабва бързо да се връщаш.",
    "source": "tatoeba",
    "upstreamId": "370407"
  },
  {
    "text": "Имаш ли брат или сестра? Не, само аз съм.",
    "source": "tatoeba",
    "upstreamId": "370408"
  },
  {
    "text": "Нека да обясним схемата.",
    "source": "tatoeba",
    "upstreamId": "370409"
  },
  {
    "text": "Небето на запад червенее.",
    "source": "tatoeba",
    "upstreamId": "370410"
  },
  {
    "text": "Той можеше да си построи малка къща.",
    "source": "tatoeba",
    "upstreamId": "370961"
  },
  {
    "text": "Секретарката постави писмото в плика.",
    "source": "tatoeba",
    "upstreamId": "370962"
  },
  {
    "text": "В бутилката почти не беше останало мляко.",
    "source": "tatoeba",
    "upstreamId": "370963"
  },
  {
    "text": "Аз обичам да ходя за риба.",
    "source": "tatoeba",
    "upstreamId": "371737"
  },
  {
    "text": "Имаш ли си кола?",
    "source": "tatoeba",
    "upstreamId": "372488"
  },
  {
    "text": "Работя като пчеличка.",
    "source": "tatoeba",
    "upstreamId": "372489"
  },
  {
    "text": "Боб я направи своя жена.",
    "source": "tatoeba",
    "upstreamId": "372490"
  },
  {
    "text": "Отнеха му книжката заради безразсъдно шофиране.",
    "source": "tatoeba",
    "upstreamId": "372491"
  },
  {
    "text": "Дайте ми и на мен мляко.",
    "source": "tatoeba",
    "upstreamId": "372492"
  },
  {
    "text": "Ненадейно птичките изчезнаха от погледа ми.",
    "source": "tatoeba",
    "upstreamId": "372496"
  },
  {
    "text": "Тази кола пречи. Преместете я моля.",
    "source": "tatoeba",
    "upstreamId": "372789"
  },
  {
    "text": "Това са нещата, които купих от Испания.",
    "source": "tatoeba",
    "upstreamId": "372790"
  },
  {
    "text": "Вашето произношение е почти правилно.",
    "source": "tatoeba",
    "upstreamId": "372797"
  },
  {
    "text": "Сега имам настинка.",
    "source": "tatoeba",
    "upstreamId": "372801"
  },
  {
    "text": "Йоко вчера ходи за покупки.",
    "source": "tatoeba",
    "upstreamId": "372805"
  },
  {
    "text": "Тя да не е доктор?",
    "source": "tatoeba",
    "upstreamId": "372806"
  },
  {
    "text": "Той е с лоша репутация.",
    "source": "tatoeba",
    "upstreamId": "372807"
  },
  {
    "text": "Салонът беше украсен с японски картини.",
    "source": "tatoeba",
    "upstreamId": "372809"
  },
  {
    "text": "Искам да имам доверен човек.",
    "source": "tatoeba",
    "upstreamId": "372815"
  },
  {
    "text": "Много от американските престъпници са наркозависими.",
    "source": "tatoeba",
    "upstreamId": "372816"
  },
  {
    "text": "Това бебе още не може да използва лъжица.",
    "source": "tatoeba",
    "upstreamId": "372817"
  },
  {
    "text": "Отсъствах от срещата.",
    "source": "tatoeba",
    "upstreamId": "372818"
  },
  {
    "text": "Благодаря, че ме поканихте на вечеря!",
    "source": "tatoeba",
    "upstreamId": "372819"
  },
  {
    "text": "Тя влезе със сълзи на очи.",
    "source": "tatoeba",
    "upstreamId": "372836"
  },
  {
    "text": "Дадох на всеки поотделно подарък.",
    "source": "tatoeba",
    "upstreamId": "372840"
  },
  {
    "text": "Тя наистина изглежда сладурана.",
    "source": "tatoeba",
    "upstreamId": "372864"
  },
  {
    "text": "Остави тези обувки да се сушат!",
    "source": "tatoeba",
    "upstreamId": "372865"
  },
  {
    "text": "Тук трябва ли да си събувам обувките?",
    "source": "tatoeba",
    "upstreamId": "372866"
  },
  {
    "text": "Тя по-скоро е срамежлива, отколкото асоциална.",
    "source": "tatoeba",
    "upstreamId": "372877"
  },
  {
    "text": "Младежката престъпност продължава да нараства.",
    "source": "tatoeba",
    "upstreamId": "372878"
  },
  {
    "text": "Не съм в състояние да се справя с този проблем.",
    "source": "tatoeba",
    "upstreamId": "372879"
  },
  {
    "text": "Този проблем за мен е неконтролируем.",
    "source": "tatoeba",
    "upstreamId": "372880"
  },
  {
    "text": "Той е футболист.",
    "source": "tatoeba",
    "upstreamId": "372881"
  },
  {
    "text": "По-добре да тръгваш.",
    "source": "tatoeba",
    "upstreamId": "372882"
  },
  {
    "text": "Най-добрият ден в живота ми.",
    "source": "tatoeba",
    "upstreamId": "372915"
  },
  {
    "text": "Напълно съм съгласен с твоето мнение.",
    "source": "tatoeba",
    "upstreamId": "372916"
  },
  {
    "text": "Той никога не е гледал с презрение на бедните хора.",
    "source": "tatoeba",
    "upstreamId": "372917"
  },
  {
    "text": "Всеки ден ние използваме много неща, които е открил Едисон.",
    "source": "tatoeba",
    "upstreamId": "373064"
  },
  {
    "text": "Този обичай се спазва предимно в домовете.",
    "source": "tatoeba",
    "upstreamId": "373065"
  },
  {
    "text": "Дори да загубя работата си, ще мога да се издържам от спестяванията си.",
    "source": "tatoeba",
    "upstreamId": "373066"
  },
  {
    "text": "Мисля, че онзи човек е нелюбезен.",
    "source": "tatoeba",
    "upstreamId": "373067"
  },
  {
    "text": "Церемонията по дипломирането ще се състои на първи март сутринта.",
    "source": "tatoeba",
    "upstreamId": "373068"
  },
  {
    "text": "Имаш ли някаква следа за разгадаването на тази мистерия.",
    "source": "tatoeba",
    "upstreamId": "373084"
  },
  {
    "text": "Кога ще свърши дъждовният сезон?",
    "source": "tatoeba",
    "upstreamId": "373093"
  },
  {
    "text": "Той никога не спазва обещанията си.",
    "source": "tatoeba",
    "upstreamId": "373366"
  },
  {
    "text": "За предпочитане е той да пристигне тук до утре.",
    "source": "tatoeba",
    "upstreamId": "373367"
  },
  {
    "text": "По-добре е да даваш, отколкото да взимаш.",
    "source": "tatoeba",
    "upstreamId": "373368"
  },
  {
    "text": "Пари да имаш, ще изчезнат.",
    "source": "tatoeba",
    "upstreamId": "373369"
  },
  {
    "text": "Обяснете ми причината, поради която те отсъстват!",
    "source": "tatoeba",
    "upstreamId": "373370"
  },
  {
    "text": "Не бих казал, че това е абсолютно сигурно.",
    "source": "tatoeba",
    "upstreamId": "374229"
  },
  {
    "text": "Заради усърдието си той успя.",
    "source": "tatoeba",
    "upstreamId": "375004"
  },
  {
    "text": "Вероятно е изключение в Китай да се яде питка.",
    "source": "tatoeba",
    "upstreamId": "375005"
  },
  {
    "text": "От магазина до вкъщи носех тежкия багаж и си подвиквах хо-о-оп-хоп.",
    "source": "tatoeba",
    "upstreamId": "375006"
  },
  {
    "text": "В Библията така пише.",
    "source": "tatoeba",
    "upstreamId": "375043"
  },
  {
    "text": "Тя може да чете дори такива трудни йероглифи.",
    "source": "tatoeba",
    "upstreamId": "375045"
  },
  {
    "text": "Не са ми останали много пари.",
    "source": "tatoeba",
    "upstreamId": "375048"
  },
  {
    "text": "Изядох сиренето.",
    "source": "tatoeba",
    "upstreamId": "375052"
  },
  {
    "text": "Да ядеш с клечки трудно ли е?",
    "source": "tatoeba",
    "upstreamId": "375056"
  },
  {
    "text": "Тя си има недостатъци, но си я обичам.",
    "source": "tatoeba",
    "upstreamId": "375057"
  },
  {
    "text": "Аз нито пия, нито пуша.",
    "source": "tatoeba",
    "upstreamId": "375058"
  },
  {
    "text": "Извинете ме, че си забравих домашното.",
    "source": "tatoeba",
    "upstreamId": "375063"
  },
  {
    "text": "Искам да имам близък човек, с когото да си говоря.",
    "source": "tatoeba",
    "upstreamId": "375064"
  },
  {
    "text": "Не знам, може би греша, но сякаш сме се срещали по-рано.",
    "source": "tatoeba",
    "upstreamId": "375066"
  },
  {
    "text": "За финансите няма нужда да се тревожиш.",
    "source": "tatoeba",
    "upstreamId": "375078"
  },
  {
    "text": "Години наред кралят управляваше страната.",
    "source": "tatoeba",
    "upstreamId": "375505"
  },
  {
    "text": "Освен че ще присъства на погребението, тя ще трябва да уреди и всичко останало.",
    "source": "tatoeba",
    "upstreamId": "375506"
  },
  {
    "text": "Най-сетне той замина за Америка.",
    "source": "tatoeba",
    "upstreamId": "375507"
  },
  {
    "text": "Не трябва да казваш онова нещо на родителите си.",
    "source": "tatoeba",
    "upstreamId": "375509"
  },
  {
    "text": "Нека след малко да видим какво е положението.",
    "source": "tatoeba",
    "upstreamId": "375510"
  },
  {
    "text": "Искам да поговоря със съпругата ви.",
    "source": "tatoeba",
    "upstreamId": "375511"
  },
  {
    "text": "Това е най- интерената исторая която съм чел някога.",
    "source": "tatoeba",
    "upstreamId": "375512"
  },
  {
    "text": "Трябва да свалиш картите на масата.",
    "source": "tatoeba",
    "upstreamId": "376010"
  },
  {
    "text": "Преди ходихме двете с майка ми на екскурзия в чужбина.",
    "source": "tatoeba",
    "upstreamId": "376012"
  },
  {
    "text": "При смените на сезона физическото ти състояние влошава ли се?",
    "source": "tatoeba",
    "upstreamId": "376014"
  },
  {
    "text": "Как си прекарваше напоследък?",
    "source": "tatoeba",
    "upstreamId": "376016"
  },
  {
    "text": "Не искаш ли да станем приятели?",
    "source": "tatoeba",
    "upstreamId": "376018"
  },
  {
    "text": "Обичаш ли китайска кухня?",
    "source": "tatoeba",
    "upstreamId": "376020"
  },
  {
    "text": "Пластмасовата магнитна карта, на която е запаметен банковият номер, кеш карта ли се нарича?",
    "source": "tatoeba",
    "upstreamId": "376023"
  },
  {
    "text": "Кучето зарови кокал в градината.",
    "source": "tatoeba",
    "upstreamId": "376946"
  },
  {
    "text": "Тази история ме накара да се замисля върху бъдещето на Токио.",
    "source": "tatoeba",
    "upstreamId": "376962"
  },
  {
    "text": "Аз не съм походящ за физически труд.",
    "source": "tatoeba",
    "upstreamId": "376964"
  },
  {
    "text": "Миналата седмица тя роди сладко момиченце.",
    "source": "tatoeba",
    "upstreamId": "376965"
  },
  {
    "text": "Там е къщата, където се роди Том.",
    "source": "tatoeba",
    "upstreamId": "376966"
  },
  {
    "text": "Може ли да погледна в телефонния указател?",
    "source": "tatoeba",
    "upstreamId": "376968"
  },
  {
    "text": "Тя е амбицирана да успее.",
    "source": "tatoeba",
    "upstreamId": "376971"
  },
  {
    "text": "\"Няма по-вредно нещо от цигарите\", казваше докторът.",
    "source": "tatoeba",
    "upstreamId": "377440"
  },
  {
    "text": "Ако настинеш, моля те, пий от това лекарство.",
    "source": "tatoeba",
    "upstreamId": "377442"
  },
  {
    "text": "Това ведро е пробито.",
    "source": "tatoeba",
    "upstreamId": "377443"
  },
  {
    "text": "Ще идем ли някой път заедно да ядем рамен?",
    "source": "tatoeba",
    "upstreamId": "380815"
  },
  {
    "text": "Това е джобен речник.",
    "source": "tatoeba",
    "upstreamId": "382158"
  },
  {
    "text": "„Никога не съм се замислял за това“ каза чичото. „Какво ли да направим?\"",
    "source": "tatoeba",
    "upstreamId": "382161"
  },
  {
    "text": "Понякога се опитваше да не мисли за майка си.",
    "source": "tatoeba",
    "upstreamId": "382163"
  },
  {
    "text": "Снощи написах три писма.",
    "source": "tatoeba",
    "upstreamId": "382164"
  },
  {
    "text": "Станал съм кожа и кости.",
    "source": "tatoeba",
    "upstreamId": "382166"
  },
  {
    "text": "Нейната заплата е висока.",
    "source": "tatoeba",
    "upstreamId": "382167"
  },
  {
    "text": "Той има пълно доверие на търговците.",
    "source": "tatoeba",
    "upstreamId": "382171"
  },
  {
    "text": "Бисквитената къщичка е направена от дърво.",
    "source": "tatoeba",
    "upstreamId": "382174"
  },
  {
    "text": "Те и двамата са добри учители.",
    "source": "tatoeba",
    "upstreamId": "382175"
  },
  {
    "text": "Неговата съдба е предопределена.",
    "source": "tatoeba",
    "upstreamId": "382177"
  },
  {
    "text": "Нямаше никой друг, който да предложи помощ.",
    "source": "tatoeba",
    "upstreamId": "382184"
  },
  {
    "text": "Спокойно мога да кажа , че с настоящите си произведения нейната репутация ще се издигне.",
    "source": "tatoeba",
    "upstreamId": "382191"
  },
  {
    "text": "Някога като имате време, ще се радвам ако хвърлите един поглед.",
    "source": "tatoeba",
    "upstreamId": "382372"
  },
  {
    "text": "Всяка сутрин пресичам жп линията.",
    "source": "tatoeba",
    "upstreamId": "382376"
  },
  {
    "text": "Снощи бях мъртвопиян и си легнах, без да се изкъпя.",
    "source": "tatoeba",
    "upstreamId": "382378"
  },
  {
    "text": "Този човек е доволен от съдбата си.",
    "source": "tatoeba",
    "upstreamId": "382897"
  },
  {
    "text": "Човек трябва да бъде доволен и от малко.",
    "source": "tatoeba",
    "upstreamId": "382900"
  },
  {
    "text": "Ох! Пак забравих, днес е денят, в който трябваше да върна книгата в библоитеката!",
    "source": "tatoeba",
    "upstreamId": "385328"
  },
  {
    "text": "Дали ще ям, или ще пия - все тая.",
    "source": "tatoeba",
    "upstreamId": "385334"
  },
  {
    "text": "Като гледаш онази картина, какво си представяш?",
    "source": "tatoeba",
    "upstreamId": "385360"
  },
  {
    "text": "Той предлага да заминаваме веднага.",
    "source": "tatoeba",
    "upstreamId": "388795"
  },
  {
    "text": "Нямам дребни в мен.",
    "source": "tatoeba",
    "upstreamId": "388872"
  },
  {
    "text": "Трябва да отидеш да се подстрижеш.",
    "source": "tatoeba",
    "upstreamId": "388873"
  },
  {
    "text": "Радвам се да те видя.",
    "source": "tatoeba",
    "upstreamId": "388874"
  },
  {
    "text": "От далече се чуваше виенето на куче.",
    "source": "tatoeba",
    "upstreamId": "392226"
  },
  {
    "text": "Ти чул ли си нещо за вчерашния пожар?",
    "source": "tatoeba",
    "upstreamId": "392227"
  },
  {
    "text": "Моля, хапнете си от всичко, което ви харесва.",
    "source": "tatoeba",
    "upstreamId": "392228"
  },
  {
    "text": "Ако опиташ този сос, ще го намериш за леко солен.",
    "source": "tatoeba",
    "upstreamId": "394592"
  },
  {
    "text": "Във всяка къща си има проблеми.",
    "source": "tatoeba",
    "upstreamId": "398668"
  },
  {
    "text": "Не разбирам това, което казваш.",
    "source": "tatoeba",
    "upstreamId": "398672"
  },
  {
    "text": "Дочух звъненето на телефона.",
    "source": "tatoeba",
    "upstreamId": "402260"
  },
  {
    "text": "Щастливи са тези, които знаят цената на здравето.",
    "source": "tatoeba",
    "upstreamId": "402262"
  },
  {
    "text": "Не оценяваме колко е ценно здравето.",
    "source": "tatoeba",
    "upstreamId": "402263"
  },
  {
    "text": "Започваме да разбираме истинската цена на здравето, когато го загубим.",
    "source": "tatoeba",
    "upstreamId": "402270"
  },
  {
    "text": "От гледна точка на здравето Токио не е толкова добър град за живеене.",
    "source": "tatoeba",
    "upstreamId": "402275"
  },
  {
    "text": "Докато не се разболееш, не знаеш и цената на здравето.",
    "source": "tatoeba",
    "upstreamId": "402280"
  },
  {
    "text": "Добрата стока сама се хвали.",
    "source": "tatoeba",
    "upstreamId": "423232"
  },
  {
    "text": "Казвам се Едгар Дега.",
    "source": "tatoeba",
    "upstreamId": "429477"
  },
  {
    "text": "Казвам се Хисаши.",
    "source": "tatoeba",
    "upstreamId": "429557"
  },
  {
    "text": "Как се казвате?",
    "source": "tatoeba",
    "upstreamId": "429629"
  },
  {
    "text": "Казвам се Ичиро Танака.",
    "source": "tatoeba",
    "upstreamId": "429636"
  },
  {
    "text": "Умирам от глад!",
    "source": "tatoeba",
    "upstreamId": "430270"
  },
  {
    "text": "Имаш ли приятели в Антигуа?",
    "source": "tatoeba",
    "upstreamId": "430273"
  },
  {
    "text": "Не разбирам немски език.",
    "source": "tatoeba",
    "upstreamId": "430526"
  },
  {
    "text": "Едно, две, три, четири, пет, шест, седем, осем, девет, десет.",
    "source": "tatoeba",
    "upstreamId": "431729"
  },
  {
    "text": "Той не вижда с едното око.",
    "source": "tatoeba",
    "upstreamId": "431749"
  },
  {
    "text": "Той винаги излиза от къщи в седем.",
    "source": "tatoeba",
    "upstreamId": "431752"
  },
  {
    "text": "Погрижете се за багажа.",
    "source": "tatoeba",
    "upstreamId": "431754"
  },
  {
    "text": "Кака ми е много умна.",
    "source": "tatoeba",
    "upstreamId": "431768"
  },
  {
    "text": "Това е просто като фасул.",
    "source": "tatoeba",
    "upstreamId": "431773"
  },
  {
    "text": "Ако можех само да имам такива красиви дрехи.",
    "source": "tatoeba",
    "upstreamId": "431776"
  },
  {
    "text": "Много благодаря!",
    "source": "tatoeba",
    "upstreamId": "432816"
  },
  {
    "text": "Къде са яйцата, моля?",
    "source": "tatoeba",
    "upstreamId": "432820"
  },
  {
    "text": "Винаги ще те обичам.",
    "source": "tatoeba",
    "upstreamId": "433101"
  },
  {
    "text": "Виe говорите ли италиански език?",
    "source": "tatoeba",
    "upstreamId": "433116"
  },
  {
    "text": "Часът е вече единайсет.",
    "source": "tatoeba",
    "upstreamId": "433136"
  },
  {
    "text": "Казвам се Джак.",
    "source": "tatoeba",
    "upstreamId": "433157"
  },
  {
    "text": "Италия е много хубава страна.",
    "source": "tatoeba",
    "upstreamId": "433164"
  },
  {
    "text": "Къде са душовете?",
    "source": "tatoeba",
    "upstreamId": "433167"
  },
  {
    "text": "Много ми харесва.",
    "source": "tatoeba",
    "upstreamId": "433806"
  },
  {
    "text": "Днес много е топло.",
    "source": "tatoeba",
    "upstreamId": "433825"
  },
  {
    "text": "Сметката, моля.",
    "source": "tatoeba",
    "upstreamId": "433842"
  },
  {
    "text": "И какво ще правим?",
    "source": "tatoeba",
    "upstreamId": "433845"
  },
  {
    "text": "Боли ме главата.",
    "source": "tatoeba",
    "upstreamId": "433847"
  },
  {
    "text": "Твърде е скъпо!",
    "source": "tatoeba",
    "upstreamId": "433852"
  },
  {
    "text": "\"Благодаря.\" \"Няма защо.\"",
    "source": "tatoeba",
    "upstreamId": "435318"
  },
  {
    "text": "Къде е тоалетната ?",
    "source": "tatoeba",
    "upstreamId": "435516"
  },
  {
    "text": "Той е хубав и разумен.",
    "source": "tatoeba",
    "upstreamId": "437925"
  },
  {
    "text": "Странно, нали? Трябваше вече да сме пристигнали.",
    "source": "tatoeba",
    "upstreamId": "455745"
  },
  {
    "text": "Баща ми беше на път да си тръгне, когато телефонът иззвъня.",
    "source": "tatoeba",
    "upstreamId": "455749"
  },
  {
    "text": "Достатъчно, казах.",
    "source": "tatoeba",
    "upstreamId": "455751"
  },
  {
    "text": "Като си в Рим, прави като римляните.",
    "source": "tatoeba",
    "upstreamId": "455752"
  },
  {
    "text": "Ще имаш ли нещо против ако дойда с теб?",
    "source": "tatoeba",
    "upstreamId": "455755"
  },
  {
    "text": "От какво се интересуваш?",
    "source": "tatoeba",
    "upstreamId": "455757"
  },
  {
    "text": "Каквото и да кажеш, тя е тази за която ще се оженя.",
    "source": "tatoeba",
    "upstreamId": "456739"
  },
  {
    "text": "Trier е най-старият град в Германия.",
    "source": "tatoeba",
    "upstreamId": "456741"
  },
  {
    "text": "Покажи ми какво имаш в джоба си.",
    "source": "tatoeba",
    "upstreamId": "456742"
  },
  {
    "text": "Този въпрос не е лесен.",
    "source": "tatoeba",
    "upstreamId": "456743"
  },
  {
    "text": "Нямам пералня вкъщи, затова трябва да ходя до пералното помещение да пера дрехите си.",
    "source": "tatoeba",
    "upstreamId": "456745"
  },
  {
    "text": "Тя има много красиво лице.",
    "source": "tatoeba",
    "upstreamId": "456747"
  },
  {
    "text": "Тя не ми върна парите.",
    "source": "tatoeba",
    "upstreamId": "456748"
  },
  {
    "text": "Наостри молива си.",
    "source": "tatoeba",
    "upstreamId": "456751"
  },
  {
    "text": "Ще се видим скоро.",
    "source": "tatoeba",
    "upstreamId": "456753"
  },
  {
    "text": "Погледни какво става навън.",
    "source": "tatoeba",
    "upstreamId": "456754"
  },
  {
    "text": "Стая с двойно легло.",
    "source": "tatoeba",
    "upstreamId": "456755"
  },
  {
    "text": "Вдигни ръката си.",
    "source": "tatoeba",
    "upstreamId": "456757"
  },
  {
    "text": "Прочети секцията за обяви, ако търсиш работа.",
    "source": "tatoeba",
    "upstreamId": "456758"
  },
  {
    "text": "Извинете, как да стигна до центъра?",
    "source": "tatoeba",
    "upstreamId": "456759"
  },
  {
    "text": "Моля, говорете по-бавно.",
    "source": "tatoeba",
    "upstreamId": "456760"
  },
  {
    "text": "Моля, кажете ми, когато трябва да сляза.",
    "source": "tatoeba",
    "upstreamId": "456763"
  },
  {
    "text": "Моля, не пипайте.",
    "source": "tatoeba",
    "upstreamId": "456764"
  },
  {
    "text": "Моля, затворете вратата, когато излизате.",
    "source": "tatoeba",
    "upstreamId": "456765"
  },
  {
    "text": "Ако обичате, извикайте ми такси.",
    "source": "tatoeba",
    "upstreamId": "456768"
  },
  {
    "text": "Моля извикайте доктор!",
    "source": "tatoeba",
    "upstreamId": "456769"
  },
  {
    "text": "В Испания хората вечерят много късно.",
    "source": "tatoeba",
    "upstreamId": "456774"
  },
  {
    "text": "Извинете, говорите ли английски?",
    "source": "tatoeba",
    "upstreamId": "456776"
  },
  {
    "text": "Хартия за писма.",
    "source": "tatoeba",
    "upstreamId": "456777"
  },
  {
    "text": "Ау, кафето е много горещо!",
    "source": "tatoeba",
    "upstreamId": "456778"
  },
  {
    "text": "Нашата работа никога не свършва.",
    "source": "tatoeba",
    "upstreamId": "456779"
  },
  {
    "text": "Гостите ни седят в хола.",
    "source": "tatoeba",
    "upstreamId": "456780"
  },
  {
    "text": "Ризите ни са в един цвят, но с различни размери.",
    "source": "tatoeba",
    "upstreamId": "456781"
  },
  {
    "text": "Нашата къща е и твоя къща.",
    "source": "tatoeba",
    "upstreamId": "456782"
  },
  {
    "text": "Хотела ни е на следващата улица.",
    "source": "tatoeba",
    "upstreamId": "456783"
  },
  {
    "text": "Приятелството ни ще трае дълго.",
    "source": "tatoeba",
    "upstreamId": "456784"
  },
  {
    "text": "Напротив, никога не съм казвал такова нещо.",
    "source": "tatoeba",
    "upstreamId": "456786"
  },
  {
    "text": "Чувайки новините, тя припадна.",
    "source": "tatoeba",
    "upstreamId": "456787"
  },
  {
    "text": "Старите хора вървят бавно.",
    "source": "tatoeba",
    "upstreamId": "456788"
  },
  {
    "text": "О, сега разбирам.",
    "source": "tatoeba",
    "upstreamId": "456790"
  },
  {
    "text": "О, Господи. Закъснявам за уроци.",
    "source": "tatoeba",
    "upstreamId": "456792"
  },
  {
    "text": "Нищо повече, благодаря.",
    "source": "tatoeba",
    "upstreamId": "456793"
  },
  {
    "text": "Не и до утре следобед.",
    "source": "tatoeba",
    "upstreamId": "456795"
  },
  {
    "text": "Не много сладко.",
    "source": "tatoeba",
    "upstreamId": "456797"
  },
  {
    "text": "Нито едно от цветята не е изкуствено.",
    "source": "tatoeba",
    "upstreamId": "456800"
  },
  {
    "text": "Никое от децата не седи седнало.",
    "source": "tatoeba",
    "upstreamId": "456804"
  },
  {
    "text": "Нито една от топките не е жълта.",
    "source": "tatoeba",
    "upstreamId": "456807"
  },
  {
    "text": "Не. Прекалено са малки.",
    "source": "tatoeba",
    "upstreamId": "456809"
  },
  {
    "text": "Не. Искам да платя в брой.",
    "source": "tatoeba",
    "upstreamId": "456810"
  },
  {
    "text": "Не, благодаря. Изморен съм.",
    "source": "tatoeba",
    "upstreamId": "456811"
  },
  {
    "text": "Не, не аз. По-малкият ми брат.",
    "source": "tatoeba",
    "upstreamId": "456813"
  },
  {
    "text": "Не благодаря, просто разглеждам.",
    "source": "tatoeba",
    "upstreamId": "456815"
  },
  {
    "text": "В \"Деня на майката\" подарих на майка ми деветнадесет цветя.",
    "source": "tatoeba",
    "upstreamId": "456816"
  },
  {
    "text": "Банката е точно до пощата.",
    "source": "tatoeba",
    "upstreamId": "456817"
  },
  {
    "text": "Вестници се продават на павилиона.",
    "source": "tatoeba",
    "upstreamId": "456819"
  },
  {
    "text": "Въпреки това, искам да отида.",
    "source": "tatoeba",
    "upstreamId": "456820"
  },
  {
    "text": "Мъдрецът ме боли.",
    "source": "tatoeba",
    "upstreamId": "456823"
  },
  {
    "text": "Часовникът ми май изостава.",
    "source": "tatoeba",
    "upstreamId": "456824"
  },
  {
    "text": "Вратовръзката ми е оранжева.",
    "source": "tatoeba",
    "upstreamId": "456827"
  },
  {
    "text": "Телевизора ми е счупен.",
    "source": "tatoeba",
    "upstreamId": "456828"
  },
  {
    "text": "Хората тук са добри.",
    "source": "tatoeba",
    "upstreamId": "456830"
  },
  {
    "text": "Реших да ѝ кажа, че я обичам.",
    "source": "tatoeba",
    "upstreamId": "456831"
  },
  {
    "text": "Стаята му е бъркотия.",
    "source": "tatoeba",
    "upstreamId": "456833"
  },
  {
    "text": "Получих писмото ти.",
    "source": "tatoeba",
    "upstreamId": "456834"
  },
  {
    "text": "Нямаш температура.",
    "source": "tatoeba",
    "upstreamId": "456835"
  },
  {
    "text": "Сам го направих.",
    "source": "tatoeba",
    "upstreamId": "456836"
  },
  {
    "text": "Често прекарвам свободното си време слушайки музика.",
    "source": "tatoeba",
    "upstreamId": "456837"
  },
  {
    "text": "По-големият ми брат тренира джудо. Много е добър.",
    "source": "tatoeba",
    "upstreamId": "456838"
  },
  {
    "text": "Старата ми рокля е синя.",
    "source": "tatoeba",
    "upstreamId": "456839"
  },
  {
    "text": "Новата ми рокля е червена.",
    "source": "tatoeba",
    "upstreamId": "456840"
  },
  {
    "text": "Казвам се Ноелиа, а ти?",
    "source": "tatoeba",
    "upstreamId": "456842"
  },
  {
    "text": "Казвам се Хенри.",
    "source": "tatoeba",
    "upstreamId": "456843"
  },
  {
    "text": "Майка ми е учителка.",
    "source": "tatoeba",
    "upstreamId": "456844"
  },
  {
    "text": "Откраднаха ми телефона.",
    "source": "tatoeba",
    "upstreamId": "456845"
  },
  {
    "text": "Фамилното ми име е Джоунс.",
    "source": "tatoeba",
    "upstreamId": "456846"
  },
  {
    "text": "Приятелят ми се чувства много зле.",
    "source": "tatoeba",
    "upstreamId": "456847"
  },
  {
    "text": "Любимият ми отбор загуби вчера.",
    "source": "tatoeba",
    "upstreamId": "456849"
  },
  {
    "text": "Любимият ми танц е танго.",
    "source": "tatoeba",
    "upstreamId": "456850"
  },
  {
    "text": "Колата ми се счупи.",
    "source": "tatoeba",
    "upstreamId": "456851"
  },
  {
    "text": "Тя загуби дамската си чанта.",
    "source": "tatoeba",
    "upstreamId": "456853"
  },
  {
    "text": "Тя живее в Ню Йорк.",
    "source": "tatoeba",
    "upstreamId": "456854"
  },
  {
    "text": "Тя обича да бяга.",
    "source": "tatoeba",
    "upstreamId": "456855"
  },
  {
    "text": "Тя обича да чете.",
    "source": "tatoeba",
    "upstreamId": "456856"
  },
  {
    "text": "Остави го заради друг мъж.",
    "source": "tatoeba",
    "upstreamId": "456857"
  },
  {
    "text": "Тя е жената, на която дадох подаръка.",
    "source": "tatoeba",
    "upstreamId": "456858"
  },
  {
    "text": "Мислиш ли, че рибата може да чува?",
    "source": "tatoeba",
    "upstreamId": "456859"
  },
  {
    "text": "Вчера той се разходи в парка.",
    "source": "tatoeba",
    "upstreamId": "456860"
  },
  {
    "text": "Трябва да преценяваш сам за себе си.",
    "source": "tatoeba",
    "upstreamId": "456866"
  },
  {
    "text": "Той приближаваше своя край.",
    "source": "tatoeba",
    "upstreamId": "456868"
  },
  {
    "text": "Асансьорът не работи.",
    "source": "tatoeba",
    "upstreamId": "456869"
  },
  {
    "text": "Заради тайфуна не можахме да се приберем в Токио.",
    "source": "tatoeba",
    "upstreamId": "456872"
  },
  {
    "text": "Той е по-умен от мен.",
    "source": "tatoeba",
    "upstreamId": "456873"
  },
  {
    "text": "Десетки хора се събраха пред гарата.",
    "source": "tatoeba",
    "upstreamId": "456875"
  },
  {
    "text": "Ще сляза от влака на следващата спирка.",
    "source": "tatoeba",
    "upstreamId": "456879"
  },
  {
    "text": "Възнамеряваш ли да вземеш участие в събранието?",
    "source": "tatoeba",
    "upstreamId": "456880"
  },
  {
    "text": "Колата не си струва да се ремонтира.",
    "source": "tatoeba",
    "upstreamId": "456882"
  },
  {
    "text": "Не може да се разчита на неговите обещания.",
    "source": "tatoeba",
    "upstreamId": "456884"
  },
  {
    "text": "Скоро ще престанеш да мислиш за нея.",
    "source": "tatoeba",
    "upstreamId": "456888"
  },
  {
    "text": "Ако утре вали, няма да ходим.",
    "source": "tatoeba",
    "upstreamId": "456892"
  },
  {
    "text": "Коя е по-дълга, река Шинано или река Агано?",
    "source": "tatoeba",
    "upstreamId": "456896"
  },
  {
    "text": "В момента съм на летището.",
    "source": "tatoeba",
    "upstreamId": "456899"
  },
  {
    "text": "Беше ме страх да съм сам в тъмното.",
    "source": "tatoeba",
    "upstreamId": "456904"
  },
  {
    "text": "Баща ми има много книги.",
    "source": "tatoeba",
    "upstreamId": "456906"
  },
  {
    "text": "Той отказа предложението. Аз също.",
    "source": "tatoeba",
    "upstreamId": "456911"
  },
  {
    "text": "Тя замина на екскурзия миналата седмица.",
    "source": "tatoeba",
    "upstreamId": "456913"
  },
  {
    "text": "Това което той каза относно момичетата, важи и за момчетата.",
    "source": "tatoeba",
    "upstreamId": "456927"
  },
  {
    "text": "Тя не живее вече там.",
    "source": "tatoeba",
    "upstreamId": "456931"
  },
  {
    "text": "Докторът, когото тя посети, е известен.",
    "source": "tatoeba",
    "upstreamId": "456933"
  },
  {
    "text": "Обичам те толкова, колкото и него.",
    "source": "tatoeba",
    "upstreamId": "456935"
  },
  {
    "text": "Аз съм по-възрастен от него с три години.",
    "source": "tatoeba",
    "upstreamId": "456938"
  },
  {
    "text": "Кошницата беше пълна с ягоди.",
    "source": "tatoeba",
    "upstreamId": "456942"
  },
  {
    "text": "Срещнах я за първи път в Лондон.",
    "source": "tatoeba",
    "upstreamId": "456945"
  },
  {
    "text": "Методът му на преподаване е и добър, и лош.",
    "source": "tatoeba",
    "upstreamId": "456948"
  },
  {
    "text": "В колко часа тръгва следващия влак?",
    "source": "tatoeba",
    "upstreamId": "456954"
  },
  {
    "text": "Това не е вярно.",
    "source": "tatoeba",
    "upstreamId": "528235"
  },
  {
    "text": "Очевидно е, че ти излъга.",
    "source": "tatoeba",
    "upstreamId": "528240"
  },
  {
    "text": "Аз знам истинската причина за неговото отсъствие.",
    "source": "tatoeba",
    "upstreamId": "528250"
  },
  {
    "text": "Да! и в долината на мрачното сянка ако ходя Няма да се уплаша от зло; Защото Ти си с мене; Твоят жезъл и Твоята тояга, те ме утешават.",
    "source": "tatoeba",
    "upstreamId": "532017"
  },
  {
    "text": "Насочи ни по правия път.",
    "source": "tatoeba",
    "upstreamId": "532948"
  },
  {
    "text": "Мария има дълга коса.",
    "source": "tatoeba",
    "upstreamId": "630623"
  },
  {
    "text": "Ще се видим довечера! До скоро!",
    "source": "tatoeba",
    "upstreamId": "630626"
  },
  {
    "text": "Бременна ли си?",
    "source": "tatoeba",
    "upstreamId": "630627"
  },
  {
    "text": "Чаша кафе, моля.",
    "source": "tatoeba",
    "upstreamId": "630636"
  },
  {
    "text": "В Япония практически всяко семейство има пералня.",
    "source": "tatoeba",
    "upstreamId": "630649"
  },
  {
    "text": "Те имат роднинска връзка.",
    "source": "tatoeba",
    "upstreamId": "630651"
  },
  {
    "text": "Моите съболезнования!",
    "source": "tatoeba",
    "upstreamId": "630655"
  },
  {
    "text": "Свършихме наличностите.",
    "source": "tatoeba",
    "upstreamId": "630659"
  },
  {
    "text": "Колкото повече учим, толкова повече научаваме.",
    "source": "tatoeba",
    "upstreamId": "630661"
  },
  {
    "text": "Само да бях по-млад.",
    "source": "tatoeba",
    "upstreamId": "630662"
  },
  {
    "text": "Не е за вярване, че е направил подобно нещо.",
    "source": "tatoeba",
    "upstreamId": "630668"
  },
  {
    "text": "Самолетът беше пренасочен към Мюнхен заради мъглата.",
    "source": "tatoeba",
    "upstreamId": "630671"
  },
  {
    "text": "И аз те обичам.",
    "source": "tatoeba",
    "upstreamId": "630672"
  },
  {
    "text": "Да превеждаш изречения в Tatoeba е по-забавно от това да си пишеш домашното.",
    "source": "tatoeba",
    "upstreamId": "630678"
  },
  {
    "text": "То е на брат ми.",
    "source": "tatoeba",
    "upstreamId": "630679"
  },
  {
    "text": "Тя е доста по-висока от мен.",
    "source": "tatoeba",
    "upstreamId": "630683"
  },
  {
    "text": "Кой е собственикът на тази кола?",
    "source": "tatoeba",
    "upstreamId": "630689"
  },
  {
    "text": "Помолих месаря да премахне всичката мазнина от месото.",
    "source": "tatoeba",
    "upstreamId": "630691"
  },
  {
    "text": "Кучетата не различават цветовете.",
    "source": "tatoeba",
    "upstreamId": "630699"
  },
  {
    "text": "Не е лесно да хванеш заек с голи ръце.",
    "source": "tatoeba",
    "upstreamId": "630703"
  },
  {
    "text": "Тя купи прахосмукачка от супермаркета.",
    "source": "tatoeba",
    "upstreamId": "630706"
  },
  {
    "text": "Ще се опитам да не закъснявам за в бъдеще.",
    "source": "tatoeba",
    "upstreamId": "630719"
  },
  {
    "text": "Не съм толкова приказлив като теб.",
    "source": "tatoeba",
    "upstreamId": "630720"
  },
  {
    "text": "Обикновено се прибират преди нас.",
    "source": "tatoeba",
    "upstreamId": "630722"
  },
  {
    "text": "Когато бях малък, ходех пеш на училище.",
    "source": "tatoeba",
    "upstreamId": "630725"
  },
  {
    "text": "Сигурен съм, че ще успее.",
    "source": "tatoeba",
    "upstreamId": "630731"
  },
  {
    "text": "Вземи хартия и пиши!",
    "source": "tatoeba",
    "upstreamId": "630732"
  },
  {
    "text": "Въпросите й показват, че тя разбира темата много добре.",
    "source": "tatoeba",
    "upstreamId": "630735"
  },
  {
    "text": "Какво прави това лято?",
    "source": "tatoeba",
    "upstreamId": "630737"
  },
  {
    "text": "Ученето на чужд език е интересно занимание.",
    "source": "tatoeba",
    "upstreamId": "630740"
  },
  {
    "text": "Кой град е това?",
    "source": "tatoeba",
    "upstreamId": "630741"
  },
  {
    "text": "Ще се върнем рано или късно.",
    "source": "tatoeba",
    "upstreamId": "630750"
  },
  {
    "text": "Паркът беше пълен с хора.",
    "source": "tatoeba",
    "upstreamId": "630779"
  },
  {
    "text": "Дядо Коледа, искам да получа приятелка за Коледа.",
    "source": "tatoeba",
    "upstreamId": "630802"
  },
  {
    "text": "Ябълките са големи.",
    "source": "tatoeba",
    "upstreamId": "630807"
  },
  {
    "text": "Кола толкова стара е почти безполезна.",
    "source": "tatoeba",
    "upstreamId": "630825"
  },
  {
    "text": "Животът е труден.",
    "source": "tatoeba",
    "upstreamId": "630832"
  },
  {
    "text": "В този ресторант храната е хубава.",
    "source": "tatoeba",
    "upstreamId": "630833"
  },
  {
    "text": "Тя е най-скучното момиче, което някога съм познавал.",
    "source": "tatoeba",
    "upstreamId": "630837"
  },
  {
    "text": "Ако не иска някой да работи, той нито да яде.",
    "source": "tatoeba",
    "upstreamId": "646324"
  },
  {
    "text": "Всички, които се залавят за нож от нож ще загинат.",
    "source": "tatoeba",
    "upstreamId": "646445"
  },
  {
    "text": "Безцветни зелени идеи яростно спят.",
    "source": "tatoeba",
    "upstreamId": "719065"
  },
  {
    "text": "Къде се намира сладкарница?",
    "source": "tatoeba",
    "upstreamId": "739381"
  },
  {
    "text": "Извини ме за късния отговор.",
    "source": "tatoeba",
    "upstreamId": "753123"
  },
  {
    "text": "Обади ми се от Токио.",
    "source": "tatoeba",
    "upstreamId": "753126"
  },
  {
    "text": "Амнезия означава \"загуба на паметта\".",
    "source": "tatoeba",
    "upstreamId": "753132"
  },
  {
    "text": "Няма по-ценно нещо от времето.",
    "source": "tatoeba",
    "upstreamId": "753137"
  },
  {
    "text": "Косата ти има нужда от подстригване.",
    "source": "tatoeba",
    "upstreamId": "753141"
  },
  {
    "text": "Иска ми се да имах приятел като теб.",
    "source": "tatoeba",
    "upstreamId": "760567"
  },
  {
    "text": "Тази група хора дойдоха с нас.",
    "source": "tatoeba",
    "upstreamId": "760568"
  },
  {
    "text": "Той ме взе за англичанин.",
    "source": "tatoeba",
    "upstreamId": "760570"
  },
  {
    "text": "Бил ли си някога в Кюшу?",
    "source": "tatoeba",
    "upstreamId": "760572"
  },
  {
    "text": "Открих едно място, където могат да се купят евтини зеленчуци.",
    "source": "tatoeba",
    "upstreamId": "760575"
  },
  {
    "text": "Това е майка ми.",
    "source": "tatoeba",
    "upstreamId": "760579"
  },
  {
    "text": "По-късно пак ще говорим.",
    "source": "tatoeba",
    "upstreamId": "760580"
  },
  {
    "text": "Наистина не знам.",
    "source": "tatoeba",
    "upstreamId": "760581"
  },
  {
    "text": "Участваш ли в някаква обществено полезна дейност?",
    "source": "tatoeba",
    "upstreamId": "760584"
  },
  {
    "text": "Недей повече да ме възприемаш като \"нормален човек\"!",
    "source": "tatoeba",
    "upstreamId": "760588"
  },
  {
    "text": "Бихте ли ме извинили за момент?",
    "source": "tatoeba",
    "upstreamId": "760590"
  },
  {
    "text": "Откъде произлизат Олимпийските игри?",
    "source": "tatoeba",
    "upstreamId": "760593"
  },
  {
    "text": "Какво ще кажеш да учим заедно в библиотеката?",
    "source": "tatoeba",
    "upstreamId": "760594"
  },
  {
    "text": "Мария е много хубаво момиче.",
    "source": "tatoeba",
    "upstreamId": "760604"
  },
  {
    "text": "Бихме искали да ядем. Можете ли да ни обслужите бързо? Трябва да сме тръгнали до един и половина.",
    "source": "tatoeba",
    "upstreamId": "760609"
  },
  {
    "text": "Кой сезон ти е най-любим?",
    "source": "tatoeba",
    "upstreamId": "760612"
  },
  {
    "text": "Добре дошъл у дома.",
    "source": "tatoeba",
    "upstreamId": "760617"
  },
  {
    "text": "Ако не ти харесва обслужването, не оставяй бакшиш.",
    "source": "tatoeba",
    "upstreamId": "760618"
  },
  {
    "text": "При това положение, много се извинявам, но не мога да приема любезната ви покана.",
    "source": "tatoeba",
    "upstreamId": "760625"
  },
  {
    "text": "Трябва да си лягам.",
    "source": "tatoeba",
    "upstreamId": "760628"
  },
  {
    "text": "Момчето бързо свикна с новия си клас.",
    "source": "tatoeba",
    "upstreamId": "760630"
  },
  {
    "text": "Когато се порежа, кървта ми потича веднага.",
    "source": "tatoeba",
    "upstreamId": "760632"
  },
  {
    "text": "Изглеждаш много блед.",
    "source": "tatoeba",
    "upstreamId": "760633"
  },
  {
    "text": "В Лондон сега е седем часа.",
    "source": "tatoeba",
    "upstreamId": "760634"
  },
  {
    "text": "Ти си образован, това е твоето предимство.",
    "source": "tatoeba",
    "upstreamId": "760637"
  },
  {
    "text": "Забранявам ти да пушиш.",
    "source": "tatoeba",
    "upstreamId": "760639"
  },
  {
    "text": "Ако отида още един път в Нагазаки, ще съм ходил там три пъти.",
    "source": "tatoeba",
    "upstreamId": "760647"
  },
  {
    "text": "Ти не ставаш толкова рано, колкото сестра ти.",
    "source": "tatoeba",
    "upstreamId": "760648"
  },
  {
    "text": "Не излагай снимките на слънце.",
    "source": "tatoeba",
    "upstreamId": "760650"
  },
  {
    "text": "Трудът не е само необходимост, но и удоволствие.",
    "source": "tatoeba",
    "upstreamId": "760651"
  },
  {
    "text": "Това лекарство бързо ли действа?",
    "source": "tatoeba",
    "upstreamId": "760655"
  },
  {
    "text": "Не изпускай тази възможност!",
    "source": "tatoeba",
    "upstreamId": "760656"
  },
  {
    "text": "Един мъж трябва да работи.",
    "source": "tatoeba",
    "upstreamId": "760657"
  },
  {
    "text": "Боли ме задникът.",
    "source": "tatoeba",
    "upstreamId": "760658"
  },
  {
    "text": "Говори по-бавно, ако обичаш.",
    "source": "tatoeba",
    "upstreamId": "760659"
  },
  {
    "text": "Вече съм идвал тук.",
    "source": "tatoeba",
    "upstreamId": "760660"
  },
  {
    "text": "Малко хора мислят така.",
    "source": "tatoeba",
    "upstreamId": "760661"
  },
  {
    "text": "Тази седмица работих през цялото време.",
    "source": "tatoeba",
    "upstreamId": "760662"
  },
  {
    "text": "Тези стари закони бяха отменени.",
    "source": "tatoeba",
    "upstreamId": "760663"
  },
  {
    "text": "Цялата етажерка е пълна с книги.",
    "source": "tatoeba",
    "upstreamId": "760664"
  },
  {
    "text": "Близо ли е хотелът до летището?",
    "source": "tatoeba",
    "upstreamId": "760668"
  },
  {
    "text": "Макар това да значеше, че ще се изложи на опасност, той се реши да отиде там.",
    "source": "tatoeba",
    "upstreamId": "760670"
  },
  {
    "text": "Изглежда той ще ходи в Кашгар.",
    "source": "tatoeba",
    "upstreamId": "760671"
  },
  {
    "text": "Той често не си е вкъщи през уикендите.",
    "source": "tatoeba",
    "upstreamId": "760673"
  },
  {
    "text": "Днес следобед ще идват много хора.",
    "source": "tatoeba",
    "upstreamId": "760676"
  },
  {
    "text": "\"Ще те пусна да преминеш,\" каза Сфинксът, \"ако отговориш правилно на моята гатанка.\"",
    "source": "tatoeba",
    "upstreamId": "760679"
  },
  {
    "text": "Нищо чудно той да е прав.",
    "source": "tatoeba",
    "upstreamId": "760682"
  },
  {
    "text": "Сигурно е, че Луси ще се омъжи за поп певеца.",
    "source": "tatoeba",
    "upstreamId": "760685"
  },
  {
    "text": "Изборът на примерно изречение не беше добър.",
    "source": "tatoeba",
    "upstreamId": "760687"
  },
  {
    "text": "Каквото ще да става, ще ги накараме да говорят.",
    "source": "tatoeba",
    "upstreamId": "760688"
  },
  {
    "text": "Домакинът наряза пуйката за гостите.",
    "source": "tatoeba",
    "upstreamId": "760689"
  },
  {
    "text": "Днес следобед ще ходя на лекар.",
    "source": "tatoeba",
    "upstreamId": "760694"
  },
  {
    "text": "Тираничните правителства често хвърлят политическите си противници в затвора.",
    "source": "tatoeba",
    "upstreamId": "760698"
  },
  {
    "text": "В това малко село живеят много учени.",
    "source": "tatoeba",
    "upstreamId": "760701"
  },
  {
    "text": "Никога не съм разменял и дума с него.",
    "source": "tatoeba",
    "upstreamId": "760705"
  },
  {
    "text": "Тайфунът разруши много къщи.",
    "source": "tatoeba",
    "upstreamId": "760706"
  },
  {
    "text": "Той попита майка ми.",
    "source": "tatoeba",
    "upstreamId": "760708"
  },
  {
    "text": "Той трябваше да плаща висок наем за фермата си.",
    "source": "tatoeba",
    "upstreamId": "760709"
  },
  {
    "text": "Той е над четирисет.",
    "source": "tatoeba",
    "upstreamId": "760710"
  },
  {
    "text": "Докато е учил в средното училище, той не е правил нищо друго, освен да чете романи.",
    "source": "tatoeba",
    "upstreamId": "760712"
  },
  {
    "text": "Имам много снимки.",
    "source": "tatoeba",
    "upstreamId": "760713"
  },
  {
    "text": "Каква е твоята кръвна група?",
    "source": "tatoeba",
    "upstreamId": "760722"
  },
  {
    "text": "В самото начало тази бира едва ли ще ти хареса. Нея трябва да я опиташ много пъти, за да свикнеш с вкуса ѝ.",
    "source": "tatoeba",
    "upstreamId": "760724"
  },
  {
    "text": "Тази зима при нас не е валял много сняг.",
    "source": "tatoeba",
    "upstreamId": "760726"
  },
  {
    "text": "Планът доведе след себе си много проблеми.",
    "source": "tatoeba",
    "upstreamId": "760731"
  },
  {
    "text": "Неговата родна страна е Германия.",
    "source": "tatoeba",
    "upstreamId": "760734"
  },
  {
    "text": "Запазихме тишина в стаята.",
    "source": "tatoeba",
    "upstreamId": "760736"
  },
  {
    "text": "Говориш ли шанхайски?",
    "source": "tatoeba",
    "upstreamId": "760737"
  },
  {
    "text": "Много страни вече са премахнали смъртната присъда.",
    "source": "tatoeba",
    "upstreamId": "760738"
  },
  {
    "text": "Седемте въпроса, които трябва да си зададе един инженер, са: кой, какво, кога, къде, защо, как и колко.",
    "source": "tatoeba",
    "upstreamId": "760742"
  },
  {
    "text": "Мълчанието означава съгласие.",
    "source": "tatoeba",
    "upstreamId": "760743"
  },
  {
    "text": "Тя ни покани да отидем на купона за рождения ѝ ден.",
    "source": "tatoeba",
    "upstreamId": "760744"
  },
  {
    "text": "Закъснях за училище.",
    "source": "tatoeba",
    "upstreamId": "760747"
  },
  {
    "text": "Той има три дъщери, едната от тях е омъжена, а другите две още не са.",
    "source": "tatoeba",
    "upstreamId": "760750"
  },
  {
    "text": "Доколкото знам, той трябва да е роден в Италия.",
    "source": "tatoeba",
    "upstreamId": "760751"
  },
  {
    "text": "Видях я да пресича улицата.",
    "source": "tatoeba",
    "upstreamId": "760752"
  },
  {
    "text": "От гледна точка на възпитанието те не са много по-напред от варварите.",
    "source": "tatoeba",
    "upstreamId": "760754"
  },
  {
    "text": "Няма нищо, не се плаши!",
    "source": "tatoeba",
    "upstreamId": "760757"
  },
  {
    "text": "Рейсовете се движеха почти празни.",
    "source": "tatoeba",
    "upstreamId": "760761"
  },
  {
    "text": "Как да те накарам да ми обърнеш повече внимание?",
    "source": "tatoeba",
    "upstreamId": "760764"
  },
  {
    "text": "Те бяха спасени с хеликоптер.",
    "source": "tatoeba",
    "upstreamId": "760765"
  },
  {
    "text": "Струва ми се, че Вие го харесвате.",
    "source": "tatoeba",
    "upstreamId": "760767"
  },
  {
    "text": "Наоко е плувкиня.",
    "source": "tatoeba",
    "upstreamId": "760769"
  },
  {
    "text": "Не ме интересува CV-то ми.",
    "source": "tatoeba",
    "upstreamId": "760770"
  },
  {
    "text": "Планът ни тръгна зле още от самото началото.",
    "source": "tatoeba",
    "upstreamId": "760772"
  },
  {
    "text": "Катерицата продължаваше напред през силния вятър.",
    "source": "tatoeba",
    "upstreamId": "760774"
  },
  {
    "text": "Много се радваме да видим всички вас тази вечер.",
    "source": "tatoeba",
    "upstreamId": "760776"
  },
  {
    "text": "Разхождахме се по брега на езерото.",
    "source": "tatoeba",
    "upstreamId": "760777"
  },
  {
    "text": "Той вече отдавна знаеше.",
    "source": "tatoeba",
    "upstreamId": "760779"
  },
  {
    "text": "Правителството на тази страна подлага хората на репресии.",
    "source": "tatoeba",
    "upstreamId": "760780"
  },
  {
    "text": "Хайде по-бързо, ако продължаваш да се бавиш, ще закъснеем.",
    "source": "tatoeba",
    "upstreamId": "760781"
  },
  {
    "text": "Той разтърси рамото на сина си.",
    "source": "tatoeba",
    "upstreamId": "760784"
  },
  {
    "text": "Той изглеждаше сякаш някога е бил богат.",
    "source": "tatoeba",
    "upstreamId": "760786"
  },
  {
    "text": "На следващия ден краката доста ме боляха.",
    "source": "tatoeba",
    "upstreamId": "760788"
  },
  {
    "text": "Гребяхме нагоре срещу течението на реката.",
    "source": "tatoeba",
    "upstreamId": "760791"
  },
  {
    "text": "Аз живея в един голям град.",
    "source": "tatoeba",
    "upstreamId": "760795"
  },
  {
    "text": "Опитахме се да го убедим.",
    "source": "tatoeba",
    "upstreamId": "760796"
  },
  {
    "text": "По добре да те откарам у вас.",
    "source": "tatoeba",
    "upstreamId": "760798"
  },
  {
    "text": "Работя в Милано.",
    "source": "tatoeba",
    "upstreamId": "760801"
  },
  {
    "text": "Планът му е да построи мост над тази река.",
    "source": "tatoeba",
    "upstreamId": "760803"
  },
  {
    "text": "Беше толкова хубав ден, че решихме да се разходим.",
    "source": "tatoeba",
    "upstreamId": "760805"
  },
  {
    "text": "Той се почувства уморен.",
    "source": "tatoeba",
    "upstreamId": "760811"
  },
  {
    "text": "Самолетът каца в осем часа.",
    "source": "tatoeba",
    "upstreamId": "760812"
  },
  {
    "text": "Тя не го е виждала от много време.",
    "source": "tatoeba",
    "upstreamId": "760813"
  },
  {
    "text": "Попитахме го как се казва.",
    "source": "tatoeba",
    "upstreamId": "760816"
  },
  {
    "text": "Не искам да те нараня.",
    "source": "tatoeba",
    "upstreamId": "760818"
  },
  {
    "text": "Не искам да купувам този килим.",
    "source": "tatoeba",
    "upstreamId": "760820"
  },
  {
    "text": "Видях една червена кола и една бяла. Червената изглеждаше по-добре от бялата.",
    "source": "tatoeba",
    "upstreamId": "760826"
  },
  {
    "text": "Това е нещо, което не харесвам у него.",
    "source": "tatoeba",
    "upstreamId": "760829"
  },
  {
    "text": "Той играеше футбол с една празна консерва.",
    "source": "tatoeba",
    "upstreamId": "760834"
  },
  {
    "text": "Повечето ученици ходят пеша на училище.",
    "source": "tatoeba",
    "upstreamId": "760836"
  },
  {
    "text": "Тя се събуди сама.",
    "source": "tatoeba",
    "upstreamId": "760849"
  },
  {
    "text": "Опитах всички възможни начини.",
    "source": "tatoeba",
    "upstreamId": "760854"
  },
  {
    "text": "Гражданите на САЩ се чувстват отговорни за демократичното общество, което се крепи върху тях.",
    "source": "tatoeba",
    "upstreamId": "760860"
  },
  {
    "text": "Позволи ми да танцувам с теб.",
    "source": "tatoeba",
    "upstreamId": "760863"
  },
  {
    "text": "Той беше прекрасен човек.",
    "source": "tatoeba",
    "upstreamId": "760865"
  },
  {
    "text": "Момичето е свикнало да си играе само.",
    "source": "tatoeba",
    "upstreamId": "760866"
  },
  {
    "text": "Профсъюзът бе скромен в исканията си за заплатите.",
    "source": "tatoeba",
    "upstreamId": "760869"
  },
  {
    "text": "Тази работа може да се свърши за седмица.",
    "source": "tatoeba",
    "upstreamId": "760871"
  },
  {
    "text": "След като съпругът ѝ умря, бебето ѝ стана всичко за нея.",
    "source": "tatoeba",
    "upstreamId": "760875"
  },
  {
    "text": "Нейната работа е по-добра от моята.",
    "source": "tatoeba",
    "upstreamId": "760881"
  },
  {
    "text": "Това цвете е най-красивото от всички цветя.",
    "source": "tatoeba",
    "upstreamId": "760884"
  },
  {
    "text": "Вероятно утре ще вали сняг.",
    "source": "tatoeba",
    "upstreamId": "760885"
  },
  {
    "text": "Не всяка лампа е вълшебна.",
    "source": "tatoeba",
    "upstreamId": "760887"
  },
  {
    "text": "Той често пише на родителите си.",
    "source": "tatoeba",
    "upstreamId": "760888"
  },
  {
    "text": "Къде намери този портфейл?",
    "source": "tatoeba",
    "upstreamId": "760891"
  },
  {
    "text": "Това е работата, която аз сам избрах.",
    "source": "tatoeba",
    "upstreamId": "760894"
  },
  {
    "text": "Стотици хора са умрели от глад в този район.",
    "source": "tatoeba",
    "upstreamId": "760895"
  },
  {
    "text": "Той не е толкова нетърпелив, колкото баща си.",
    "source": "tatoeba",
    "upstreamId": "760896"
  },
  {
    "text": "Той нямаше представа кога да започне.",
    "source": "tatoeba",
    "upstreamId": "760897"
  },
  {
    "text": "Коя година е сега?",
    "source": "tatoeba",
    "upstreamId": "760899"
  },
  {
    "text": "Той никога повече нямаше да се завърне в родния си град.",
    "source": "tatoeba",
    "upstreamId": "760903"
  },
  {
    "text": "Време е за ставане.",
    "source": "tatoeba",
    "upstreamId": "760904"
  },
  {
    "text": "Къде се намира пощата?",
    "source": "tatoeba",
    "upstreamId": "760907"
  },
  {
    "text": "Баба ми е най-възрастната в този град.",
    "source": "tatoeba",
    "upstreamId": "760909"
  },
  {
    "text": "Луната сияе ярко.",
    "source": "tatoeba",
    "upstreamId": "760910"
  },
  {
    "text": "Може ли да си тръгна сега?",
    "source": "tatoeba",
    "upstreamId": "760911"
  },
  {
    "text": "Искам една стая от задната страна.",
    "source": "tatoeba",
    "upstreamId": "760914"
  },
  {
    "text": "Този уикенд, ако може.",
    "source": "tatoeba",
    "upstreamId": "760915"
  },
  {
    "text": "Ще обядваме около дванайсет часа.",
    "source": "tatoeba",
    "upstreamId": "760917"
  },
  {
    "text": "Болница, в която има какви ли не правила, но няма правило за пазене на тишина?!",
    "source": "tatoeba",
    "upstreamId": "760921"
  },
  {
    "text": "Някои книги си струва да се препрочитат отново и отново.",
    "source": "tatoeba",
    "upstreamId": "760923"
  },
  {
    "text": "На следващата сутрин много ни се спеше.",
    "source": "tatoeba",
    "upstreamId": "760925"
  },
  {
    "text": "Той гори от ентусиазъм.",
    "source": "tatoeba",
    "upstreamId": "760929"
  },
  {
    "text": "Този студент учи социология.",
    "source": "tatoeba",
    "upstreamId": "760930"
  },
  {
    "text": "Няма начин да се свържете с него.",
    "source": "tatoeba",
    "upstreamId": "760932"
  },
  {
    "text": "Искате ли кафе?",
    "source": "tatoeba",
    "upstreamId": "760934"
  },
  {
    "text": "Еленът бягаше сам.",
    "source": "tatoeba",
    "upstreamId": "760937"
  },
  {
    "text": "\"Каква марка е колата ти?\" \"Форд е.\"",
    "source": "tatoeba",
    "upstreamId": "760940"
  },
  {
    "text": "Просто застанете там, ако обичате.",
    "source": "tatoeba",
    "upstreamId": "760942"
  },
  {
    "text": "Да го накарам ли да дойде с теб?",
    "source": "tatoeba",
    "upstreamId": "760944"
  },
  {
    "text": "Пет дена след като тя завърши, дъщеря ми отлетя от летище Осака към Германия.",
    "source": "tatoeba",
    "upstreamId": "760945"
  },
  {
    "text": "Скрежта е замръзнала роса.",
    "source": "tatoeba",
    "upstreamId": "760947"
  },
  {
    "text": "Кобе е градът, където съм роден.",
    "source": "tatoeba",
    "upstreamId": "760948"
  },
  {
    "text": "Защо боядиса пейката в червено?",
    "source": "tatoeba",
    "upstreamId": "760955"
  },
  {
    "text": "Бих бил много благодарен, ако ми помогнеш.",
    "source": "tatoeba",
    "upstreamId": "760956"
  },
  {
    "text": "Тя наведе засрамено глава.",
    "source": "tatoeba",
    "upstreamId": "760959"
  },
  {
    "text": "Той не знаеше, че Шекспир е написал \"Ромео и Жулиета\".",
    "source": "tatoeba",
    "upstreamId": "760961"
  },
  {
    "text": "Когато свърша с работата, ще ти се обадя.",
    "source": "tatoeba",
    "upstreamId": "760966"
  },
  {
    "text": "Мишо беше много любезен. Оправи ми колата безплатно.",
    "source": "tatoeba",
    "upstreamId": "760969"
  },
  {
    "text": "Не забравяй да ми се обадиш утре сутринта.",
    "source": "tatoeba",
    "upstreamId": "760971"
  },
  {
    "text": "Моментът на слава за Ханшин не продължи дълго. Те набързо бяха изместени от първото място.",
    "source": "tatoeba",
    "upstreamId": "760975"
  },
  {
    "text": "Твоите коментари винаги са ми били много полезни.",
    "source": "tatoeba",
    "upstreamId": "760976"
  },
  {
    "text": "Пушенето не влияе добре на здравето.",
    "source": "tatoeba",
    "upstreamId": "760979"
  },
  {
    "text": "Изглеждаш ужасно.",
    "source": "tatoeba",
    "upstreamId": "760981"
  },
  {
    "text": "Щом няма живот след смъртта, по-добре направи нещо с този си живот.",
    "source": "tatoeba",
    "upstreamId": "760987"
  },
  {
    "text": "Това е възможно най-лошото.",
    "source": "tatoeba",
    "upstreamId": "760988"
  },
  {
    "text": "Ако закъснееш с предаването на контролното, то няма да бъде прието.",
    "source": "tatoeba",
    "upstreamId": "760991"
  },
  {
    "text": "Думата \"rook\" идва от санскрит и означава \"колесница\".",
    "source": "tatoeba",
    "upstreamId": "760992"
  },
  {
    "text": "Ще дойде време, когато тя ще съжалява за това, което е казала.",
    "source": "tatoeba",
    "upstreamId": "760994"
  },
  {
    "text": "Хората са го имали за велик учен.",
    "source": "tatoeba",
    "upstreamId": "760995"
  },
  {
    "text": "Не знам на кого да дам този подарък: на момичето или момчето?",
    "source": "tatoeba",
    "upstreamId": "761000"
  },
  {
    "text": "Качихме се на рейса в Шинджуку.",
    "source": "tatoeba",
    "upstreamId": "761005"
  },
  {
    "text": "Гласът ѝ все още отеква в ушите ми.",
    "source": "tatoeba",
    "upstreamId": "761016"
  },
  {
    "text": "Той седна начело на масата.",
    "source": "tatoeba",
    "upstreamId": "761021"
  },
  {
    "text": "Приключи ли със закуската?",
    "source": "tatoeba",
    "upstreamId": "761022"
  },
  {
    "text": "Трябва да призная, че хъркам.",
    "source": "tatoeba",
    "upstreamId": "761025"
  },
  {
    "text": "Мисля, че тичането е добро упражнение.",
    "source": "tatoeba",
    "upstreamId": "761028"
  },
  {
    "text": "Не ме включвай в този план. Не искам да участвам.",
    "source": "tatoeba",
    "upstreamId": "761029"
  },
  {
    "text": "Имам чувството, че той няма да ми позволи да се откача толкова лесно.",
    "source": "tatoeba",
    "upstreamId": "761030"
  },
  {
    "text": "След като запалиш фитила ще имаш петнайсет секунди, за да отидеш на безопасно място.",
    "source": "tatoeba",
    "upstreamId": "761031"
  },
  {
    "text": "Той не може да си позволи нова кола.",
    "source": "tatoeba",
    "upstreamId": "761032"
  },
  {
    "text": "Искам да отида в Австрия, за да уча музика.",
    "source": "tatoeba",
    "upstreamId": "761036"
  },
  {
    "text": "Боклукът ни се събира три пъти седмично.",
    "source": "tatoeba",
    "upstreamId": "761037"
  },
  {
    "text": "Беше красив слънчев ден.",
    "source": "tatoeba",
    "upstreamId": "761039"
  },
  {
    "text": "Тя все още ще седи там и ще чете книга.",
    "source": "tatoeba",
    "upstreamId": "761040"
  },
  {
    "text": "Стомахът ми се е свил от глад.",
    "source": "tatoeba",
    "upstreamId": "761043"
  },
  {
    "text": "Новоизлюпените пилета още не са си отворили очите.",
    "source": "tatoeba",
    "upstreamId": "761049"
  },
  {
    "text": "Все още имам желанието да отида да уча една година в чужбина.",
    "source": "tatoeba",
    "upstreamId": "761050"
  },
  {
    "text": "Опитвам се да спестя пари.",
    "source": "tatoeba",
    "upstreamId": "761051"
  },
  {
    "text": "Искаш да си тръгнеш в последния момент?",
    "source": "tatoeba",
    "upstreamId": "761054"
  },
  {
    "text": "Времето се развали.",
    "source": "tatoeba",
    "upstreamId": "761055"
  },
  {
    "text": "Силният вятър ми отвя чадъра.",
    "source": "tatoeba",
    "upstreamId": "761059"
  },
  {
    "text": "Скоро идва Коледа.",
    "source": "tatoeba",
    "upstreamId": "761060"
  },
  {
    "text": "На него не му пука за пари.",
    "source": "tatoeba",
    "upstreamId": "761063"
  },
  {
    "text": "Парите са по-тежки от живота.",
    "source": "tatoeba",
    "upstreamId": "761065"
  },
  {
    "text": "Не исках да подслушвам, но чух какво казахте.",
    "source": "tatoeba",
    "upstreamId": "761067"
  },
  {
    "text": "Не исках да направя нищо лошо.",
    "source": "tatoeba",
    "upstreamId": "761069"
  },
  {
    "text": "Ах, колко жалко!",
    "source": "tatoeba",
    "upstreamId": "761070"
  },
  {
    "text": "Ей, погледни на нещата откъм положителната им страна! Поне не закъсня за работа!",
    "source": "tatoeba",
    "upstreamId": "761071"
  },
  {
    "text": "Мъжете правят къщи, жените – домове.",
    "source": "tatoeba",
    "upstreamId": "761072"
  },
  {
    "text": "Наложил съм си като правило да не седя до късно.",
    "source": "tatoeba",
    "upstreamId": "761073"
  },
  {
    "text": "Децата мислеха, че родителите им са направени от пари.",
    "source": "tatoeba",
    "upstreamId": "761075"
  },
  {
    "text": "От коя страна си?",
    "source": "tatoeba",
    "upstreamId": "761122"
  },
  {
    "text": "От коя страна идваш?",
    "source": "tatoeba",
    "upstreamId": "761123"
  },
  {
    "text": "От къде си в Канада?",
    "source": "tatoeba",
    "upstreamId": "761133"
  },
  {
    "text": "Тайландският е официалният език на Тайланд.",
    "source": "tatoeba",
    "upstreamId": "761156"
  },
  {
    "text": "Скъперникът трупа пари не защото е благоразумен, а защото е алчен.",
    "source": "tatoeba",
    "upstreamId": "761706"
  },
  {
    "text": "\"Знаеш ли телефонния код на Ливан?\" попита Дима.",
    "source": "tatoeba",
    "upstreamId": "761707"
  },
  {
    "text": "Това, че той не дойде, за мен показва незаинтересованост.",
    "source": "tatoeba",
    "upstreamId": "761709"
  },
  {
    "text": "Няма пряк път към успеха.",
    "source": "tatoeba",
    "upstreamId": "761715"
  },
  {
    "text": "Аз съм честен човек.",
    "source": "tatoeba",
    "upstreamId": "761717"
  },
  {
    "text": "Вчера купих този принтер.",
    "source": "tatoeba",
    "upstreamId": "761721"
  },
  {
    "text": "Интересуваш ли се от политика?",
    "source": "tatoeba",
    "upstreamId": "761722"
  },
  {
    "text": "Отидох на четвъртия етаж с асансьора.",
    "source": "tatoeba",
    "upstreamId": "761723"
  },
  {
    "text": "Извинявай, не успях да се удържа.",
    "source": "tatoeba",
    "upstreamId": "761724"
  },
  {
    "text": "Изгубих си молива.",
    "source": "tatoeba",
    "upstreamId": "761725"
  },
  {
    "text": "От изражението им става ясно, че вероятно са загубили.",
    "source": "tatoeba",
    "upstreamId": "761728"
  },
  {
    "text": "Беше една тиха нощ.",
    "source": "tatoeba",
    "upstreamId": "761729"
  },
  {
    "text": "Спестявам парите, които имам.",
    "source": "tatoeba",
    "upstreamId": "761730"
  },
  {
    "text": "Кен, време е да си лягаш вече.",
    "source": "tatoeba",
    "upstreamId": "761732"
  },
  {
    "text": "Под бюрото има котка.",
    "source": "tatoeba",
    "upstreamId": "761734"
  },
  {
    "text": "Книгата падна от рафта.",
    "source": "tatoeba",
    "upstreamId": "761735"
  },
  {
    "text": "Баща ми често се гневи.",
    "source": "tatoeba",
    "upstreamId": "761736"
  },
  {
    "text": "Толкова съм уморен, че не мога да се катеря повече.",
    "source": "tatoeba",
    "upstreamId": "761740"
  },
  {
    "text": "Парите са последното нещо, което той иска.",
    "source": "tatoeba",
    "upstreamId": "761741"
  },
  {
    "text": "Кой е собственикът на тази къща?",
    "source": "tatoeba",
    "upstreamId": "761742"
  },
  {
    "text": "Навикът е втора природа.",
    "source": "tatoeba",
    "upstreamId": "761743"
  },
  {
    "text": "Сънят е най-големият крадец, открадна половината ми живот.",
    "source": "tatoeba",
    "upstreamId": "761745"
  },
  {
    "text": "Тя обмисля да отиде на пътешествие.",
    "source": "tatoeba",
    "upstreamId": "761747"
  },
  {
    "text": "Той е по-добър по математика от мен.",
    "source": "tatoeba",
    "upstreamId": "761748"
  },
  {
    "text": "Братчето ми още спи.",
    "source": "tatoeba",
    "upstreamId": "761749"
  },
  {
    "text": "Искам да стана лекар.",
    "source": "tatoeba",
    "upstreamId": "761751"
  },
  {
    "text": "Съгласен съм да стоиш тук до нас.",
    "source": "tatoeba",
    "upstreamId": "761752"
  },
  {
    "text": "Аз съм изключително объркан.",
    "source": "tatoeba",
    "upstreamId": "761754"
  },
  {
    "text": "Никак не ми беше лесно да открия вашата къща.",
    "source": "tatoeba",
    "upstreamId": "761755"
  },
  {
    "text": "Моля, приемете този малък подарък!",
    "source": "tatoeba",
    "upstreamId": "761756"
  },
  {
    "text": "Искреността е важен добродетел.",
    "source": "tatoeba",
    "upstreamId": "761758"
  },
  {
    "text": "Стойността на един човек се определя не от това какво притежава, а от това какъв е той самият.",
    "source": "tatoeba",
    "upstreamId": "761759"
  },
  {
    "text": "Служителката обяви, че клиентите трябва да се наредят един след друг.",
    "source": "tatoeba",
    "upstreamId": "761760"
  },
  {
    "text": "Видях луната над покрива.",
    "source": "tatoeba",
    "upstreamId": "761762"
  },
  {
    "text": "Да, разбира се.",
    "source": "tatoeba",
    "upstreamId": "761763"
  },
  {
    "text": "Думите бяха написани неправилно.",
    "source": "tatoeba",
    "upstreamId": "761765"
  },
  {
    "text": "Имаме много за домашно.",
    "source": "tatoeba",
    "upstreamId": "761767"
  },
  {
    "text": "Нямам я тази книга.",
    "source": "tatoeba",
    "upstreamId": "761768"
  },
  {
    "text": "Тя е виновна за измама.",
    "source": "tatoeba",
    "upstreamId": "761769"
  },
  {
    "text": "Спечели първата награда.",
    "source": "tatoeba",
    "upstreamId": "761770"
  },
  {
    "text": "Защо не дойдете да танцувате с мен?",
    "source": "tatoeba",
    "upstreamId": "761771"
  },
  {
    "text": "Как намираш храна в космоса?",
    "source": "tatoeba",
    "upstreamId": "761773"
  },
  {
    "text": "Виждал ли си фотоапарата ми?",
    "source": "tatoeba",
    "upstreamId": "761774"
  },
  {
    "text": "Тенисът е любимият ми спорт.",
    "source": "tatoeba",
    "upstreamId": "761778"
  },
  {
    "text": "Защо не носиш летни дрехи?",
    "source": "tatoeba",
    "upstreamId": "761779"
  },
  {
    "text": "Днес е национален празник.",
    "source": "tatoeba",
    "upstreamId": "761781"
  },
  {
    "text": "Говоря арабски, но уча английски.",
    "source": "tatoeba",
    "upstreamId": "761782"
  },
  {
    "text": "Това не мога да го повярвам!",
    "source": "tatoeba",
    "upstreamId": "761783"
  },
  {
    "text": "Това имаме, това обичаме.",
    "source": "tatoeba",
    "upstreamId": "761784"
  },
  {
    "text": "На покрива има един бял гълъб.",
    "source": "tatoeba",
    "upstreamId": "761786"
  },
  {
    "text": "Дадох му назаем едно списание.",
    "source": "tatoeba",
    "upstreamId": "761789"
  },
  {
    "text": "Щастлив е онзи мъж, който се ожени за добра жена.",
    "source": "tatoeba",
    "upstreamId": "761790"
  },
  {
    "text": "Не може да са излезли, защото вътре свети.",
    "source": "tatoeba",
    "upstreamId": "761792"
  },
  {
    "text": "Тя си сложи пуловера.",
    "source": "tatoeba",
    "upstreamId": "761793"
  },
  {
    "text": "Някои жени изглеждат по-скоро мъжествено, отколкото женствено.",
    "source": "tatoeba",
    "upstreamId": "761794"
  },
  {
    "text": "Използва ли фотоапарата ми?",
    "source": "tatoeba",
    "upstreamId": "761795"
  },
  {
    "text": "Той се сгоди за братовчедка ми.",
    "source": "tatoeba",
    "upstreamId": "761796"
  },
  {
    "text": "Тя има и пиано?",
    "source": "tatoeba",
    "upstreamId": "761797"
  },
  {
    "text": "Концертът започва в седем. Не трябва да закъсняваме.",
    "source": "tatoeba",
    "upstreamId": "761798"
  },
  {
    "text": "Стаята беше украсена с цветя за партито.",
    "source": "tatoeba",
    "upstreamId": "761799"
  },
  {
    "text": "Той обвини за катастрофата мен.",
    "source": "tatoeba",
    "upstreamId": "761802"
  },
  {
    "text": "Страстта му към него не стихва.",
    "source": "tatoeba",
    "upstreamId": "761803"
  },
  {
    "text": "Четенето е много полезно.",
    "source": "tatoeba",
    "upstreamId": "761804"
  },
  {
    "text": "Спах девет часа.",
    "source": "tatoeba",
    "upstreamId": "761805"
  },
  {
    "text": "Плановете ми за почивката се провалиха.",
    "source": "tatoeba",
    "upstreamId": "761806"
  },
  {
    "text": "Кметството е в центъра на града.",
    "source": "tatoeba",
    "upstreamId": "761807"
  },
  {
    "text": "Тази вечер е ужасно студено.",
    "source": "tatoeba",
    "upstreamId": "761812"
  },
  {
    "text": "Оборотът на Токийската борса достигна рекордно ниво за годината.",
    "source": "tatoeba",
    "upstreamId": "761815"
  },
  {
    "text": "Не забравяй да сложиш марка на писмото си.",
    "source": "tatoeba",
    "upstreamId": "761816"
  },
  {
    "text": "Трябва им някаква посока.",
    "source": "tatoeba",
    "upstreamId": "761817"
  },
  {
    "text": "Накратко, трябват ми пари. Би ли ми заел, ако обичаш?",
    "source": "tatoeba",
    "upstreamId": "761819"
  },
  {
    "text": "Беше му казано да се стане, и той така и направи.",
    "source": "tatoeba",
    "upstreamId": "761820"
  },
  {
    "text": "Има планове да се построи нова градска болница.",
    "source": "tatoeba",
    "upstreamId": "761821"
  },
  {
    "text": "Успях да го убедя за купуването на ново легло.",
    "source": "tatoeba",
    "upstreamId": "761823"
  },
  {
    "text": "Никое от старите дървета не оцеля след пожара.",
    "source": "tatoeba",
    "upstreamId": "761824"
  },
  {
    "text": "Лекарството го излекува от болестта му.",
    "source": "tatoeba",
    "upstreamId": "761825"
  },
  {
    "text": "Той е толкова прилежен, колкото човек изобщо може да бъде.",
    "source": "tatoeba",
    "upstreamId": "761826"
  },
  {
    "text": "Дж.Ф. Кенеди е погребан в гробищата в Арлингтън.",
    "source": "tatoeba",
    "upstreamId": "761827"
  },
  {
    "text": "Този политически проблем предизвика разгорещени дебати.",
    "source": "tatoeba",
    "upstreamId": "761828"
  },
  {
    "text": "Сиракът ридаеше заради нещастието си.",
    "source": "tatoeba",
    "upstreamId": "761829"
  },
  {
    "text": "Йошио по характер прилича на майка си, а по външност – на баща си.",
    "source": "tatoeba",
    "upstreamId": "761830"
  },
  {
    "text": "Знаеш ли как се кара кола?",
    "source": "tatoeba",
    "upstreamId": "761831"
  },
  {
    "text": "Спомням си събитията толкова живо, сякаш че беше вчера.",
    "source": "tatoeba",
    "upstreamId": "761832"
  },
  {
    "text": "Колкото повече работи човек, толкова повече му се работи.",
    "source": "tatoeba",
    "upstreamId": "761833"
  },
  {
    "text": "Тя му наготви вкусно ядене.",
    "source": "tatoeba",
    "upstreamId": "761834"
  },
  {
    "text": "С нея сме на една и съща възраст.",
    "source": "tatoeba",
    "upstreamId": "762168"
  },
  {
    "text": "Мислех, че ще се задуша в претъпкания влак.",
    "source": "tatoeba",
    "upstreamId": "762169"
  },
  {
    "text": "Какво е щастието?",
    "source": "tatoeba",
    "upstreamId": "762170"
  },
  {
    "text": "Той не искаше да те наранява.",
    "source": "tatoeba",
    "upstreamId": "762171"
  },
  {
    "text": "Той ще стане виден човек на изкуството.",
    "source": "tatoeba",
    "upstreamId": "762172"
  },
  {
    "text": "Ще ми кажете ли пътя до гарата?",
    "source": "tatoeba",
    "upstreamId": "762173"
  },
  {
    "text": "Ще започнеш да я харесваш.",
    "source": "tatoeba",
    "upstreamId": "762174"
  },
  {
    "text": "Примирих се със загубата.",
    "source": "tatoeba",
    "upstreamId": "762175"
  },
  {
    "text": "Джим завъртя ключа в ключалката.",
    "source": "tatoeba",
    "upstreamId": "762176"
  },
  {
    "text": "На никого досега не му се е удавало да избяга от съдбата.",
    "source": "tatoeba",
    "upstreamId": "762177"
  },
  {
    "text": "Ще ти помогна, колкото ми позволяват възможностите.",
    "source": "tatoeba",
    "upstreamId": "762178"
  },
  {
    "text": "Кога го свърши?",
    "source": "tatoeba",
    "upstreamId": "762179"
  },
  {
    "text": "Той ми даде пример.",
    "source": "tatoeba",
    "upstreamId": "762180"
  },
  {
    "text": "Той взе пари назаем при висока лихва.",
    "source": "tatoeba",
    "upstreamId": "762181"
  },
  {
    "text": "От вас няма повече полза.",
    "source": "tatoeba",
    "upstreamId": "762182"
  },
  {
    "text": "Ню Йорк е борсовият център на САЩ.",
    "source": "tatoeba",
    "upstreamId": "762183"
  },
  {
    "text": "Токийската фондова борса отбеляза силен ръст в края на деня.",
    "source": "tatoeba",
    "upstreamId": "762184"
  }
]
